Workbook
Name ввв: '[15]ОДТ и ГЦТ'!#REF!
Name Вес_коэфф_Доля_ОТА_ЮЛ: #REF!
Name Вес_коэфф_Доход_на_1_ОТА: #REF!
Name Вес_коэфф_Доход_на_1_ОТА_темп_роста: #REF!
Name Вес_коэфф_Доходы_темп_роста: #REF!
Name Вес_коэфф_Заявки: #REF!
Name Вес_коэфф_ОТА_темп_роста: #REF!
Name Вес_коэфф_Темп_прироста: #REF!
Name Вес_коэфф_Тлф_плотность: #REF!
Name Вес_коэфф_Трафик_темп_роста: #REF!
Name Вес_коэфф_Эксперт_оценка: #REF!
Name ГЦТ_Алматытелеком_Выдел.интернет: '[15]ОДТ и ГЦТ'!#REF!
Name ГЦТ_Алматытелеком_Выдел.интернет_2002: '[15]ОДТ и ГЦТ'!#REF!
Name ГЦТ_Алматытелеком_ADSL: '[15]ОДТ и ГЦТ'!#REF!
Name ГЦТ_Алматытелеком_ADSL_2002: '[15]ОДТ и ГЦТ'!#REF!
Name ГЦТ_Астанателеком_2002: '[15]ОДТ и ГЦТ'!#REF!
Name д: #REF!
Name ен: '[16]I. Прогноз доходов'!$F$31
Name Интернет_скоростя: [17]!Таблица1[#Data]
Name й: '[7]I. Прогноз доходов'!$F$31
Name ййй: #REF!
Name йййй: #REF!
Name ййййй: '[18]25. Hidden'!$C$40
Name йййййй: '[18]2. Inputs'!$D$22
Name Карагандинская_ОДТ_2002: '[15]ОДТ и ГЦТ'!#REF!
Name Макс_знач_Доля_ЮЛ: #REF!
Name Макс_знач_Доход_на_1_ОТА: #REF!
Name Макс_знач_Доход_на_1_ОТА_темп_роста: #REF!
Name Макс_знач_Доходы_темпы_роста: #REF!
Name Макс_знач_ОТА_темпы_роста: #REF!
Name Макс_знач_Ср_возраст_Мод: #REF!
Name Макс_знач_Ср_возраст_Разв: #REF!
Name Макс_знач_Тлф_плотность: #REF!
Name Макс_знач_Трафик_темпы_роста: #REF!
Name Менеджер: [19]!Таблица7[#Data]
Name Мин_знач_Доля_ЮЛ: #REF!
Name Мин_знач_Доход_на_1_ОТА: #REF!
Name Мин_знач_Доход_на_1_ОТА_темп_роста: #REF!
Name Мин_знач_Доходы_темпы_роста: #REF!
Name Мин_знач_ОТА_темпы_роста: #REF!
Name Мин_знач_Ср_возраст_Мод: #REF!
Name Мин_знач_Ср_возраст_Разв: #REF!
Name Мин_знач_Тлф_плотность: #REF!
Name мин_знач_Трафик_темпы_роста: #REF!
Name Мред_знач_Трафик_темпы_роста: #REF!
Name Нумерация: #REF!
Name Отар: #REF!
Name Отар_1: #REF!
Name Отар_2: #REF!
Name Подключение_Выдел.Интернет: '[15]ОДТ и ГЦТ'!#REF!
Name Подключение_ADSL: '[15]ОДТ и ГЦТ'!#REF!
Name Поставщики: #REF!
Name Рост_от_разблокировки: '[20]I. Прогноз доходов'!$F$32
Name Рост_от_цифровизации: '[20]I. Прогноз доходов'!$F$31
Name Рост_от_цифровизации_МСС: '[21]I. Прогноз доходов'!$F$32
Name С_Казахстанская_ОДТ_2002: '[15]ОДТ и ГЦТ'!#REF!
Name СВОД_ВПН1: #REF!
Name Скидка_на_подключение_ОТА: '[22]2.2.I. Прогноз доходов'!$F$30
Name Сред_знач_Доля_ЮЛ: #REF!
Name Сред_знач_Доход_на_1_ОТА: #REF!

Sheet ГУ Пункты пропуска
A1: №п/п | B1: Подразделение (центральное / областное) | C1: Наименование ГУ | D1: Физический адрес | E1: Из списка исходного СОИ | F1: Статус строительства ВОЛС | G1: Статус подключения | H1: Готовность ПСД | I1: КВЭП
A2: Завершены работы
A3: 1 | B3: ДГД по Актюбинской области | C3: ПУНКТ ПРОПУСКА «КАРАШАТАУ» | D3: Актюбинская область, Айтекебийский район, м/у п. Комсомол и п. Карашатау, 380 метров от ЛГГ | E3: Нет (новый) | F3: Завершен | G3: Наряд | H3: готов | I3: 46101
A4: 2 | B4: ДГД по Алматинской области | C4: ПУНКТ ПРОПУСКА «КЕГЕН» (АВТОМОБИЛЬНЫЙ) | D4: Алматинская область, Райымбекский район, 12 км от н.п.Каркара, 20 м от ЛГГ | E4: Да | F4: Завершен | G4: Наряд | H4: готов | I4: 46101
A5: 3 | B5: ДГД по Атырауской области | C5: ПУНКТ ПРОПУСКА «КУРМАНГАЗЫ» | D5: Атырауская область. Н.п.Караозек | E5: Нет (новый) | F5: Завершен | G5: Наряд | H5: готов | I5: 46101
A6: 4 | B6: ДГД по Жамбылской области | C6: ПУНКТ ПРОПУСКА «АЙША БИБИ» | D6: Жамбылская область, Жамбылский район село Гродеково | E6: Нет (новый) | F6: Завершен | G6: Подключен | H6: готов | I6: 46101
A7: 5 | B7: ДГД по ЗКО | C7: ПУНКТ ПРОПУСКА «ЖАНИБЕК» (АВТОМОБИЛЬНЫЙ) ЗКО | D7: п. Жанибек, Жанибекского сельского округа, Жанибекского района, 10 метров от ЛГГ | E7: Нет (новый) | F7: Завершен | G7: Наряд | H7: готов | I7: 46101
A8: 6 | B8: ДГД по ЗКО | C8: ПУНКТ ПРОПУСКА «АКСАЙ» (АВТОМОБИЛЬНЫЙ) ЗКО | D8: Бурлинский район от 9 км от н.п.Жарсуат, 150 м от ЛГГ | E8: Да | F8: Завершен | G8: Наряд | H8: готов | I8: 46101
A9: 7 | B9: ДГД по Карагандинской области | C9: Подразделение таможенного поста «Караганда-ЦТО» | D9: г. Караганда, ул. Сатпаева, 204, ТОО «СВХ Техносклад» | E9: Нет (новый) | F9: Завершен | G9: Подключен | H9: готов | I9: 46101
A10: 8 | B10: ДГД по Костанайской области | C10: ПУНКТ ПРОПУСКА «АКБАЛШИК» | D10: Костанайская область, 3 км от н.п. Белоглинка, Узынкольский р-н, 400 м от ЛГГ | E10: Нет (новый) | F10: Завершен | G10: Наряд | H10: готов | I10: 46101
A11: 9 | B11: ДГД по Костанайской области | C11: ПУНКТ ПРОПУСКА «АЯТ» | D11: Костанайская область, в 500 м. от н.п. Варваринка, Тарановского района, 4500 м от ЛГГ | E11: Нет (новый) | F11: Завершен | G11: Наряд | H11: готов | I11: 46101
A12: 10 | B12: ДГД по Мангистауской области | C12: Таможенный пост «Кара Шекпен» | D12: Мангистауская обл.,Тупкараганский район, п. Баутино, ул. Мунайши 2 | E12: Да | F12: Завершен | G12: Подключен | H12: готов | I12: 46101
A13: 11 | B13: ДГД по области Абай | C13: ПУНКТ ПРОПУСКА «ЖЕЗКЕНТ» (АВТОМОБИЛЬНЫЙ) | D13: Бородулихинский р-н, с. Жезкент, 1500м от ЛГГ | E13: Нет (новый) | F13: Завершен | G13: Наряд | H13: готов | I13: 46101
A14: 12 | B14: ДГД по Павлодарской области | C14: ПУНКТ ПРОПУСКА «УРЛИТОБЕ» | D14: Павлодарская область, на автомагистрали Павлодар-Омск, 220 км от г. Павлодар | E14: Нет (новый) | F14: Завершен | G14: Наряд | H14: готов | I14: 46101
... A18: 16 | B18: ДГД по СКО | C18: Таможенный пост «Петропавловск-Центр таможенного оформления» | D18: СКО, г. Петропавловск, ул. Мухтара Ауэзова, 297 | E18: Нет (новый) | F18: Завершен | G18: Подключен | H18: готов, без коммуникации | I18: 46101
A19: 17 | B19: ДГД по СКО | C19: ДГД по СКО | D19: СКО, г. Петропавловск, ул. Лесная 67 (ЖД пункт пропуска УЭК) | H19: готов | I19: 46101
A20: 18 | B20: ДГД по области Жетысу | C20: ТП Талдыкорган | D20: Область Жетысу,Талдыкорган ул. Жансугурова 111 | E20: Нет (новый) | F20: 46081 | G20: собственными силами
A22: В производстве
A23: 19 | B23: ДГД по Актюбинской области | C23: ПУНКТ ПРОПУСКА «АЛИМБЕТ» | D23: Актюбинская обл, Карагалинский район 12 км от пос. Алимбетовка | E23: Нет (новый) | F23: 46081 | G23: 46094 | H23: готов | I23: 46101
A24: 20 | B24: ДГД по Жамбылской области | C24: ПУНКТ ПРОПУСКА «Аухатты» | D24: Жамбылская область, Кордайский р-н, н.п. Аухатты, РУМПП "Оңтүстік", | E24: Нет (новый) | F24: 46081 | G24: 46085 | H24: готов, без коммуникации | I24: 46101
A25: 21 | B25: ДГД по Кызылординской области | C25: Таможенный пост «Байконыр» | D25: г. Байконыр, ул. Максимова, 8 | E25: Нет (новый) | F25: 46081 | G25: 46087 | H25: Ожидаем ТУ на прокладку по сущ тел канализации | I25: 46101
A26: 22 | B26: ДГД по Туркестанской области | C26: Таможенный пост «Туркестан Центр таможенного оформления» в г. Арыс | D26: г.Арыс ул.Шпал зауыты, участок 2084, на территории СВХ ТОО «Акжол Транс Трейд» | G26: 46094 | H26: готов | I26: 46101
E27: Нет (новый) | F27: 46096
A28: В производстве со сроком завершения СМР 15.04.2026 г.
A29: 23 | B29: ДГД по Костанайской области | C29: ПУНКТ ПРОПУСКА «КАЙРАК» | D29: Костанайская область, на 927 км автодороги М36 Астана-Екатеринбург, 500 м от ЛГГ | E29: Нет (новый) | F29: 46127 | G29: 46127 | H29: готов, без коммуникации | I29: 46171
A30: 24 | B30: ДГД по Костанайской области | C30: ПУНКТ ПРОПУСКА «КОНДЫБАЙ» | D30: Костанайская область, в 90 км. от г. Житикара, Житикаринского района, 350 м от ЛГГ | E30: Нет (новый) | F30: 46127 | G30: 46127 | H30: готов, без коммуникации | I30: 46171
A31: 25 | B31: ДГД по Костанайской области | C31: ПУНКТ ПРОПУСКА «ЖЕЛКУАР» | D31: Костанайская область, Житикаринский район, г. Житикара, 800 м от ЛГГ | E31: Нет (новый) | F31: 46127 | G31: 46127 | H31: готов, без коммуникации | I31: 46171
A32: 26 | B32: ДГД по Костанайской области | C32: ПУНКТ ПРОПУСКА «УБАГАН» | D32: Костанайская область, в 6 км. от п. Убаган, Узункольского района, 700 м от ЛГГ | E32: Нет (новый) | F32: 46127 | G32: 46127 | H32: готов, без коммуникации | I32: 46171
A33: 27 | B33: ДГД по области Абай | C33: ПУНКТ ПРОПУСКА «АУЫЛ» (АВТОМОБИЛЬНЫЙ) ВКО | D33: Бородулихинский р-н, станции Аул | E33: Да | F33: 46188 | G33: 46188 | H33: готов, без коммуникации | I33: 46171
A34: 28 | B34: ДГД по области Абай | C34: ПУНКТ ПРОПУСКА «КОЯНБАЙ» (АВТОМОБИЛЬНЫЙ) ВКО | D34: Бескарагайского р-не в 14 км от населенного пункта Коянбай, 200 м от ЛГГ | E34: Да | F34: 46188 | G34: 46188 | H34: готов, без коммуникации | I34: 46171
A35: 29 | B35: ДГД по области Абай | C35: ПУНКТ ПРОПУСКА «БАЙТАНАТ» (АВТОМОБИЛЬНЫЙ) ВКО | D35: Бородулихинский р-н, с. Байтанат, 12 км от ЛГГ | E35: Нет (новый) | F35: 46127 | G35: 46127 | H35: готов, без коммуникации | I35: 46171
A36: 30 | B36: ДГД по Павлодарской области | C36: ПУНКТ ПРОПУСКА «АМАНГЕЛЬДЫ» (АВТОМОБИЛЬНЫЙ) | D36: Павлодарская область, на автомагистрали Павлодар-Омск, 320 км от г. Павлодар | E36: Нет (новый) | F36: 46127 | G36: 46127 | H36: готов, без коммуникации | I36: 46171
A37: 31 | B37: ДГД по СКО | C37: ПУНКТ ПРОПУСКА «КЫЗЫЛЖАР» | D37: Кызылжарский район, 3 км от н.п. Красный Яр, 83 км от г. Петропавловск, 500 м от ЛГГ | E37: Нет (новый) | F37: 46127 | G37: 46127 | H37: готов, без коммуникации | I37: 46171
A38: 32 | B38: ДГД по СКО | C38: ПУНКТ ПРОПУСКА «БИДАИК» | D38: Ч.Уалихановский район 11 км от село Бидаик, 20 м от ЛГГ | E38: Нет (новый) | F38: 46127 | G38: 46127 | H38: готов, без коммуникации | I38: 46171
A39: 33 | B39: ДГД по СКО | C39: ПУНКТ ПРОПУСКА «ЖАНАЖОЛ» | D39: Мамлютский район село Чистое, 640 м от ЛГГ | E39: Нет (новый) | F39: 46127 | G39: 46127 | H39: готов, без коммуникации | I39: 46171
A40: 34 | B40: ДГД по СКО | C40: ПУНКТ ПРОПУСКА «ЖАНАЖОЛ» 2 | D40: Мамлютский район село Чистое, 640 м от ЛГГ Здание 2 | E40: Нет (новый) | F40: 46127 | G40: 46127 | H40: готов, без коммуникации | I40: 46171
A41: 35 | B41: ДГД по Атырауской области | C41: Таможенный пост "Тенгиз" | D41: Атырауская обл., Жылыойский район, гор. Кульсары, промзона Тенгизшевройл | E41: Нет (новый) | F41: 46096 | G41: 46096 | H41: готов, без коммуникации | I41: 46171
A42: 36 | B42: ДГД по Актюбинской области | C42: ПУНКТ ПРОПУСКА «ЖАЙСАН» | D42: Актюбинская область, Мартукский район, п. Жайсан, 5 метров от ЛГГ | G42: 46111 | H42: готов, без коммуникации | I42: 46171
A43: 37 | B43: ДГД по ВКО | C43: ПУНКТ ПРОПУСКА «УБА» (АВТОМОБИЛЬНЫЙ) | D43: н.п. Шемонаиха | G43: 46172 | H43: готов, без коммуникации | I43: 46171
A44: 38 | B44: ДГД по Актюбинской области | C44: Таможенный пост «Эмбi» | D44: Мугалжарский район, новая база УПТО и КО АО «СНПС-Актобемунайгаз» месторождение «Жанажол» | G44: 46111 | H44: готов, без коммуникации | I44: 46171

Sheet ПИР-ПСД
I1: Исходно-разрешительные документы | T1: Инженерные изыскания | Y1: Проектирование | AH1: Согласования | BC1: Землеустроительные работы | BH1: Экспертиза проекта | BJ1: Итоги
A2: Номер Заказа | B2: ПИР год реализации | C2: Подрядчик | D2: КАТО | E2: Область | F2: Район | G2: Сельский округ | H2: СНП | I2: Акт выбора трасс | K2: АПЗ | M2: Технические условия на подключение | O2: Постановление о разрешении на ПИР | Q2: Технические условия на пересечение | S2: Общий статус выполнения, % | T2: Инженерно геологические изыскания | V2: Инженерно-геодезические изыскания | X2: Общий статус выполнения, % | Y2: Рабочие чертежи | AA2: Сметная документация | AC2: Проект организации строительства | AE2: Экологическая часть проекта | AG2: Общий статус выполнения, % | AH2: Заключение историко-культурной экспертизы | AJ2: Письмо об отсутствии сибиреязвенных захоронений и скотомогильников | AL2: Протокол дозиметрического контроля | AN2: Протокол измерений содержания радона и продуктов его распада в воздухе | AP2: Согласование трассы ВОЛС с соответствующей Бассейновой водохозяйственной инспекцией | AR2: Согласование с АО "Авиационная администрация Казахстана" | AT2: Согласование трассы ВОЛС с местным Лесхозом | AV2: Согласование с владельцами пересекаемых коммуникаций | AX2: Согласование экологической части проекта | AZ2: Согласование проекта с Заказчиком | BB2: Общий статус выполнения, % | BC2: Землеотвод под ВОЛС (постановление, гос акт. серветут, распоряжение) | BE2: Изготовление землеустроительного проекта | BG2: Общий статус выполнения, % | BH2: Комплексная вневедомственная экспертиза проекта | BJ2: Проектная протяженность трассы ВОЛС после экспертизы, м | BK2: Плановая дата завершения проекта | BL2: Суммарная готовность (%)
I3: Информация | J3: да/нет | K3: Информация | L3: да/нет | M3: Информация | N3: да/нет | O3: Информация | P3: да/нет | Q3: Информация | R3: да/нет | T3: Информация | U3: да/нет | V3: Информация | W3: да/нет | Y3: Информация | Z3: % | AA3: Информация | AB3: % | AC3: Информация | AD3: да/нет | AE3: Информация | AF3: да/нет | AH3: Информация | AI3: да/нет | AJ3: Информация | AK3: да/нет | AL3: Информация | AM3: да/нет | AN3: Информация | AO3: да/нет | AP3: Информация | AQ3: да/нет | AR3: Информация | AS3: да/нет | AT3: Информация | AU3: да/нет | AV3: Информация | AW3: да/нет | AX3: Информация | AY3: да/нет | AZ3: Информация | BA3: да/нет | BC3: Информация | BD3: да/нет | BE3: Информация | BF3: да/нет | BH3: Информация | BI3: %
B4: 2026 | C4: ТОО "5А Engineering" | D4: 113241200 | E4: Акмолинская область | F4: Аккольский район | G4: Карасайский с.о. | H4: с.Карасай | I4: Имеется | J4: 1 | K4: на стадии подготовки | L4: 0.25 | M4: на стадии подготовки | N4: 0 | O4: на стадии подготовки | P4: 0 | Q4: на стадии подготовки | R4: 0 | S4: =(J4*'"Вес" ПИР'!$B$13+L4*'"Вес" ПИР'!$B$14+N4*'"Вес" ПИР'!$B$15+P4*'"Вес" ПИР'!$B$16+R4*'"Вес" ПИР'!$B$17)/100 -> 0.125 | T4: Готово | U4: 1 | V4: Готово | W4: 1 | X4: =(U4*'"Вес" ПИР'!$B$22+W4*'"Вес" ПИР'!$B$23)/100 -> 1 | Z4: 0.1 | AB4: 0 | AD4: 0 | AF4: 0 | AG4: =(Z4*'"Вес" ПИР'!$B$28+AB4*'"Вес" ПИР'!$B$29+AD4*'"Вес" ПИР'!$B$30+AF4*'"Вес" ПИР'!$B$31)/100 -> 0.075 | AJ4: на стадии подготовки | AP4: на стадии подготовки | AR4: на стадии подготовки | AT4: на стадии подготовки | BB4: =(AI4*'"Вес" ПИР'!$B$36+AK4*'"Вес" ПИР'!$B$37+AM4*'"Вес" ПИР'!$B$38+AO4*'"Вес" ПИР'!$B$39+AQ4*'"Вес" ПИР'!$B$40+AS4*'"Вес" ПИР'!$B$41+AU4*'"Вес" ПИР'!$B$42+AW4*'"Вес" ПИР'!$B$43+AY4*'"Вес" ПИР'!$B$44+BA4*'"Вес" ПИР'!$B$45)/100 -> 0 | BC4: на стадии подготовки | BE4: на стадии подготовки | BG4: =(BD4*'"Вес" ПИР'!$B$50+BF4*'"Вес" ПИР'!$B$51)/100 -> 0 | BI4: 0 | BK4: 46218 | BL4: =(S4*'"Вес" ПИР'!$B$3+X4*'"Вес" ПИР'!$B$4+AG4*'"Вес" ПИР'!$B$5+BB4*'"Вес" ПИР'!$B$6+BG4*'"Вес" ПИР'!$B$7+BI4*'"Вес" ПИР'!$B$8)/100 -> 0.1875
B5: 2026 | C5: ТОО "5А Engineering" | D5: 113241100 | E5: Акмолинская область | F5: Аккольский район | G5: Карасайский с.о. | H5: с.Кына | I5: Имеется | J5: 1 | K5: на стадии подготовки | M5: на стадии подготовки | O5: на стадии подготовки | Q5: на стадии подготовки | S5: =(J5*'"Вес" ПИР'!$B$13+L5*'"Вес" ПИР'!$B$14+N5*'"Вес" ПИР'!$B$15+P5*'"Вес" ПИР'!$B$16+R5*'"Вес" ПИР'!$B$17)/100 -> 0.05 | T5: Готово | V5: Готово | X5: =(U5*'"Вес" ПИР'!$B$22+W5*'"Вес" ПИР'!$B$23)/100 -> 0 | AG5: =(Z5*'"Вес" ПИР'!$B$28+AB5*'"Вес" ПИР'!$B$29+AD5*'"Вес" ПИР'!$B$30+AF5*'"Вес" ПИР'!$B$31)/100 -> 0 | AJ5: на стадии подготовки | AP5: на стадии подготовки | AR5: на стадии подготовки | AT5: на стадии подготовки | BB5: =(AI5*'"Вес" ПИР'!$B$36+AK5*'"Вес" ПИР'!$B$37+AM5*'"Вес" ПИР'!$B$38+AO5*'"Вес" ПИР'!$B$39+AQ5*'"Вес" ПИР'!$B$40+AS5*'"Вес" ПИР'!$B$41+AU5*'"Вес" ПИР'!$B$42+AW5*'"Вес" ПИР'!$B$43+AY5*'"Вес" ПИР'!$B$44+BA5*'"Вес" ПИР'!$B$45)/100 -> 0 | BC5: на стадии подготовки | BE5: на стадии подготовки | BG5: =(BD5*'"Вес" ПИР'!$B$50+BF5*'"Вес" ПИР'!$B$51)/100 -> 0 | BI5: 0 | BK5: 46218 | BL5: =(S5*'"Вес" ПИР'!$B$3+X5*'"Вес" ПИР'!$B$4+AG5*'"Вес" ПИР'!$B$5+BB5*'"Вес" ПИР'!$B$6+BG5*'"Вес" ПИР'!$B$7+BI5*'"Вес" ПИР'!$B$8)/100 -> 0.00375
B6: 2026 | C6: ТОО "5А Engineering" | D6: 113241300 | E6: Акмолинская область | F6: Аккольский район | G6: Карасайский с.о. | H6: с.Сазды булак | I6: Имеется | J6: 1 | K6: на стадии подготовки | M6: на стадии подготовки | O6: на стадии подготовки | Q6: на стадии подготовки | S6: =(J6*'"Вес" ПИР'!$B$13+L6*'"Вес" ПИР'!$B$14+N6*'"Вес" ПИР'!$B$15+P6*'"Вес" ПИР'!$B$16+R6*'"Вес" ПИР'!$B$17)/100 -> 0.05 | T6: Готово | V6: Готово | X6: =(U6*'"Вес" ПИР'!$B$22+W6*'"Вес" ПИР'!$B$23)/100 -> 0 | AG6: =(Z6*'"Вес" ПИР'!$B$28+AB6*'"Вес" ПИР'!$B$29+AD6*'"Вес" ПИР'!$B$30+AF6*'"Вес" ПИР'!$B$31)/100 -> 0 | AJ6: на стадии подготовки | AP6: на стадии подготовки | AR6: на стадии подготовки | AT6: на стадии подготовки | BB6: =(AI6*'"Вес" ПИР'!$B$36+AK6*'"Вес" ПИР'!$B$37+AM6*'"Вес" ПИР'!$B$38+AO6*'"Вес" ПИР'!$B$39+AQ6*'"Вес" ПИР'!$B$40+AS6*'"Вес" ПИР'!$B$41+AU6*'"Вес" ПИР'!$B$42+AW6*'"Вес" ПИР'!$B$43+AY6*'"Вес" ПИР'!$B$44+BA6*'"Вес" ПИР'!$B$45)/100 -> 0 | BC6: на стадии подготовки | BE6: на стадии подготовки | BG6: =(BD6*'"Вес" ПИР'!$B$50+BF6*'"Вес" ПИР'!$B$51)/100 -> 0 | BI6: 0 | BK6: 46218 | BL6: =(S6*'"Вес" ПИР'!$B$3+X6*'"Вес" ПИР'!$B$4+AG6*'"Вес" ПИР'!$B$5+BB6*'"Вес" ПИР'!$B$6+BG6*'"Вес" ПИР'!$B$7+BI6*'"Вес" ПИР'!$B$8)/100 -> 0.00375
B7: 2026 | C7: ТОО "5А Engineering" | D7: 113247300 | E7: Акмолинская область | F7: Аккольский район | G7: Наумовский с.о. | H7: с.Орнек | I7: Имеется | J7: 1 | K7: на стадии подготовки | M7: на стадии подготовки | O7: на стадии подготовки | Q7: на стадии подготовки | S7: =(J7*'"Вес" ПИР'!$B$13+L7*'"Вес" ПИР'!$B$14+N7*'"Вес" ПИР'!$B$15+P7*'"Вес" ПИР'!$B$16+R7*'"Вес" ПИР'!$B$17)/100 -> 0.05 | T7: Готово | V7: Готово | X7: =(U7*'"Вес" ПИР'!$B$22+W7*'"Вес" ПИР'!$B$23)/100 -> 0 | AG7: =(Z7*'"Вес" ПИР'!$B$28+AB7*'"Вес" ПИР'!$B$29+AD7*'"Вес" ПИР'!$B$30+AF7*'"Вес" ПИР'!$B$31)/100 -> 0 | AJ7: на стадии подготовки | AP7: на стадии подготовки | AR7: на стадии подготовки | AT7: на стадии подготовки | BB7: =(AI7*'"Вес" ПИР'!$B$36+AK7*'"Вес" ПИР'!$B$37+AM7*'"Вес" ПИР'!$B$38+AO7*'"Вес" ПИР'!$B$39+AQ7*'"Вес" ПИР'!$B$40+AS7*'"Вес" ПИР'!$B$41+AU7*'"Вес" ПИР'!$B$42+AW7*'"Вес" ПИР'!$B$43+AY7*'"Вес" ПИР'!$B$44+BA7*'"Вес" ПИР'!$B$45)/100 -> 0 | BC7: на стадии подготовки | BE7: на стадии подготовки | BG7: =(BD7*'"Вес" ПИР'!$B$50+BF7*'"Вес" ПИР'!$B$51)/100 -> 0 | BI7: 0 | BK7: 46218 | BL7: =(S7*'"Вес" ПИР'!$B$3+X7*'"Вес" ПИР'!$B$4+AG7*'"Вес" ПИР'!$B$5+BB7*'"Вес" ПИР'!$B$6+BG7*'"Вес" ПИР'!$B$7+BI7*'"Вес" ПИР'!$B$8)/100 -> 0.00375
B8: 2026 | C8: ТОО "5А Engineering" | D8: 113451100 | E8: Акмолинская область | F8: Аршалынский район | G8: Булаксайский с.о. | H8: с.Булаксай | I8: Имеется | J8: 1 | K8: на стадии подготовки | M8: на стадии подготовки | O8: на стадии подготовки | Q8: на стадии подготовки | S8: =(J8*'"Вес" ПИР'!$B$13+L8*'"Вес" ПИР'!$B$14+N8*'"Вес" ПИР'!$B$15+P8*'"Вес" ПИР'!$B$16+R8*'"Вес" ПИР'!$B$17)/100 -> 0.05 | T8: 01.12.2025-30.03.2026 | V8: 01.12.2025-30.03.2026 | X8: =(U8*'"Вес" ПИР'!$B$22+W8*'"Вес" ПИР'!$B$23)/100 -> 0 | AG8: =(Z8*'"Вес" ПИР'!$B$28+AB8*'"Вес" ПИР'!$B$29+AD8*'"Вес" ПИР'!$B$30+AF8*'"Вес" ПИР'!$B$31)/100 -> 0 | AJ8: на стадии подготовки | AP8: на стадии подготовки | AR8: на стадии подготовки | AT8: на стадии подготовки | BB8: =(AI8*'"Вес" ПИР'!$B$36+AK8*'"Вес" ПИР'!$B$37+AM8*'"Вес" ПИР'!$B$38+AO8*'"Вес" ПИР'!$B$39+AQ8*'"Вес" ПИР'!$B$40+AS8*'"Вес" ПИР'!$B$41+AU8*'"Вес" ПИР'!$B$42+AW8*'"Вес" ПИР'!$B$43+AY8*'"Вес" ПИР'!$B$44+BA8*'"Вес" ПИР'!$B$45)/100 -> 0 | BC8: на стадии подготовки | BE8: на стадии подготовки | BG8: =(BD8*'"Вес" ПИР'!$B$50+BF8*'"Вес" ПИР'!$B$51)/100 -> 0 | BI8: 0 | BK8: 46266 | BL8: =(S8*'"Вес" ПИР'!$B$3+X8*'"Вес" ПИР'!$B$4+AG8*'"Вес" ПИР'!$B$5+BB8*'"Вес" ПИР'!$B$6+BG8*'"Вес" ПИР'!$B$7+BI8*'"Вес" ПИР'!$B$8)/100 -> 0.00375
B9: 2026 | C9: ТОО "5А Engineering" | D9: 113453100 | E9: Акмолинская область | F9: Аршалынский район | G9: Сарабинский с.о. | H9: с.Сарыоба | I9: Имеется | J9: 1 | K9: на стадии подготовки | M9: на стадии подготовки | O9: на стадии подготовки | Q9: на стадии подготовки | S9: =(J9*'"Вес" ПИР'!$B$13+L9*'"Вес" ПИР'!$B$14+N9*'"Вес" ПИР'!$B$15+P9*'"Вес" ПИР'!$B$16+R9*'"Вес" ПИР'!$B$17)/100 -> 0.05 | T9: 01.12.2025-30.03.2026 | V9: 01.12.2025-30.03.2026 | X9: =(U9*'"Вес" ПИР'!$B$22+W9*'"Вес" ПИР'!$B$23)/100 -> 0 | AG9: =(Z9*'"Вес" ПИР'!$B$28+AB9*'"Вес" ПИР'!$B$29+AD9*'"Вес" ПИР'!$B$30+AF9*'"Вес" ПИР'!$B$31)/100 -> 0 | AJ9: на стадии подготовки | AP9: на стадии подготовки | AR9: на стадии подготовки | AT9: на стадии подготовки | BB9: =(AI9*'"Вес" ПИР'!$B$36+AK9*'"Вес" ПИР'!$B$37+AM9*'"Вес" ПИР'!$B$38+AO9*'"Вес" ПИР'!$B$39+AQ9*'"Вес" ПИР'!$B$40+AS9*'"Вес" ПИР'!$B$41+AU9*'"Вес" ПИР'!$B$42+AW9*'"Вес" ПИР'!$B$43+AY9*'"Вес" ПИР'!$B$44+BA9*'"Вес" ПИР'!$B$45)/100 -> 0 | BC9: на стадии подготовки | BE9: на стадии подготовки | BG9: =(BD9*'"Вес" ПИР'!$B$50+BF9*'"Вес" ПИР'!$B$51)/100 -> 0 | BI9: 0 | BK9: 46266 | BL9: =(S9*'"Вес" ПИР'!$B$3+X9*'"Вес" ПИР'!$B$4+AG9*'"Вес" ПИР'!$B$5+BB9*'"Вес" ПИР'!$B$6+BG9*'"Вес" ПИР'!$B$7+BI9*'"Вес" ПИР'!$B$8)/100 -> 0.00375
B10: 2026 | C10: ТОО "5А Engineering" | D10: 113453500 | E10: Акмолинская область | F10: Аршалынский район | G10: Сарабинский с.о. | H10: ст.Сарыоба | I10: Имеется | J10: 1 | K10: на стадии подготовки | M10: на стадии подготовки | O10: на стадии подготовки | Q10: на стадии подготовки | S10: =(J10*'"Вес" ПИР'!$B$13+L10*'"Вес" ПИР'!$B$14+N10*'"Вес" ПИР'!$B$15+P10*'"Вес" ПИР'!$B$16+R10*'"Вес" ПИР'!$B$17)/100 -> 0.05 | T10: 01.12.2025-30.03.2026 | V10: 01.12.2025-30.03.2026 | X10: =(U10*'"Вес" ПИР'!$B$22+W10*'"Вес" ПИР'!$B$23)/100 -> 0 | AG10: =(Z10*'"Вес" ПИР'!$B$28+AB10*'"Вес" ПИР'!$B$29+AD10*'"Вес" ПИР'!$B$30+AF10*'"Вес" ПИР'!$B$31)/100 -> 0 | AJ10: на стадии подготовки | AP10: на стадии подготовки | AR10: на стадии подготовки | AT10: на стадии подготовки | BB10: =(AI10*'"Вес" ПИР'!$B$36+AK10*'"Вес" ПИР'!$B$37+AM10*'"Вес" ПИР'!$B$38+AO10*'"Вес" ПИР'!$B$39+AQ10*'"Вес" ПИР'!$B$40+AS10*'"Вес" ПИР'!$B$41+AU10*'"Вес" ПИР'!$B$42+AW10*'"Вес" ПИР'!$B$43+AY10*'"Вес" ПИР'!$B$44+BA10*'"Вес" ПИР'!$B$45)/100 -> 0 | BC10: на стадии подготовки | BE10: на стадии подготовки | BG10: =(BD10*'"Вес" ПИР'!$B$50+BF10*'"Вес" ПИР'!$B$51)/100 -> 0 | BI10: 0 | BK10: 46266 | BL10: =(S10*'"Вес" ПИР'!$B$3+X10*'"Вес" ПИР'!$B$4+AG10*'"Вес" ПИР'!$B$5+BB10*'"Вес" ПИР'!$B$6+BG10*'"Вес" ПИР'!$B$7+BI10*'"Вес" ПИР'!$B$8)/100 -> 0.00375
B11: 2026 | C11: ТОО "5А Engineering" | D11: 113651100 | E11: Акмолинская область | F11: Астраханский район | G11: Острогорский с.о. | H11: с.Новый Колутон | I11: Имеется | J11: 1 | K11: на стадии подготовки | M11: на стадии подготовки | O11: на стадии подготовки | Q11: на стадии подготовки | S11: =(J11*'"Вес" ПИР'!$B$13+L11*'"Вес" ПИР'!$B$14+N11*'"Вес" ПИР'!$B$15+P11*'"Вес" ПИР'!$B$16+R11*'"Вес" ПИР'!$B$17)/100 -> 0.05 | T11: 01.12.2025-30.03.2026 | V11: 01.12.2025-30.03.2026 | X11: =(U11*'"Вес" ПИР'!$B$22+W11*'"Вес" ПИР'!$B$23)/100 -> 0 | AG11: =(Z11*'"Вес" ПИР'!$B$28+AB11*'"Вес" ПИР'!$B$29+AD11*'"Вес" ПИР'!$B$30+AF11*'"Вес" ПИР'!$B$31)/100 -> 0 | AJ11: на стадии подготовки | AP11: на стадии подготовки | AR11: на стадии подготовки | AT11: на стадии подготовки | BB11: =(AI11*'"Вес" ПИР'!$B$36+AK11*'"Вес" ПИР'!$B$37+AM11*'"Вес" ПИР'!$B$38+AO11*'"Вес" ПИР'!$B$39+AQ11*'"Вес" ПИР'!$B$40+AS11*'"Вес" ПИР'!$B$41+AU11*'"Вес" ПИР'!$B$42+AW11*'"Вес" ПИР'!$B$43+AY11*'"Вес" ПИР'!$B$44+BA11*'"Вес" ПИР'!$B$45)/100 -> 0 | BC11: на стадии подготовки | BE11: на стадии подготовки | BG11: =(BD11*'"Вес" ПИР'!$B$50+BF11*'"Вес" ПИР'!$B$51)/100 -> 0 | BI11: 0 | BK11: 46266 | BL11: =(S11*'"Вес" ПИР'!$B$3+X11*'"Вес" ПИР'!$B$4+AG11*'"Вес" ПИР'!$B$5+BB11*'"Вес" ПИР'!$B$6+BG11*'"Вес" ПИР'!$B$7+BI11*'"Вес" ПИР'!$B$8)/100 -> 0.00375
B12: 2026 | C12: ТОО "5А Engineering" | D12: 114655300 | E12: Акмолинская область | F12: Ерейментауский район | G12: Еркиншиликский с.о. | H12: с.Енбек | I12: Имеется | J12: 1 | K12: на стадии подготовки | M12: на стадии подготовки | O12: на стадии подготовки | Q12: на стадии подготовки | S12: =(J12*'"Вес" ПИР'!$B$13+L12*'"Вес" ПИР'!$B$14+N12*'"Вес" ПИР'!$B$15+P12*'"Вес" ПИР'!$B$16+R12*'"Вес" ПИР'!$B$17)/100 -> 0.05 | T12: Готово | V12: Готово | X12: =(U12*'"Вес" ПИР'!$B$22+W12*'"Вес" ПИР'!$B$23)/100 -> 0 | AG12: =(Z12*'"Вес" ПИР'!$B$28+AB12*'"Вес" ПИР'!$B$29+AD12*'"Вес" ПИР'!$B$30+AF12*'"Вес" ПИР'!$B$31)/100 -> 0 | AJ12: на стадии подготовки | AP12: на стадии подготовки | AR12: на стадии подготовки | AT12: на стадии подготовки | BB12: =(AI12*'"Вес" ПИР'!$B$36+AK12*'"Вес" ПИР'!$B$37+AM12*'"Вес" ПИР'!$B$38+AO12*'"Вес" ПИР'!$B$39+AQ12*'"Вес" ПИР'!$B$40+AS12*'"Вес" ПИР'!$B$41+AU12*'"Вес" ПИР'!$B$42+AW12*'"Вес" ПИР'!$B$43+AY12*'"Вес" ПИР'!$B$44+BA12*'"Вес" ПИР'!$B$45)/100 -> 0 | BC12: на стадии подготовки | BE12: на стадии подготовки | BG12: =(BD12*'"Вес" ПИР'!$B$50+BF12*'"Вес" ПИР'!$B$51)/100 -> 0 | BI12: 0 | BK12: 46218 | BL12: =(S12*'"Вес" ПИР'!$B$3+X12*'"Вес" ПИР'!$B$4+AG12*'"Вес" ПИР'!$B$5+BB12*'"Вес" ПИР'!$B$6+BG12*'"Вес" ПИР'!$B$7+BI12*'"Вес" ПИР'!$B$8)/100 -> 0.00375
B13: 2026 | C13: ТОО "5А Engineering" | D13: 114639100 | E13: Акмолинская область | F13: Ерейментауский район | G13: с.Бозтал | H13: с.Бозтал | I13: Имеется | J13: 1 | K13: на стадии подготовки | M13: на стадии подготовки | O13: на стадии подготовки | Q13: на стадии подготовки | S13: =(J13*'"Вес" ПИР'!$B$13+L13*'"Вес" ПИР'!$B$14+N13*'"Вес" ПИР'!$B$15+P13*'"Вес" ПИР'!$B$16+R13*'"Вес" ПИР'!$B$17)/100 -> 0.05 | T13: Готово | V13: Готово | X13: =(U13*'"Вес" ПИР'!$B$22+W13*'"Вес" ПИР'!$B$23)/100 -> 0 | AG13: =(Z13*'"Вес" ПИР'!$B$28+AB13*'"Вес" ПИР'!$B$29+AD13*'"Вес" ПИР'!$B$30+AF13*'"Вес" ПИР'!$B$31)/100 -> 0 | AJ13: на стадии подготовки | AP13: на стадии подготовки | AR13: на стадии подготовки | AT13: на стадии подготовки | BB13: =(AI13*'"Вес" ПИР'!$B$36+AK13*'"Вес" ПИР'!$B$37+AM13*'"Вес" ПИР'!$B$38+AO13*'"Вес" ПИР'!$B$39+AQ13*'"Вес" ПИР'!$B$40+AS13*'"Вес" ПИР'!$B$41+AU13*'"Вес" ПИР'!$B$42+AW13*'"Вес" ПИР'!$B$43+AY13*'"Вес" ПИР'!$B$44+BA13*'"Вес" ПИР'!$B$45)/100 -> 0 | BC13: на стадии подготовки | BE13: на стадии подготовки | BG13: =(BD13*'"Вес" ПИР'!$B$50+BF13*'"Вес" ПИР'!$B$51)/100 -> 0 | BI13: 0 | BK13: 46218 | BL13: =(S13*'"Вес" ПИР'!$B$3+X13*'"Вес" ПИР'!$B$4+AG13*'"Вес" ПИР'!$B$5+BB13*'"Вес" ПИР'!$B$6+BG13*'"Вес" ПИР'!$B$7+BI13*'"Вес" ПИР'!$B$8)/100 -> 0.00375
B14: 2026 | C14: ТОО "5А Engineering" | D14: 114837300 | E14: Акмолинская область | F14: Есильский район | G14: Бузулукский с.о. | H14: с.Сурган | I14: Имеется | J14: 1 | K14: на стадии подготовки | M14: на стадии подготовки | O14: на стадии подготовки | Q14: на стадии подготовки | S14: =(J14*'"Вес" ПИР'!$B$13+L14*'"Вес" ПИР'!$B$14+N14*'"Вес" ПИР'!$B$15+P14*'"Вес" ПИР'!$B$16+R14*'"Вес" ПИР'!$B$17)/100 -> 0.05 | T14: Готово | V14: Готово | X14: =(U14*'"Вес" ПИР'!$B$22+W14*'"Вес" ПИР'!$B$23)/100 -> 0 | AG14: =(Z14*'"Вес" ПИР'!$B$28+AB14*'"Вес" ПИР'!$B$29+AD14*'"Вес" ПИР'!$B$30+AF14*'"Вес" ПИР'!$B$31)/100 -> 0 | AJ14: на стадии подготовки | AP14: на стадии подготовки | AR14: на стадии подготовки | AT14: на стадии подготовки | BB14: =(AI14*'"Вес" ПИР'!$B$36+AK14*'"Вес" ПИР'!$B$37+AM14*'"Вес" ПИР'!$B$38+AO14*'"Вес" ПИР'!$B$39+AQ14*'"Вес" ПИР'!$B$40+AS14*'"Вес" ПИР'!$B$41+AU14*'"Вес" ПИР'!$B$42+AW14*'"Вес" ПИР'!$B$43+AY14*'"Вес" ПИР'!$B$44+BA14*'"Вес" ПИР'!$B$45)/100 -> 0 | BC14: на стадии подготовки | BE14: на стадии подготовки | BG14: =(BD14*'"Вес" ПИР'!$B$50+BF14*'"Вес" ПИР'!$B$51)/100 -> 0 | BI14: 0 | BK14: 31.09.2026 | BL14: =(S14*'"Вес" ПИР'!$B$3+X14*'"Вес" ПИР'!$B$4+AG14*'"Вес" ПИР'!$B$5+BB14*'"Вес" ПИР'!$B$6+BG14*'"Вес" ПИР'!$B$7+BI14*'"Вес" ПИР'!$B$8)/100 -> 0.00375
B15: 2026 | C15: ТОО "5А Engineering" | D15: 114845200 | E15: Акмолинская область | F15: Есильский район | G15: Жаныспайский с.о. | H15: с.Ковыльное | I15: Имеется | J15: 1 | K15: на стадии подготовки | M15: на стадии подготовки | O15: на стадии подготовки | Q15: на стадии подготовки | S15: =(J15*'"Вес" ПИР'!$B$13+L15*'"Вес" ПИР'!$B$14+N15*'"Вес" ПИР'!$B$15+P15*'"Вес" ПИР'!$B$16+R15*'"Вес" ПИР'!$B$17)/100 -> 0.05 | T15: Готово | V15: Готово | X15: =(U15*'"Вес" ПИР'!$B$22+W15*'"Вес" ПИР'!$B$23)/100 -> 0 | AG15: =(Z15*'"Вес" ПИР'!$B$28+AB15*'"Вес" ПИР'!$B$29+AD15*'"Вес" ПИР'!$B$30+AF15*'"Вес" ПИР'!$B$31)/100 -> 0 | AJ15: на стадии подготовки | AP15: на стадии подготовки | AR15: на стадии подготовки | AT15: на стадии подготовки | BB15: =(AI15*'"Вес" ПИР'!$B$36+AK15*'"Вес" ПИР'!$B$37+AM15*'"Вес" ПИР'!$B$38+AO15*'"Вес" ПИР'!$B$39+AQ15*'"Вес" ПИР'!$B$40+AS15*'"Вес" ПИР'!$B$41+AU15*'"Вес" ПИР'!$B$42+AW15*'"Вес" ПИР'!$B$43+AY15*'"Вес" ПИР'!$B$44+BA15*'"Вес" ПИР'!$B$45)/100 -> 0 | BC15: на стадии подготовки | BE15: на стадии подготовки | BG15: =(BD15*'"Вес" ПИР'!$B$50+BF15*'"Вес" ПИР'!$B$51)/100 -> 0 | BI15: 0 | BK15: 31.09.2026 | BL15: =(S15*'"Вес" ПИР'!$B$3+X15*'"Вес" ПИР'!$B$4+AG15*'"Вес" ПИР'!$B$5+BB15*'"Вес" ПИР'!$B$6+BG15*'"Вес" ПИР'!$B$7+BI15*'"Вес" ПИР'!$B$8)/100 -> 0.00375
B16: 2026 | C16: ТОО "5А Engineering" | D16: 114859200 | E16: Акмолинская область | F16: Есильский район | G16: Канай Бийский с.о. | H16: с.Иглик | I16: Имеется | J16: 1 | K16: на стадии подготовки | M16: на стадии подготовки | O16: на стадии подготовки | Q16: на стадии подготовки | S16: =(J16*'"Вес" ПИР'!$B$13+L16*'"Вес" ПИР'!$B$14+N16*'"Вес" ПИР'!$B$15+P16*'"Вес" ПИР'!$B$16+R16*'"Вес" ПИР'!$B$17)/100 -> 0.05 | T16: Готово | V16: Готово | X16: =(U16*'"Вес" ПИР'!$B$22+W16*'"Вес" ПИР'!$B$23)/100 -> 0 | AG16: =(Z16*'"Вес" ПИР'!$B$28+AB16*'"Вес" ПИР'!$B$29+AD16*'"Вес" ПИР'!$B$30+AF16*'"Вес" ПИР'!$B$31)/100 -> 0 | AJ16: на стадии подготовки | AP16: на стадии подготовки | AR16: на стадии подготовки | AT16: на стадии подготовки | BB16: =(AI16*'"Вес" ПИР'!$B$36+AK16*'"Вес" ПИР'!$B$37+AM16*'"Вес" ПИР'!$B$38+AO16*'"Вес" ПИР'!$B$39+AQ16*'"Вес" ПИР'!$B$40+AS16*'"Вес" ПИР'!$B$41+AU16*'"Вес" ПИР'!$B$42+AW16*'"Вес" ПИР'!$B$43+AY16*'"Вес" ПИР'!$B$44+BA16*'"Вес" ПИР'!$B$45)/100 -> 0 | BC16: на стадии подготовки | BE16: на стадии подготовки | BG16: =(BD16*'"Вес" ПИР'!$B$50+BF16*'"Вес" ПИР'!$B$51)/100 -> 0 | BI16: 0 | BK16: 31.09.2026 | BL16: =(S16*'"Вес" ПИР'!$B$3+X16*'"Вес" ПИР'!$B$4+AG16*'"Вес" ПИР'!$B$5+BB16*'"Вес" ПИР'!$B$6+BG16*'"Вес" ПИР'!$B$7+BI16*'"Вес" ПИР'!$B$8)/100 -> 0.00375
B17: 2026 | C17: ТОО "5А Engineering" | D17: 114857300 | E17: Акмолинская область | F17: Есильский район | G17: Красивинский с.о. | H17: с.Кумай | I17: Имеется | J17: 1 | K17: на стадии подготовки | M17: на стадии подготовки | O17: на стадии подготовки | Q17: на стадии подготовки | S17: =(J17*'"Вес" ПИР'!$B$13+L17*'"Вес" ПИР'!$B$14+N17*'"Вес" ПИР'!$B$15+P17*'"Вес" ПИР'!$B$16+R17*'"Вес" ПИР'!$B$17)/100 -> 0.05 | T17: Готово | V17: Готово | X17: =(U17*'"Вес" ПИР'!$B$22+W17*'"Вес" ПИР'!$B$23)/100 -> 0 | AG17: =(Z17*'"Вес" ПИР'!$B$28+AB17*'"Вес" ПИР'!$B$29+AD17*'"Вес" ПИР'!$B$30+AF17*'"Вес" ПИР'!$B$31)/100 -> 0 | AJ17: на стадии подготовки | AP17: на стадии подготовки | AR17: на стадии подготовки | AT17: на стадии подготовки | BB17: =(AI17*'"Вес" ПИР'!$B$36+AK17*'"Вес" ПИР'!$B$37+AM17*'"Вес" ПИР'!$B$38+AO17*'"Вес" ПИР'!$B$39+AQ17*'"Вес" ПИР'!$B$40+AS17*'"Вес" ПИР'!$B$41+AU17*'"Вес" ПИР'!$B$42+AW17*'"Вес" ПИР'!$B$43+AY17*'"Вес" ПИР'!$B$44+BA17*'"Вес" ПИР'!$B$45)/100 -> 0 | BC17: на стадии подготовки | BE17: на стадии подготовки | BG17: =(BD17*'"Вес" ПИР'!$B$50+BF17*'"Вес" ПИР'!$B$51)/100 -> 0 | BI17: 0 | BK17: 31.09.2026 | BL17: =(S17*'"Вес" ПИР'!$B$3+X17*'"Вес" ПИР'!$B$4+AG17*'"Вес" ПИР'!$B$5+BB17*'"Вес" ПИР'!$B$6+BG17*'"Вес" ПИР'!$B$7+BI17*'"Вес" ПИР'!$B$8)/100 -> 0.00375
B18: 2026 | C18: ТОО "5А Engineering" | D18: 115669100 | E18: Акмолинская область | F18: Зерендинский район | G18: Байтерекский с.о. | H18: с.Байтерек | I18: Имеется | J18: 1 | K18: на стадии подготовки | M18: на стадии подготовки | O18: на стадии подготовки | Q18: на стадии подготовки | S18: =(J18*'"Вес" ПИР'!$B$13+L18*'"Вес" ПИР'!$B$14+N18*'"Вес" ПИР'!$B$15+P18*'"Вес" ПИР'!$B$16+R18*'"Вес" ПИР'!$B$17)/100 -> 0.05 | T18: 01.12.2025-30.03.2026 | V18: 01.12.2025-30.03.2026 | X18: =(U18*'"Вес" ПИР'!$B$22+W18*'"Вес" ПИР'!$B$23)/100 -> 0 | AG18: =(Z18*'"Вес" ПИР'!$B$28+AB18*'"Вес" ПИР'!$B$29+AD18*'"Вес" ПИР'!$B$30+AF18*'"Вес" ПИР'!$B$31)/100 -> 0 | AJ18: на стадии подготовки | AP18: на стадии подготовки | AR18: на стадии подготовки | AT18: на стадии подготовки | BB18: =(AI18*'"Вес" ПИР'!$B$36+AK18*'"Вес" ПИР'!$B$37+AM18*'"Вес" ПИР'!$B$38+AO18*'"Вес" ПИР'!$B$39+AQ18*'"Вес" ПИР'!$B$40+AS18*'"Вес" ПИР'!$B$41+AU18*'"Вес" ПИР'!$B$42+AW18*'"Вес" ПИР'!$B$43+AY18*'"Вес" ПИР'!$B$44+BA18*'"Вес" ПИР'!$B$45)/100 -> 0 | BC18: на стадии подготовки | BE18: на стадии подготовки | BG18: =(BD18*'"Вес" ПИР'!$B$50+BF18*'"Вес" ПИР'!$B$51)/100 -> 0 | BI18: 0 | BK18: 46266 | BL18: =(S18*'"Вес" ПИР'!$B$3+X18*'"Вес" ПИР'!$B$4+AG18*'"Вес" ПИР'!$B$5+BB18*'"Вес" ПИР'!$B$6+BG18*'"Вес" ПИР'!$B$7+BI18*'"Вес" ПИР'!$B$8)/100 -> 0.00375
B19: 2026 | C19: ТОО "5А Engineering" | D19: 115669300 | E19: Акмолинская область | F19: Зерендинский район | G19: Байтерекский с.о. | H19: с.Ермаковка | I19: Имеется | J19: 1 | K19: на стадии подготовки | M19: на стадии подготовки | O19: на стадии подготовки | Q19: на стадии подготовки | S19: =(J19*'"Вес" ПИР'!$B$13+L19*'"Вес" ПИР'!$B$14+N19*'"Вес" ПИР'!$B$15+P19*'"Вес" ПИР'!$B$16+R19*'"Вес" ПИР'!$B$17)/100 -> 0.05 | T19: 01.12.2025-30.03.2026 | V19: 01.12.2025-30.03.2026 | X19: =(U19*'"Вес" ПИР'!$B$22+W19*'"Вес" ПИР'!$B$23)/100 -> 0 | AG19: =(Z19*'"Вес" ПИР'!$B$28+AB19*'"Вес" ПИР'!$B$29+AD19*'"Вес" ПИР'!$B$30+AF19*'"Вес" ПИР'!$B$31)/100 -> 0 | AJ19: на стадии подготовки | AP19: на стадии подготовки | AR19: на стадии подготовки | AT19: на стадии подготовки | BB19: =(AI19*'"Вес" ПИР'!$B$36+AK19*'"Вес" ПИР'!$B$37+AM19*'"Вес" ПИР'!$B$38+AO19*'"Вес" ПИР'!$B$39+AQ19*'"Вес" ПИР'!$B$40+AS19*'"Вес" ПИР'!$B$41+AU19*'"Вес" ПИР'!$B$42+AW19*'"Вес" ПИР'!$B$43+AY19*'"Вес" ПИР'!$B$44+BA19*'"Вес" ПИР'!$B$45)/100 -> 0 | BC19: на стадии подготовки | BE19: на стадии подготовки | BG19: =(BD19*'"Вес" ПИР'!$B$50+BF19*'"Вес" ПИР'!$B$51)/100 -> 0 | BI19: 0 | BK19: 46266 | BL19: =(S19*'"Вес" ПИР'!$B$3+X19*'"Вес" ПИР'!$B$4+AG19*'"Вес" ПИР'!$B$5+BB19*'"Вес" ПИР'!$B$6+BG19*'"Вес" ПИР'!$B$7+BI19*'"Вес" ПИР'!$B$8)/100 -> 0.00375
B20: 2026 | C20: ТОО "5А Engineering" | D20: 115669400 | E20: Акмолинская область | F20: Зерендинский район | G20: Байтерекский с.о. | H20: с.Красный Кордон | I20: Имеется | J20: 1 | K20: на стадии подготовки | M20: на стадии подготовки | O20: на стадии подготовки | Q20: на стадии подготовки | S20: =(J20*'"Вес" ПИР'!$B$13+L20*'"Вес" ПИР'!$B$14+N20*'"Вес" ПИР'!$B$15+P20*'"Вес" ПИР'!$B$16+R20*'"Вес" ПИР'!$B$17)/100 -> 0.05 | T20: 01.12.2025-30.03.2026 | V20: 01.12.2025-30.03.2026 | X20: =(U20*'"Вес" ПИР'!$B$22+W20*'"Вес" ПИР'!$B$23)/100 -> 0 | AG20: =(Z20*'"Вес" ПИР'!$B$28+AB20*'"Вес" ПИР'!$B$29+AD20*'"Вес" ПИР'!$B$30+AF20*'"Вес" ПИР'!$B$31)/100 -> 0 | AJ20: на стадии подготовки | AP20: на стадии подготовки | AR20: на стадии подготовки | AT20: на стадии подготовки | BB20: =(AI20*'"Вес" ПИР'!$B$36+AK20*'"Вес" ПИР'!$B$37+AM20*'"Вес" ПИР'!$B$38+AO20*'"Вес" ПИР'!$B$39+AQ20*'"Вес" ПИР'!$B$40+AS20*'"Вес" ПИР'!$B$41+AU20*'"Вес" ПИР'!$B$42+AW20*'"Вес" ПИР'!$B$43+AY20*'"Вес" ПИР'!$B$44+BA20*'"Вес" ПИР'!$B$45)/100 -> 0 | BC20: на стадии подготовки | BE20: на стадии подготовки | BG20: =(BD20*'"Вес" ПИР'!$B$50+BF20*'"Вес" ПИР'!$B$51)/100 -> 0 | BI20: 0 | BK20: 46266 | BL20: =(S20*'"Вес" ПИР'!$B$3+X20*'"Вес" ПИР'!$B$4+AG20*'"Вес" ПИР'!$B$5+BB20*'"Вес" ПИР'!$B$6+BG20*'"Вес" ПИР'!$B$7+BI20*'"Вес" ПИР'!$B$8)/100 -> 0.00375
B21: 2026 | C21: ТОО "5А Engineering" | D21: 115637400 | E21: Акмолинская область | F21: Зерендинский район | G21: Булакский с.о. | H21: с.Жанааул | I21: Имеется | J21: 1 | K21: на стадии подготовки | M21: на стадии подготовки | O21: на стадии подготовки | Q21: на стадии подготовки | S21: =(J21*'"Вес" ПИР'!$B$13+L21*'"Вес" ПИР'!$B$14+N21*'"Вес" ПИР'!$B$15+P21*'"Вес" ПИР'!$B$16+R21*'"Вес" ПИР'!$B$17)/100 -> 0.05 | T21: 01.12.2025-30.03.2026 | V21: 01.12.2025-30.03.2026 | X21: =(U21*'"Вес" ПИР'!$B$22+W21*'"Вес" ПИР'!$B$23)/100 -> 0 | AG21: =(Z21*'"Вес" ПИР'!$B$28+AB21*'"Вес" ПИР'!$B$29+AD21*'"Вес" ПИР'!$B$30+AF21*'"Вес" ПИР'!$B$31)/100 -> 0 | AJ21: на стадии подготовки | AP21: на стадии подготовки | AR21: на стадии подготовки | AT21: на стадии подготовки | BB21: =(AI21*'"Вес" ПИР'!$B$36+AK21*'"Вес" ПИР'!$B$37+AM21*'"Вес" ПИР'!$B$38+AO21*'"Вес" ПИР'!$B$39+AQ21*'"Вес" ПИР'!$B$40+AS21*'"Вес" ПИР'!$B$41+AU21*'"Вес" ПИР'!$B$42+AW21*'"Вес" ПИР'!$B$43+AY21*'"Вес" ПИР'!$B$44+BA21*'"Вес" ПИР'!$B$45)/100 -> 0 | BC21: на стадии подготовки | BE21: на стадии подготовки | BG21: =(BD21*'"Вес" ПИР'!$B$50+BF21*'"Вес" ПИР'!$B$51)/100 -> 0 | BI21: 0 | BK21: 46266 | BL21: =(S21*'"Вес" ПИР'!$B$3+X21*'"Вес" ПИР'!$B$4+AG21*'"Вес" ПИР'!$B$5+BB21*'"Вес" ПИР'!$B$6+BG21*'"Вес" ПИР'!$B$7+BI21*'"Вес" ПИР'!$B$8)/100 -> 0.00375
B22: 2026 | C22: ТОО "5А Engineering" | D22: 115637700 | E22: Акмолинская область | F22: Зерендинский район | G22: Булакский с.о. | H22: с.Карлыколь | I22: Имеется | J22: 1 | K22: на стадии подготовки | M22: на стадии подготовки | O22: на стадии подготовки | Q22: на стадии подготовки | S22: =(J22*'"Вес" ПИР'!$B$13+L22*'"Вес" ПИР'!$B$14+N22*'"Вес" ПИР'!$B$15+P22*'"Вес" ПИР'!$B$16+R22*'"Вес" ПИР'!$B$17)/100 -> 0.05 | T22: 01.12.2025-30.03.2026 | V22: 01.12.2025-30.03.2026 | X22: =(U22*'"Вес" ПИР'!$B$22+W22*'"Вес" ПИР'!$B$23)/100 -> 0 | AG22: =(Z22*'"Вес" ПИР'!$B$28+AB22*'"Вес" ПИР'!$B$29+AD22*'"Вес" ПИР'!$B$30+AF22*'"Вес" ПИР'!$B$31)/100 -> 0 | AJ22: на стадии подготовки | AP22: на стадии подготовки | AR22: на стадии подготовки | AT22: на стадии подготовки | BB22: =(AI22*'"Вес" ПИР'!$B$36+AK22*'"Вес" ПИР'!$B$37+AM22*'"Вес" ПИР'!$B$38+AO22*'"Вес" ПИР'!$B$39+AQ22*'"Вес" ПИР'!$B$40+AS22*'"Вес" ПИР'!$B$41+AU22*'"Вес" ПИР'!$B$42+AW22*'"Вес" ПИР'!$B$43+AY22*'"Вес" ПИР'!$B$44+BA22*'"Вес" ПИР'!$B$45)/100 -> 0 | BC22: на стадии подготовки | BE22: на стадии подготовки | BG22: =(BD22*'"Вес" ПИР'!$B$50+BF22*'"Вес" ПИР'!$B$51)/100 -> 0 | BI22: 0 | BK22: 46266 | BL22: =(S22*'"Вес" ПИР'!$B$3+X22*'"Вес" ПИР'!$B$4+AG22*'"Вес" ПИР'!$B$5+BB22*'"Вес" ПИР'!$B$6+BG22*'"Вес" ПИР'!$B$7+BI22*'"Вес" ПИР'!$B$8)/100 -> 0.00375
B23: 2026 | C23: ТОО "5А Engineering" | D23: 115643600 | E23: Акмолинская область | F23: Зерендинский район | G23: Викторовский с.о. | H23: с.Богенбай би | I23: Имеется | J23: 1 | K23: на стадии подготовки | M23: на стадии подготовки | O23: на стадии подготовки | Q23: на стадии подготовки | S23: =(J23*'"Вес" ПИР'!$B$13+L23*'"Вес" ПИР'!$B$14+N23*'"Вес" ПИР'!$B$15+P23*'"Вес" ПИР'!$B$16+R23*'"Вес" ПИР'!$B$17)/100 -> 0.05 | T23: 01.12.2025-30.03.2026 | V23: 01.12.2025-30.03.2026 | X23: =(U23*'"Вес" ПИР'!$B$22+W23*'"Вес" ПИР'!$B$23)/100 -> 0 | AG23: =(Z23*'"Вес" ПИР'!$B$28+AB23*'"Вес" ПИР'!$B$29+AD23*'"Вес" ПИР'!$B$30+AF23*'"Вес" ПИР'!$B$31)/100 -> 0 | AJ23: на стадии подготовки | AP23: на стадии подготовки | AR23: на стадии подготовки | AT23: на стадии подготовки | BB23: =(AI23*'"Вес" ПИР'!$B$36+AK23*'"Вес" ПИР'!$B$37+AM23*'"Вес" ПИР'!$B$38+AO23*'"Вес" ПИР'!$B$39+AQ23*'"Вес" ПИР'!$B$40+AS23*'"Вес" ПИР'!$B$41+AU23*'"Вес" ПИР'!$B$42+AW23*'"Вес" ПИР'!$B$43+AY23*'"Вес" ПИР'!$B$44+BA23*'"Вес" ПИР'!$B$45)/100 -> 0 | BC23: на стадии подготовки | BE23: на стадии подготовки | BG23: =(BD23*'"Вес" ПИР'!$B$50+BF23*'"Вес" ПИР'!$B$51)/100 -> 0 | BI23: 0 | BK23: 46266 | BL23: =(S23*'"Вес" ПИР'!$B$3+X23*'"Вес" ПИР'!$B$4+AG23*'"Вес" ПИР'!$B$5+BB23*'"Вес" ПИР'!$B$6+BG23*'"Вес" ПИР'!$B$7+BI23*'"Вес" ПИР'!$B$8)/100 -> 0.00375
B24: 2026 | C24: ТОО "5А Engineering" | D24: 115630380 | E24: Акмолинская область | F24: Зерендинский район | G24: Зерендинский с.о. | H24: с.Коктерек | I24: Имеется | J24: 1 | K24: на стадии подготовки | M24: на стадии подготовки | O24: на стадии подготовки | Q24: на стадии подготовки | S24: =(J24*'"Вес" ПИР'!$B$13+L24*'"Вес" ПИР'!$B$14+N24*'"Вес" ПИР'!$B$15+P24*'"Вес" ПИР'!$B$16+R24*'"Вес" ПИР'!$B$17)/100 -> 0.05 | T24: 01.12.2025-30.03.2026 | V24: 01.12.2025-30.03.2026 | X24: =(U24*'"Вес" ПИР'!$B$22+W24*'"Вес" ПИР'!$B$23)/100 -> 0 | AG24: =(Z24*'"Вес" ПИР'!$B$28+AB24*'"Вес" ПИР'!$B$29+AD24*'"Вес" ПИР'!$B$30+AF24*'"Вес" ПИР'!$B$31)/100 -> 0 | AJ24: на стадии подготовки | AP24: на стадии подготовки | AR24: на стадии подготовки | AT24: на стадии подготовки | BB24: =(AI24*'"Вес" ПИР'!$B$36+AK24*'"Вес" ПИР'!$B$37+AM24*'"Вес" ПИР'!$B$38+AO24*'"Вес" ПИР'!$B$39+AQ24*'"Вес" ПИР'!$B$40+AS24*'"Вес" ПИР'!$B$41+AU24*'"Вес" ПИР'!$B$42+AW24*'"Вес" ПИР'!$B$43+AY24*'"Вес" ПИР'!$B$44+BA24*'"Вес" ПИР'!$B$45)/100 -> 0 | BC24: на стадии подготовки | BE24: на стадии подготовки | BG24: =(BD24*'"Вес" ПИР'!$B$50+BF24*'"Вес" ПИР'!$B$51)/100 -> 0 | BI24: 0 | BK24: 46266 | BL24: =(S24*'"Вес" ПИР'!$B$3+X24*'"Вес" ПИР'!$B$4+AG24*'"Вес" ПИР'!$B$5+BB24*'"Вес" ПИР'!$B$6+BG24*'"Вес" ПИР'!$B$7+BI24*'"Вес" ПИР'!$B$8)/100 -> 0.00375
B25: 2026 | C25: ТОО "5А Engineering" | D25: 115663100 | E25: Акмолинская область | F25: Зерендинский район | G25: Исаковский с.о. | H25: с.Исаковка | I25: Имеется | J25: 1 | K25: на стадии подготовки | M25: на стадии подготовки | O25: на стадии подготовки | Q25: на стадии подготовки | S25: =(J25*'"Вес" ПИР'!$B$13+L25*'"Вес" ПИР'!$B$14+N25*'"Вес" ПИР'!$B$15+P25*'"Вес" ПИР'!$B$16+R25*'"Вес" ПИР'!$B$17)/100 -> 0.05 | T25: 01.12.2025-30.03.2026 | V25: 01.12.2025-30.03.2026 | X25: =(U25*'"Вес" ПИР'!$B$22+W25*'"Вес" ПИР'!$B$23)/100 -> 0 | AG25: =(Z25*'"Вес" ПИР'!$B$28+AB25*'"Вес" ПИР'!$B$29+AD25*'"Вес" ПИР'!$B$30+AF25*'"Вес" ПИР'!$B$31)/100 -> 0 | AJ25: на стадии подготовки | AP25: на стадии подготовки | AR25: на стадии подготовки | AT25: на стадии подготовки | BB25: =(AI25*'"Вес" ПИР'!$B$36+AK25*'"Вес" ПИР'!$B$37+AM25*'"Вес" ПИР'!$B$38+AO25*'"Вес" ПИР'!$B$39+AQ25*'"Вес" ПИР'!$B$40+AS25*'"Вес" ПИР'!$B$41+AU25*'"Вес" ПИР'!$B$42+AW25*'"Вес" ПИР'!$B$43+AY25*'"Вес" ПИР'!$B$44+BA25*'"Вес" ПИР'!$B$45)/100 -> 0 | BC25: на стадии подготовки | BE25: на стадии подготовки | BG25: =(BD25*'"Вес" ПИР'!$B$50+BF25*'"Вес" ПИР'!$B$51)/100 -> 0 | BI25: 0 | BK25: 46266 | BL25: =(S25*'"Вес" ПИР'!$B$3+X25*'"Вес" ПИР'!$B$4+AG25*'"Вес" ПИР'!$B$5+BB25*'"Вес" ПИР'!$B$6+BG25*'"Вес" ПИР'!$B$7+BI25*'"Вес" ПИР'!$B$8)/100 -> 0.00375
B26: 2026 | C26: ТОО "5А Engineering" | D26: 115663400 | E26: Акмолинская область | F26: Зерендинский район | G26: Исаковский с.о. | H26: с.Костомаровка | I26: Имеется | J26: 1 | K26: на стадии подготовки | M26: на стадии подготовки | O26: на стадии подготовки | Q26: на стадии подготовки | S26: =(J26*'"Вес" ПИР'!$B$13+L26*'"Вес" ПИР'!$B$14+N26*'"Вес" ПИР'!$B$15+P26*'"Вес" ПИР'!$B$16+R26*'"Вес" ПИР'!$B$17)/100 -> 0.05 | T26: 01.12.2025-30.03.2026 | V26: 01.12.2025-30.03.2026 | X26: =(U26*'"Вес" ПИР'!$B$22+W26*'"Вес" ПИР'!$B$23)/100 -> 0 | AG26: =(Z26*'"Вес" ПИР'!$B$28+AB26*'"Вес" ПИР'!$B$29+AD26*'"Вес" ПИР'!$B$30+AF26*'"Вес" ПИР'!$B$31)/100 -> 0 | AJ26: на стадии подготовки | AP26: на стадии подготовки | AR26: на стадии подготовки | AT26: на стадии подготовки | BB26: =(AI26*'"Вес" ПИР'!$B$36+AK26*'"Вес" ПИР'!$B$37+AM26*'"Вес" ПИР'!$B$38+AO26*'"Вес" ПИР'!$B$39+AQ26*'"Вес" ПИР'!$B$40+AS26*'"Вес" ПИР'!$B$41+AU26*'"Вес" ПИР'!$B$42+AW26*'"Вес" ПИР'!$B$43+AY26*'"Вес" ПИР'!$B$44+BA26*'"Вес" ПИР'!$B$45)/100 -> 0 | BC26: на стадии подготовки | BE26: на стадии подготовки | BG26: =(BD26*'"Вес" ПИР'!$B$50+BF26*'"Вес" ПИР'!$B$51)/100 -> 0 | BI26: 0 | BK26: 46266 | BL26: =(S26*'"Вес" ПИР'!$B$3+X26*'"Вес" ПИР'!$B$4+AG26*'"Вес" ПИР'!$B$5+BB26*'"Вес" ПИР'!$B$6+BG26*'"Вес" ПИР'!$B$7+BI26*'"Вес" ПИР'!$B$8)/100 -> 0.00375
B27: 2026 | C27: ТОО "5А Engineering" | D27: 115649200 | E27: Акмолинская область | F27: Зерендинский район | G27: Конысбайский с.о. | H27: с.Васильковка | I27: Имеется | J27: 1 | K27: на стадии подготовки | M27: на стадии подготовки | O27: на стадии подготовки | Q27: на стадии подготовки | S27: =(J27*'"Вес" ПИР'!$B$13+L27*'"Вес" ПИР'!$B$14+N27*'"Вес" ПИР'!$B$15+P27*'"Вес" ПИР'!$B$16+R27*'"Вес" ПИР'!$B$17)/100 -> 0.05 | T27: 01.12.2025-30.03.2026 | V27: 01.12.2025-30.03.2026 | X27: =(U27*'"Вес" ПИР'!$B$22+W27*'"Вес" ПИР'!$B$23)/100 -> 0 | AG27: =(Z27*'"Вес" ПИР'!$B$28+AB27*'"Вес" ПИР'!$B$29+AD27*'"Вес" ПИР'!$B$30+AF27*'"Вес" ПИР'!$B$31)/100 -> 0 | AJ27: на стадии подготовки | AP27: на стадии подготовки | AR27: на стадии подготовки | AT27: на стадии подготовки | BB27: =(AI27*'"Вес" ПИР'!$B$36+AK27*'"Вес" ПИР'!$B$37+AM27*'"Вес" ПИР'!$B$38+AO27*'"Вес" ПИР'!$B$39+AQ27*'"Вес" ПИР'!$B$40+AS27*'"Вес" ПИР'!$B$41+AU27*'"Вес" ПИР'!$B$42+AW27*'"Вес" ПИР'!$B$43+AY27*'"Вес" ПИР'!$B$44+BA27*'"Вес" ПИР'!$B$45)/100 -> 0 | BC27: на стадии подготовки | BE27: на стадии подготовки | BG27: =(BD27*'"Вес" ПИР'!$B$50+BF27*'"Вес" ПИР'!$B$51)/100 -> 0 | BI27: 0 | BK27: 46266 | BL27: =(S27*'"Вес" ПИР'!$B$3+X27*'"Вес" ПИР'!$B$4+AG27*'"Вес" ПИР'!$B$5+BB27*'"Вес" ПИР'!$B$6+BG27*'"Вес" ПИР'!$B$7+BI27*'"Вес" ПИР'!$B$8)/100 -> 0.00375
B28: 2026 | C28: ТОО "5А Engineering" | D28: 115649400 | E28: Акмолинская область | F28: Зерендинский район | G28: Конысбайский с.о. | H28: с.Донгулагаш | I28: Имеется | J28: 1 | K28: на стадии подготовки | M28: на стадии подготовки | O28: на стадии подготовки | Q28: на стадии подготовки | S28: =(J28*'"Вес" ПИР'!$B$13+L28*'"Вес" ПИР'!$B$14+N28*'"Вес" ПИР'!$B$15+P28*'"Вес" ПИР'!$B$16+R28*'"Вес" ПИР'!$B$17)/100 -> 0.05 | T28: 01.12.2025-30.03.2026 | V28: 01.12.2025-30.03.2026 | X28: =(U28*'"Вес" ПИР'!$B$22+W28*'"Вес" ПИР'!$B$23)/100 -> 0 | AG28: =(Z28*'"Вес" ПИР'!$B$28+AB28*'"Вес" ПИР'!$B$29+AD28*'"Вес" ПИР'!$B$30+AF28*'"Вес" ПИР'!$B$31)/100 -> 0 | AJ28: на стадии подготовки | AP28: на стадии подготовки | AR28: на стадии подготовки | AT28: на стадии подготовки | BB28: =(AI28*'"Вес" ПИР'!$B$36+AK28*'"Вес" ПИР'!$B$37+AM28*'"Вес" ПИР'!$B$38+AO28*'"Вес" ПИР'!$B$39+AQ28*'"Вес" ПИР'!$B$40+AS28*'"Вес" ПИР'!$B$41+AU28*'"Вес" ПИР'!$B$42+AW28*'"Вес" ПИР'!$B$43+AY28*'"Вес" ПИР'!$B$44+BA28*'"Вес" ПИР'!$B$45)/100 -> 0 | BC28: на стадии подготовки | BE28: на стадии подготовки | BG28: =(BD28*'"Вес" ПИР'!$B$50+BF28*'"Вес" ПИР'!$B$51)/100 -> 0 | BI28: 0 | BK28: 46266 | BL28: =(S28*'"Вес" ПИР'!$B$3+X28*'"Вес" ПИР'!$B$4+AG28*'"Вес" ПИР'!$B$5+BB28*'"Вес" ПИР'!$B$6+BG28*'"Вес" ПИР'!$B$7+BI28*'"Вес" ПИР'!$B$8)/100 -> 0.00375
B29: 2026 | C29: ТОО "5А Engineering" | D29: 115667100 | E29: Акмолинская область | F29: Зерендинский район | G29: Кызылегисский с.о. | H29: с.Кызылегис | I29: Имеется | J29: 1 | K29: на стадии подготовки | M29: на стадии подготовки | O29: на стадии подготовки | Q29: на стадии подготовки | S29: =(J29*'"Вес" ПИР'!$B$13+L29*'"Вес" ПИР'!$B$14+N29*'"Вес" ПИР'!$B$15+P29*'"Вес" ПИР'!$B$16+R29*'"Вес" ПИР'!$B$17)/100 -> 0.05 | T29: 01.12.2025-30.03.2026 | V29: 01.12.2025-30.03.2026 | X29: =(U29*'"Вес" ПИР'!$B$22+W29*'"Вес" ПИР'!$B$23)/100 -> 0 | AG29: =(Z29*'"Вес" ПИР'!$B$28+AB29*'"Вес" ПИР'!$B$29+AD29*'"Вес" ПИР'!$B$30+AF29*'"Вес" ПИР'!$B$31)/100 -> 0 | AJ29: на стадии подготовки | AP29: на стадии подготовки | AR29: на стадии подготовки | AT29: на стадии подготовки | BB29: =(AI29*'"Вес" ПИР'!$B$36+AK29*'"Вес" ПИР'!$B$37+AM29*'"Вес" ПИР'!$B$38+AO29*'"Вес" ПИР'!$B$39+AQ29*'"Вес" ПИР'!$B$40+AS29*'"Вес" ПИР'!$B$41+AU29*'"Вес" ПИР'!$B$42+AW29*'"Вес" ПИР'!$B$43+AY29*'"Вес" ПИР'!$B$44+BA29*'"Вес" ПИР'!$B$45)/100 -> 0 | BC29: на стадии подготовки | BE29: на стадии подготовки | BG29: =(BD29*'"Вес" ПИР'!$B$50+BF29*'"Вес" ПИР'!$B$51)/100 -> 0 | BI29: 0 | BK29: 46266 | BL29: =(S29*'"Вес" ПИР'!$B$3+X29*'"Вес" ПИР'!$B$4+AG29*'"Вес" ПИР'!$B$5+BB29*'"Вес" ПИР'!$B$6+BG29*'"Вес" ПИР'!$B$7+BI29*'"Вес" ПИР'!$B$8)/100 -> 0.00375
B30: 2026 | C30: ТОО "5А Engineering" | D30: 115667700 | E30: Акмолинская область | F30: Зерендинский район | G30: Кызылегисский с.о. | H30: с.Ортаагаш | I30: Имеется | J30: 1 | K30: на стадии подготовки | M30: на стадии подготовки | O30: на стадии подготовки | Q30: на стадии подготовки | S30: =(J30*'"Вес" ПИР'!$B$13+L30*'"Вес" ПИР'!$B$14+N30*'"Вес" ПИР'!$B$15+P30*'"Вес" ПИР'!$B$16+R30*'"Вес" ПИР'!$B$17)/100 -> 0.05 | T30: 01.12.2025-30.03.2026 | V30: 01.12.2025-30.03.2026 | X30: =(U30*'"Вес" ПИР'!$B$22+W30*'"Вес" ПИР'!$B$23)/100 -> 0 | AG30: =(Z30*'"Вес" ПИР'!$B$28+AB30*'"Вес" ПИР'!$B$29+AD30*'"Вес" ПИР'!$B$30+AF30*'"Вес" ПИР'!$B$31)/100 -> 0 | AJ30: на стадии подготовки | AP30: на стадии подготовки | AR30: на стадии подготовки | AT30: на стадии подготовки | BB30: =(AI30*'"Вес" ПИР'!$B$36+AK30*'"Вес" ПИР'!$B$37+AM30*'"Вес" ПИР'!$B$38+AO30*'"Вес" ПИР'!$B$39+AQ30*'"Вес" ПИР'!$B$40+AS30*'"Вес" ПИР'!$B$41+AU30*'"Вес" ПИР'!$B$42+AW30*'"Вес" ПИР'!$B$43+AY30*'"Вес" ПИР'!$B$44+BA30*'"Вес" ПИР'!$B$45)/100 -> 0 | BC30: на стадии подготовки | BE30: на стадии подготовки | BG30: =(BD30*'"Вес" ПИР'!$B$50+BF30*'"Вес" ПИР'!$B$51)/100 -> 0 | BI30: 0 | BK30: 46266 | BL30: =(S30*'"Вес" ПИР'!$B$3+X30*'"Вес" ПИР'!$B$4+AG30*'"Вес" ПИР'!$B$5+BB30*'"Вес" ПИР'!$B$6+BG30*'"Вес" ПИР'!$B$7+BI30*'"Вес" ПИР'!$B$8)/100 -> 0.00375
B31: 2026 | C31: ТОО "5А Engineering" | D31: 115651100 | E31: Акмолинская область | F31: Зерендинский район | G31: Кызылсаянский с.о. | H31: с.Кызылсая | I31: Имеется | K31: на стадии подготовки | M31: на стадии подготовки | O31: на стадии подготовки | Q31: на стадии подготовки | S31: =(J31*'"Вес" ПИР'!$B$13+L31*'"Вес" ПИР'!$B$14+N31*'"Вес" ПИР'!$B$15+P31*'"Вес" ПИР'!$B$16+R31*'"Вес" ПИР'!$B$17)/100 -> 0 | T31: 01.12.2025-30.03.2026 | V31: 01.12.2025-30.03.2026 | X31: =(U31*'"Вес" ПИР'!$B$22+W31*'"Вес" ПИР'!$B$23)/100 -> 0 | AG31: =(Z31*'"Вес" ПИР'!$B$28+AB31*'"Вес" ПИР'!$B$29+AD31*'"Вес" ПИР'!$B$30+AF31*'"Вес" ПИР'!$B$31)/100 -> 0 | AJ31: на стадии подготовки | AP31: на стадии подготовки | AR31: на стадии подготовки | AT31: на стадии подготовки | BB31: =(AI31*'"Вес" ПИР'!$B$36+AK31*'"Вес" ПИР'!$B$37+AM31*'"Вес" ПИР'!$B$38+AO31*'"Вес" ПИР'!$B$39+AQ31*'"Вес" ПИР'!$B$40+AS31*'"Вес" ПИР'!$B$41+AU31*'"Вес" ПИР'!$B$42+AW31*'"Вес" ПИР'!$B$43+AY31*'"Вес" ПИР'!$B$44+BA31*'"Вес" ПИР'!$B$45)/100 -> 0 | BC31: на стадии подготовки | BE31: на стадии подготовки | BG31: =(BD31*'"Вес" ПИР'!$B$50+BF31*'"Вес" ПИР'!$B$51)/100 -> 0 | BI31: 0 | BK31: 46266 | BL31: =(S31*'"Вес" ПИР'!$B$3+X31*'"Вес" ПИР'!$B$4+AG31*'"Вес" ПИР'!$B$5+BB31*'"Вес" ПИР'!$B$6+BG31*'"Вес" ПИР'!$B$7+BI31*'"Вес" ПИР'!$B$8)/100 -> 0
B32: 2026 | C32: ТОО "5А Engineering" | D32: 115652400 | E32: Акмолинская область | F32: Зерендинский район | G32: Ортакский с.о. | H32: с.Кызылтан | I32: Имеется | K32: на стадии подготовки | M32: на стадии подготовки | O32: на стадии подготовки | Q32: на стадии подготовки | S32: =(J32*'"Вес" ПИР'!$B$13+L32*'"Вес" ПИР'!$B$14+N32*'"Вес" ПИР'!$B$15+P32*'"Вес" ПИР'!$B$16+R32*'"Вес" ПИР'!$B$17)/100 -> 0 | T32: 01.12.2025-30.03.2026 | V32: 01.12.2025-30.03.2026 | X32: =(U32*'"Вес" ПИР'!$B$22+W32*'"Вес" ПИР'!$B$23)/100 -> 0 | AG32: =(Z32*'"Вес" ПИР'!$B$28+AB32*'"Вес" ПИР'!$B$29+AD32*'"Вес" ПИР'!$B$30+AF32*'"Вес" ПИР'!$B$31)/100 -> 0 | AJ32: на стадии подготовки | AP32: на стадии подготовки | AR32: на стадии подготовки | AT32: на стадии подготовки | BB32: =(AI32*'"Вес" ПИР'!$B$36+AK32*'"Вес" ПИР'!$B$37+AM32*'"Вес" ПИР'!$B$38+AO32*'"Вес" ПИР'!$B$39+AQ32*'"Вес" ПИР'!$B$40+AS32*'"Вес" ПИР'!$B$41+AU32*'"Вес" ПИР'!$B$42+AW32*'"Вес" ПИР'!$B$43+AY32*'"Вес" ПИР'!$B$44+BA32*'"Вес" ПИР'!$B$45)/100 -> 0 | BC32: на стадии подготовки | BE32: на стадии подготовки | BG32: =(BD32*'"Вес" ПИР'!$B$50+BF32*'"Вес" ПИР'!$B$51)/100 -> 0 | BI32: 0 | BK32: 46266 | BL32: =(S32*'"Вес" ПИР'!$B$3+X32*'"Вес" ПИР'!$B$4+AG32*'"Вес" ПИР'!$B$5+BB32*'"Вес" ПИР'!$B$6+BG32*'"Вес" ПИР'!$B$7+BI32*'"Вес" ПИР'!$B$8)/100 -> 0
B33: 2026 | C33: ТОО "5А Engineering" | D33: 115653400 | E33: Акмолинская область | F33: Зерендинский район | G33: Приреченский с.о. | H33: с.Павловка | I33: Имеется | K33: на стадии подготовки | M33: на стадии подготовки | O33: на стадии подготовки | Q33: на стадии подготовки | S33: =(J33*'"Вес" ПИР'!$B$13+L33*'"Вес" ПИР'!$B$14+N33*'"Вес" ПИР'!$B$15+P33*'"Вес" ПИР'!$B$16+R33*'"Вес" ПИР'!$B$17)/100 -> 0 | T33: 01.12.2025-30.03.2026 | V33: 01.12.2025-30.03.2026 | X33: =(U33*'"Вес" ПИР'!$B$22+W33*'"Вес" ПИР'!$B$23)/100 -> 0 | AG33: =(Z33*'"Вес" ПИР'!$B$28+AB33*'"Вес" ПИР'!$B$29+AD33*'"Вес" ПИР'!$B$30+AF33*'"Вес" ПИР'!$B$31)/100 -> 0 | AJ33: на стадии подготовки | AP33: на стадии подготовки | AR33: на стадии подготовки | AT33: на стадии подготовки | BB33: =(AI33*'"Вес" ПИР'!$B$36+AK33*'"Вес" ПИР'!$B$37+AM33*'"Вес" ПИР'!$B$38+AO33*'"Вес" ПИР'!$B$39+AQ33*'"Вес" ПИР'!$B$40+AS33*'"Вес" ПИР'!$B$41+AU33*'"Вес" ПИР'!$B$42+AW33*'"Вес" ПИР'!$B$43+AY33*'"Вес" ПИР'!$B$44+BA33*'"Вес" ПИР'!$B$45)/100 -> 0 | BC33: на стадии подготовки | BE33: на стадии подготовки | BG33: =(BD33*'"Вес" ПИР'!$B$50+BF33*'"Вес" ПИР'!$B$51)/100 -> 0 | BI33: 0 | BK33: 46266 | BL33: =(S33*'"Вес" ПИР'!$B$3+X33*'"Вес" ПИР'!$B$4+AG33*'"Вес" ПИР'!$B$5+BB33*'"Вес" ПИР'!$B$6+BG33*'"Вес" ПИР'!$B$7+BI33*'"Вес" ПИР'!$B$8)/100 -> 0
B34: 2026 | C34: ТОО "5А Engineering" | D34: 115665400 | E34: Акмолинская область | F34: Зерендинский район | G34: с.о.им.Канай би | H34: с.Игилик | I34: Имеется | K34: на стадии подготовки | M34: на стадии подготовки | O34: на стадии подготовки | Q34: на стадии подготовки | S34: =(J34*'"Вес" ПИР'!$B$13+L34*'"Вес" ПИР'!$B$14+N34*'"Вес" ПИР'!$B$15+P34*'"Вес" ПИР'!$B$16+R34*'"Вес" ПИР'!$B$17)/100 -> 0 | T34: 01.12.2025-30.03.2026 | V34: 01.12.2025-30.03.2026 | X34: =(U34*'"Вес" ПИР'!$B$22+W34*'"Вес" ПИР'!$B$23)/100 -> 0 | AG34: =(Z34*'"Вес" ПИР'!$B$28+AB34*'"Вес" ПИР'!$B$29+AD34*'"Вес" ПИР'!$B$30+AF34*'"Вес" ПИР'!$B$31)/100 -> 0 | AJ34: на стадии подготовки | AP34: на стадии подготовки | AR34: на стадии подготовки | AT34: на стадии подготовки | BB34: =(AI34*'"Вес" ПИР'!$B$36+AK34*'"Вес" ПИР'!$B$37+AM34*'"Вес" ПИР'!$B$38+AO34*'"Вес" ПИР'!$B$39+AQ34*'"Вес" ПИР'!$B$40+AS34*'"Вес" ПИР'!$B$41+AU34*'"Вес" ПИР'!$B$42+AW34*'"Вес" ПИР'!$B$43+AY34*'"Вес" ПИР'!$B$44+BA34*'"Вес" ПИР'!$B$45)/100 -> 0 | BC34: на стадии подготовки | BE34: на стадии подготовки | BG34: =(BD34*'"Вес" ПИР'!$B$50+BF34*'"Вес" ПИР'!$B$51)/100 -> 0 | BI34: 0 | BK34: 46266 | BL34: =(S34*'"Вес" ПИР'!$B$3+X34*'"Вес" ПИР'!$B$4+AG34*'"Вес" ПИР'!$B$5+BB34*'"Вес" ПИР'!$B$6+BG34*'"Вес" ПИР'!$B$7+BI34*'"Вес" ПИР'!$B$8)/100 -> 0
B35: 2026 | C35: ТОО "5А Engineering" | D35: 115665100 | E35: Акмолинская область | F35: Зерендинский район | G35: с.о.им.Канай би | H35: с.Карауыл Канай-бия | I35: Имеется | K35: на стадии подготовки | M35: на стадии подготовки | O35: на стадии подготовки | Q35: на стадии подготовки | S35: =(J35*'"Вес" ПИР'!$B$13+L35*'"Вес" ПИР'!$B$14+N35*'"Вес" ПИР'!$B$15+P35*'"Вес" ПИР'!$B$16+R35*'"Вес" ПИР'!$B$17)/100 -> 0 | T35: 01.12.2025-30.03.2026 | V35: 01.12.2025-30.03.2026 | X35: =(U35*'"Вес" ПИР'!$B$22+W35*'"Вес" ПИР'!$B$23)/100 -> 0 | AG35: =(Z35*'"Вес" ПИР'!$B$28+AB35*'"Вес" ПИР'!$B$29+AD35*'"Вес" ПИР'!$B$30+AF35*'"Вес" ПИР'!$B$31)/100 -> 0 | AJ35: на стадии подготовки | AP35: на стадии подготовки | AR35: на стадии подготовки | AT35: на стадии подготовки | BB35: =(AI35*'"Вес" ПИР'!$B$36+AK35*'"Вес" ПИР'!$B$37+AM35*'"Вес" ПИР'!$B$38+AO35*'"Вес" ПИР'!$B$39+AQ35*'"Вес" ПИР'!$B$40+AS35*'"Вес" ПИР'!$B$41+AU35*'"Вес" ПИР'!$B$42+AW35*'"Вес" ПИР'!$B$43+AY35*'"Вес" ПИР'!$B$44+BA35*'"Вес" ПИР'!$B$45)/100 -> 0 | BC35: на стадии подготовки | BE35: на стадии подготовки | BG35: =(BD35*'"Вес" ПИР'!$B$50+BF35*'"Вес" ПИР'!$B$51)/100 -> 0 | BI35: 0 | BK35: 46266 | BL35: =(S35*'"Вес" ПИР'!$B$3+X35*'"Вес" ПИР'!$B$4+AG35*'"Вес" ПИР'!$B$5+BB35*'"Вес" ПИР'!$B$6+BG35*'"Вес" ПИР'!$B$7+BI35*'"Вес" ПИР'!$B$8)/100 -> 0
B36: 2026 | C36: ТОО "5А Engineering" | D36: 115673100 | E36: Акмолинская область | F36: Зерендинский район | G36: с.о.им.Сакена Сейфуллина | H36: с.Бирлестик | I36: Имеется | K36: на стадии подготовки | M36: на стадии подготовки | O36: на стадии подготовки | Q36: на стадии подготовки | S36: =(J36*'"Вес" ПИР'!$B$13+L36*'"Вес" ПИР'!$B$14+N36*'"Вес" ПИР'!$B$15+P36*'"Вес" ПИР'!$B$16+R36*'"Вес" ПИР'!$B$17)/100 -> 0 | T36: 01.12.2025-30.03.2026 | V36: 01.12.2025-30.03.2026 | X36: =(U36*'"Вес" ПИР'!$B$22+W36*'"Вес" ПИР'!$B$23)/100 -> 0 | AG36: =(Z36*'"Вес" ПИР'!$B$28+AB36*'"Вес" ПИР'!$B$29+AD36*'"Вес" ПИР'!$B$30+AF36*'"Вес" ПИР'!$B$31)/100 -> 0 | AJ36: на стадии подготовки | AP36: на стадии подготовки | AR36: на стадии подготовки | AT36: на стадии подготовки | BB36: =(AI36*'"Вес" ПИР'!$B$36+AK36*'"Вес" ПИР'!$B$37+AM36*'"Вес" ПИР'!$B$38+AO36*'"Вес" ПИР'!$B$39+AQ36*'"Вес" ПИР'!$B$40+AS36*'"Вес" ПИР'!$B$41+AU36*'"Вес" ПИР'!$B$42+AW36*'"Вес" ПИР'!$B$43+AY36*'"Вес" ПИР'!$B$44+BA36*'"Вес" ПИР'!$B$45)/100 -> 0 | BC36: на стадии подготовки | BE36: на стадии подготовки | BG36: =(BD36*'"Вес" ПИР'!$B$50+BF36*'"Вес" ПИР'!$B$51)/100 -> 0 | BI36: 0 | BK36: 46266 | BL36: =(S36*'"Вес" ПИР'!$B$3+X36*'"Вес" ПИР'!$B$4+AG36*'"Вес" ПИР'!$B$5+BB36*'"Вес" ПИР'!$B$6+BG36*'"Вес" ПИР'!$B$7+BI36*'"Вес" ПИР'!$B$8)/100 -> 0
B37: 2026 | C37: ТОО "5А Engineering" | D37: 115673500 | E37: Акмолинская область | F37: Зерендинский район | G37: с.о.им.Сакена Сейфуллина | H37: с.Сейфуллино | I37: Имеется | K37: на стадии подготовки | M37: на стадии подготовки | O37: на стадии подготовки | Q37: на стадии подготовки | S37: =(J37*'"Вес" ПИР'!$B$13+L37*'"Вес" ПИР'!$B$14+N37*'"Вес" ПИР'!$B$15+P37*'"Вес" ПИР'!$B$16+R37*'"Вес" ПИР'!$B$17)/100 -> 0 | T37: 01.12.2025-30.03.2026 | V37: 01.12.2025-30.03.2026 | X37: =(U37*'"Вес" ПИР'!$B$22+W37*'"Вес" ПИР'!$B$23)/100 -> 0 | AG37: =(Z37*'"Вес" ПИР'!$B$28+AB37*'"Вес" ПИР'!$B$29+AD37*'"Вес" ПИР'!$B$30+AF37*'"Вес" ПИР'!$B$31)/100 -> 0 | AJ37: на стадии подготовки | AP37: на стадии подготовки | AR37: на стадии подготовки | AT37: на стадии подготовки | BB37: =(AI37*'"Вес" ПИР'!$B$36+AK37*'"Вес" ПИР'!$B$37+AM37*'"Вес" ПИР'!$B$38+AO37*'"Вес" ПИР'!$B$39+AQ37*'"Вес" ПИР'!$B$40+AS37*'"Вес" ПИР'!$B$41+AU37*'"Вес" ПИР'!$B$42+AW37*'"Вес" ПИР'!$B$43+AY37*'"Вес" ПИР'!$B$44+BA37*'"Вес" ПИР'!$B$45)/100 -> 0 | BC37: на стадии подготовки | BE37: на стадии подготовки | BG37: =(BD37*'"Вес" ПИР'!$B$50+BF37*'"Вес" ПИР'!$B$51)/100 -> 0 | BI37: 0 | BK37: 46266 | BL37: =(S37*'"Вес" ПИР'!$B$3+X37*'"Вес" ПИР'!$B$4+AG37*'"Вес" ПИР'!$B$5+BB37*'"Вес" ПИР'!$B$6+BG37*'"Вес" ПИР'!$B$7+BI37*'"Вес" ПИР'!$B$8)/100 -> 0
B38: 2026 | C38: ТОО "5А Engineering" | D38: 115655100 | E38: Акмолинская область | F38: Зерендинский район | G38: с.о.Малика Габдуллина | H38: с.Малика Габдуллина | I38: Имеется | K38: на стадии подготовки | M38: на стадии подготовки | O38: на стадии подготовки | Q38: на стадии подготовки | S38: =(J38*'"Вес" ПИР'!$B$13+L38*'"Вес" ПИР'!$B$14+N38*'"Вес" ПИР'!$B$15+P38*'"Вес" ПИР'!$B$16+R38*'"Вес" ПИР'!$B$17)/100 -> 0 | T38: 01.12.2025-30.03.2026 | V38: 01.12.2025-30.03.2026 | X38: =(U38*'"Вес" ПИР'!$B$22+W38*'"Вес" ПИР'!$B$23)/100 -> 0 | AG38: =(Z38*'"Вес" ПИР'!$B$28+AB38*'"Вес" ПИР'!$B$29+AD38*'"Вес" ПИР'!$B$30+AF38*'"Вес" ПИР'!$B$31)/100 -> 0 | AJ38: на стадии подготовки | AP38: на стадии подготовки | AR38: на стадии подготовки | AT38: на стадии подготовки | BB38: =(AI38*'"Вес" ПИР'!$B$36+AK38*'"Вес" ПИР'!$B$37+AM38*'"Вес" ПИР'!$B$38+AO38*'"Вес" ПИР'!$B$39+AQ38*'"Вес" ПИР'!$B$40+AS38*'"Вес" ПИР'!$B$41+AU38*'"Вес" ПИР'!$B$42+AW38*'"Вес" ПИР'!$B$43+AY38*'"Вес" ПИР'!$B$44+BA38*'"Вес" ПИР'!$B$45)/100 -> 0 | BC38: на стадии подготовки | BE38: на стадии подготовки | BG38: =(BD38*'"Вес" ПИР'!$B$50+BF38*'"Вес" ПИР'!$B$51)/100 -> 0 | BI38: 0 | BK38: 46266 | BL38: =(S38*'"Вес" ПИР'!$B$3+X38*'"Вес" ПИР'!$B$4+AG38*'"Вес" ПИР'!$B$5+BB38*'"Вес" ПИР'!$B$6+BG38*'"Вес" ПИР'!$B$7+BI38*'"Вес" ПИР'!$B$8)/100 -> 0
B39: 2026 | C39: ТОО "5А Engineering" | D39: 115671200 | E39: Акмолинская область | F39: Зерендинский район | G39: Садовый с.о. | H39: с.Еликти | I39: Имеется | K39: на стадии подготовки | M39: на стадии подготовки | O39: на стадии подготовки | Q39: на стадии подготовки | S39: =(J39*'"Вес" ПИР'!$B$13+L39*'"Вес" ПИР'!$B$14+N39*'"Вес" ПИР'!$B$15+P39*'"Вес" ПИР'!$B$16+R39*'"Вес" ПИР'!$B$17)/100 -> 0 | T39: 01.12.2025-30.03.2026 | V39: 01.12.2025-30.03.2026 | X39: =(U39*'"Вес" ПИР'!$B$22+W39*'"Вес" ПИР'!$B$23)/100 -> 0 | AG39: =(Z39*'"Вес" ПИР'!$B$28+AB39*'"Вес" ПИР'!$B$29+AD39*'"Вес" ПИР'!$B$30+AF39*'"Вес" ПИР'!$B$31)/100 -> 0 | AJ39: на стадии подготовки | AP39: на стадии подготовки | AR39: на стадии подготовки | AT39: на стадии подготовки | BB39: =(AI39*'"Вес" ПИР'!$B$36+AK39*'"Вес" ПИР'!$B$37+AM39*'"Вес" ПИР'!$B$38+AO39*'"Вес" ПИР'!$B$39+AQ39*'"Вес" ПИР'!$B$40+AS39*'"Вес" ПИР'!$B$41+AU39*'"Вес" ПИР'!$B$42+AW39*'"Вес" ПИР'!$B$43+AY39*'"Вес" ПИР'!$B$44+BA39*'"Вес" ПИР'!$B$45)/100 -> 0 | BC39: на стадии подготовки | BE39: на стадии подготовки | BG39: =(BD39*'"Вес" ПИР'!$B$50+BF39*'"Вес" ПИР'!$B$51)/100 -> 0 | BI39: 0 | BK39: 46266 | BL39: =(S39*'"Вес" ПИР'!$B$3+X39*'"Вес" ПИР'!$B$4+AG39*'"Вес" ПИР'!$B$5+BB39*'"Вес" ПИР'!$B$6+BG39*'"Вес" ПИР'!$B$7+BI39*'"Вес" ПИР'!$B$8)/100 -> 0
B40: 2026 | C40: ТОО "5А Engineering" | D40: 115671300 | E40: Акмолинская область | F40: Зерендинский район | G40: Садовый с.о. | H40: с.Заречное | I40: Имеется | K40: на стадии подготовки | M40: на стадии подготовки | O40: на стадии подготовки | Q40: на стадии подготовки | S40: =(J40*'"Вес" ПИР'!$B$13+L40*'"Вес" ПИР'!$B$14+N40*'"Вес" ПИР'!$B$15+P40*'"Вес" ПИР'!$B$16+R40*'"Вес" ПИР'!$B$17)/100 -> 0 | T40: 01.12.2025-30.03.2026 | V40: 01.12.2025-30.03.2026 | X40: =(U40*'"Вес" ПИР'!$B$22+W40*'"Вес" ПИР'!$B$23)/100 -> 0 | AG40: =(Z40*'"Вес" ПИР'!$B$28+AB40*'"Вес" ПИР'!$B$29+AD40*'"Вес" ПИР'!$B$30+AF40*'"Вес" ПИР'!$B$31)/100 -> 0 | AJ40: на стадии подготовки | AP40: на стадии подготовки | AR40: на стадии подготовки | AT40: на стадии подготовки | BB40: =(AI40*'"Вес" ПИР'!$B$36+AK40*'"Вес" ПИР'!$B$37+AM40*'"Вес" ПИР'!$B$38+AO40*'"Вес" ПИР'!$B$39+AQ40*'"Вес" ПИР'!$B$40+AS40*'"Вес" ПИР'!$B$41+AU40*'"Вес" ПИР'!$B$42+AW40*'"Вес" ПИР'!$B$43+AY40*'"Вес" ПИР'!$B$44+BA40*'"Вес" ПИР'!$B$45)/100 -> 0 | BC40: на стадии подготовки | BE40: на стадии подготовки | BG40: =(BD40*'"Вес" ПИР'!$B$50+BF40*'"Вес" ПИР'!$B$51)/100 -> 0 | BI40: 0 | BK40: 46266 | BL40: =(S40*'"Вес" ПИР'!$B$3+X40*'"Вес" ПИР'!$B$4+AG40*'"Вес" ПИР'!$B$5+BB40*'"Вес" ПИР'!$B$6+BG40*'"Вес" ПИР'!$B$7+BI40*'"Вес" ПИР'!$B$8)/100 -> 0
B41: 2026 | C41: ТОО "5А Engineering" | D41: 115658400 | E41: Акмолинская область | F41: Зерендинский район | G41: Троицкий с.о. | H41: с.Карсак | I41: Имеется | K41: на стадии подготовки | M41: на стадии подготовки | O41: на стадии подготовки | Q41: на стадии подготовки | S41: =(J41*'"Вес" ПИР'!$B$13+L41*'"Вес" ПИР'!$B$14+N41*'"Вес" ПИР'!$B$15+P41*'"Вес" ПИР'!$B$16+R41*'"Вес" ПИР'!$B$17)/100 -> 0 | T41: 01.12.2025-30.03.2026 | V41: 01.12.2025-30.03.2026 | X41: =(U41*'"Вес" ПИР'!$B$22+W41*'"Вес" ПИР'!$B$23)/100 -> 0 | AG41: =(Z41*'"Вес" ПИР'!$B$28+AB41*'"Вес" ПИР'!$B$29+AD41*'"Вес" ПИР'!$B$30+AF41*'"Вес" ПИР'!$B$31)/100 -> 0 | AJ41: на стадии подготовки | AP41: на стадии подготовки | AR41: на стадии подготовки | AT41: на стадии подготовки | BB41: =(AI41*'"Вес" ПИР'!$B$36+AK41*'"Вес" ПИР'!$B$37+AM41*'"Вес" ПИР'!$B$38+AO41*'"Вес" ПИР'!$B$39+AQ41*'"Вес" ПИР'!$B$40+AS41*'"Вес" ПИР'!$B$41+AU41*'"Вес" ПИР'!$B$42+AW41*'"Вес" ПИР'!$B$43+AY41*'"Вес" ПИР'!$B$44+BA41*'"Вес" ПИР'!$B$45)/100 -> 0 | BC41: на стадии подготовки | BE41: на стадии подготовки | BG41: =(BD41*'"Вес" ПИР'!$B$50+BF41*'"Вес" ПИР'!$B$51)/100 -> 0 | BI41: 0 | BK41: 46266 | BL41: =(S41*'"Вес" ПИР'!$B$3+X41*'"Вес" ПИР'!$B$4+AG41*'"Вес" ПИР'!$B$5+BB41*'"Вес" ПИР'!$B$6+BG41*'"Вес" ПИР'!$B$7+BI41*'"Вес" ПИР'!$B$8)/100 -> 0
B42: 2026 | C42: ТОО "5А Engineering" | D42: 115658500 | E42: Акмолинская область | F42: Зерендинский район | G42: Троицкий с.о. | H42: с.Кошкарбай | I42: Имеется | K42: на стадии подготовки | M42: на стадии подготовки | O42: на стадии подготовки | Q42: на стадии подготовки | S42: =(J42*'"Вес" ПИР'!$B$13+L42*'"Вес" ПИР'!$B$14+N42*'"Вес" ПИР'!$B$15+P42*'"Вес" ПИР'!$B$16+R42*'"Вес" ПИР'!$B$17)/100 -> 0 | T42: 01.12.2025-30.03.2026 | V42: 01.12.2025-30.03.2026 | X42: =(U42*'"Вес" ПИР'!$B$22+W42*'"Вес" ПИР'!$B$23)/100 -> 0 | AG42: =(Z42*'"Вес" ПИР'!$B$28+AB42*'"Вес" ПИР'!$B$29+AD42*'"Вес" ПИР'!$B$30+AF42*'"Вес" ПИР'!$B$31)/100 -> 0 | AJ42: на стадии подготовки | AP42: на стадии подготовки | AR42: на стадии подготовки | AT42: на стадии подготовки | BB42: =(AI42*'"Вес" ПИР'!$B$36+AK42*'"Вес" ПИР'!$B$37+AM42*'"Вес" ПИР'!$B$38+AO42*'"Вес" ПИР'!$B$39+AQ42*'"Вес" ПИР'!$B$40+AS42*'"Вес" ПИР'!$B$41+AU42*'"Вес" ПИР'!$B$42+AW42*'"Вес" ПИР'!$B$43+AY42*'"Вес" ПИР'!$B$44+BA42*'"Вес" ПИР'!$B$45)/100 -> 0 | BC42: на стадии подготовки | BE42: на стадии подготовки | BG42: =(BD42*'"Вес" ПИР'!$B$50+BF42*'"Вес" ПИР'!$B$51)/100 -> 0 | BI42: 0 | BK42: 46266 | BL42: =(S42*'"Вес" ПИР'!$B$3+X42*'"Вес" ПИР'!$B$4+AG42*'"Вес" ПИР'!$B$5+BB42*'"Вес" ПИР'!$B$6+BG42*'"Вес" ПИР'!$B$7+BI42*'"Вес" ПИР'!$B$8)/100 -> 0
... B91: 2026 | C91: ТОО "5А Engineering" | D91: 114641200 | E91: Акмолинская область | F91: Ерейментауский район | G91: Тайбайский с.о. | H91: с. Ельтай | I91: Имеется | K91: на стадии подготовки | M91: на стадии подготовки | O91: на стадии подготовки | Q91: на стадии подготовки | S91: =(J91*'"Вес" ПИР'!$B$13+L91*'"Вес" ПИР'!$B$14+N91*'"Вес" ПИР'!$B$15+P91*'"Вес" ПИР'!$B$16+R91*'"Вес" ПИР'!$B$17)/100 -> 0 | T91: Готово | V91: Готово | X91: =(U91*'"Вес" ПИР'!$B$22+W91*'"Вес" ПИР'!$B$23)/100 -> 0 | AG91: =(Z91*'"Вес" ПИР'!$B$28+AB91*'"Вес" ПИР'!$B$29+AD91*'"Вес" ПИР'!$B$30+AF91*'"Вес" ПИР'!$B$31)/100 -> 0 | AJ91: на стадии подготовки | AP91: на стадии подготовки | AR91: на стадии подготовки | AT91: на стадии подготовки | BB91: =(AI91*'"Вес" ПИР'!$B$36+AK91*'"Вес" ПИР'!$B$37+AM91*'"Вес" ПИР'!$B$38+AO91*'"Вес" ПИР'!$B$39+AQ91*'"Вес" ПИР'!$B$40+AS91*'"Вес" ПИР'!$B$41+AU91*'"Вес" ПИР'!$B$42+AW91*'"Вес" ПИР'!$B$43+AY91*'"Вес" ПИР'!$B$44+BA91*'"Вес" ПИР'!$B$45)/100 -> 0 | BC91: на стадии подготовки | BE91: на стадии подготовки | BG91: =(BD91*'"Вес" ПИР'!$B$50+BF91*'"Вес" ПИР'!$B$51)/100 -> 0 | BI91: 0 | BK91: 46218 | BL91: =(S91*'"Вес" ПИР'!$B$3+X91*'"Вес" ПИР'!$B$4+AG91*'"Вес" ПИР'!$B$5+BB91*'"Вес" ПИР'!$B$6+BG91*'"Вес" ПИР'!$B$7+BI91*'"Вес" ПИР'!$B$8)/100 -> 0
B92: 2026 | C92: ТОО "5А Engineering" | D92: 114857400 | E92: Акмолинская область | F92: Есильский район | G92: Красивинский с.о. | H92: с.Ленинское | I92: Имеется | K92: на стадии подготовки | M92: на стадии подготовки | O92: на стадии подготовки | Q92: на стадии подготовки | S92: =(J92*'"Вес" ПИР'!$B$13+L92*'"Вес" ПИР'!$B$14+N92*'"Вес" ПИР'!$B$15+P92*'"Вес" ПИР'!$B$16+R92*'"Вес" ПИР'!$B$17)/100 -> 0 | T92: Готово | V92: Готово | X92: =(U92*'"Вес" ПИР'!$B$22+W92*'"Вес" ПИР'!$B$23)/100 -> 0 | AG92: =(Z92*'"Вес" ПИР'!$B$28+AB92*'"Вес" ПИР'!$B$29+AD92*'"Вес" ПИР'!$B$30+AF92*'"Вес" ПИР'!$B$31)/100 -> 0 | AJ92: на стадии подготовки | AP92: на стадии подготовки | AR92: на стадии подготовки | AT92: на стадии подготовки | BB92: =(AI92*'"Вес" ПИР'!$B$36+AK92*'"Вес" ПИР'!$B$37+AM92*'"Вес" ПИР'!$B$38+AO92*'"Вес" ПИР'!$B$39+AQ92*'"Вес" ПИР'!$B$40+AS92*'"Вес" ПИР'!$B$41+AU92*'"Вес" ПИР'!$B$42+AW92*'"Вес" ПИР'!$B$43+AY92*'"Вес" ПИР'!$B$44+BA92*'"Вес" ПИР'!$B$45)/100 -> 0 | BC92: на стадии подготовки | BE92: на стадии подготовки | BG92: =(BD92*'"Вес" ПИР'!$B$50+BF92*'"Вес" ПИР'!$B$51)/100 -> 0 | BI92: 0 | BK92: 31.09.2026 | BL92: =(S92*'"Вес" ПИР'!$B$3+X92*'"Вес" ПИР'!$B$4+AG92*'"Вес" ПИР'!$B$5+BB92*'"Вес" ПИР'!$B$6+BG92*'"Вес" ПИР'!$B$7+BI92*'"Вес" ПИР'!$B$8)/100 -> 0
B93: 2026 | C93: ТОО "5А Engineering" | D93: 114857700 | E93: Акмолинская область | F93: Есильский район | G93: Красивинский с.о. | H93: с.Ярославка | I93: Имеется | K93: на стадии подготовки | M93: на стадии подготовки | O93: на стадии подготовки | Q93: на стадии подготовки | S93: =(J93*'"Вес" ПИР'!$B$13+L93*'"Вес" ПИР'!$B$14+N93*'"Вес" ПИР'!$B$15+P93*'"Вес" ПИР'!$B$16+R93*'"Вес" ПИР'!$B$17)/100 -> 0 | T93: Готово | V93: Готово | X93: =(U93*'"Вес" ПИР'!$B$22+W93*'"Вес" ПИР'!$B$23)/100 -> 0 | AG93: =(Z93*'"Вес" ПИР'!$B$28+AB93*'"Вес" ПИР'!$B$29+AD93*'"Вес" ПИР'!$B$30+AF93*'"Вес" ПИР'!$B$31)/100 -> 0 | AJ93: на стадии подготовки | AP93: на стадии подготовки | AR93: на стадии подготовки | AT93: на стадии подготовки | BB93: =(AI93*'"Вес" ПИР'!$B$36+AK93*'"Вес" ПИР'!$B$37+AM93*'"Вес" ПИР'!$B$38+AO93*'"Вес" ПИР'!$B$39+AQ93*'"Вес" ПИР'!$B$40+AS93*'"Вес" ПИР'!$B$41+AU93*'"Вес" ПИР'!$B$42+AW93*'"Вес" ПИР'!$B$43+AY93*'"Вес" ПИР'!$B$44+BA93*'"Вес" ПИР'!$B$45)/100 -> 0 | BC93: на стадии подготовки | BE93: на стадии подготовки | BG93: =(BD93*'"Вес" ПИР'!$B$50+BF93*'"Вес" ПИР'!$B$51)/100 -> 0 | BI93: 0 | BK93: 31.09.2026 | BL93: =(S93*'"Вес" ПИР'!$B$3+X93*'"Вес" ПИР'!$B$4+AG93*'"Вес" ПИР'!$B$5+BB93*'"Вес" ПИР'!$B$6+BG93*'"Вес" ПИР'!$B$7+BI93*'"Вес" ПИР'!$B$8)/100 -> 0
B94: 2026 | C94: ТОО "5А Engineering" | D94: 114873300 | E94: Акмолинская область | F94: Есильский район | G94: Свободненский с.о. | H94: с.Раздольное | I94: Имеется | K94: на стадии подготовки | M94: на стадии подготовки | O94: на стадии подготовки | Q94: на стадии подготовки | S94: =(J94*'"Вес" ПИР'!$B$13+L94*'"Вес" ПИР'!$B$14+N94*'"Вес" ПИР'!$B$15+P94*'"Вес" ПИР'!$B$16+R94*'"Вес" ПИР'!$B$17)/100 -> 0 | T94: Готово | V94: Готово | X94: =(U94*'"Вес" ПИР'!$B$22+W94*'"Вес" ПИР'!$B$23)/100 -> 0 | AG94: =(Z94*'"Вес" ПИР'!$B$28+AB94*'"Вес" ПИР'!$B$29+AD94*'"Вес" ПИР'!$B$30+AF94*'"Вес" ПИР'!$B$31)/100 -> 0 | AJ94: на стадии подготовки | AP94: на стадии подготовки | AR94: на стадии подготовки | AT94: на стадии подготовки | BB94: =(AI94*'"Вес" ПИР'!$B$36+AK94*'"Вес" ПИР'!$B$37+AM94*'"Вес" ПИР'!$B$38+AO94*'"Вес" ПИР'!$B$39+AQ94*'"Вес" ПИР'!$B$40+AS94*'"Вес" ПИР'!$B$41+AU94*'"Вес" ПИР'!$B$42+AW94*'"Вес" ПИР'!$B$43+AY94*'"Вес" ПИР'!$B$44+BA94*'"Вес" ПИР'!$B$45)/100 -> 0 | BC94: на стадии подготовки | BE94: на стадии подготовки | BG94: =(BD94*'"Вес" ПИР'!$B$50+BF94*'"Вес" ПИР'!$B$51)/100 -> 0 | BI94: 0 | BK94: 31.09.2026 | BL94: =(S94*'"Вес" ПИР'!$B$3+X94*'"Вес" ПИР'!$B$4+AG94*'"Вес" ПИР'!$B$5+BB94*'"Вес" ПИР'!$B$6+BG94*'"Вес" ПИР'!$B$7+BI94*'"Вес" ПИР'!$B$8)/100 -> 0
B95: 2026 | C95: ТОО "5А Engineering" | D95: 114859300 | E95: Акмолинская область | F95: Есильский район | G95: Красногорский с.о | H95: с. Калачи | I95: Имеется | K95: на стадии подготовки | M95: на стадии подготовки | O95: на стадии подготовки | Q95: на стадии подготовки | S95: =(J95*'"Вес" ПИР'!$B$13+L95*'"Вес" ПИР'!$B$14+N95*'"Вес" ПИР'!$B$15+P95*'"Вес" ПИР'!$B$16+R95*'"Вес" ПИР'!$B$17)/100 -> 0 | T95: Готово | V95: Готово | X95: =(U95*'"Вес" ПИР'!$B$22+W95*'"Вес" ПИР'!$B$23)/100 -> 0 | AG95: =(Z95*'"Вес" ПИР'!$B$28+AB95*'"Вес" ПИР'!$B$29+AD95*'"Вес" ПИР'!$B$30+AF95*'"Вес" ПИР'!$B$31)/100 -> 0 | AJ95: на стадии подготовки | AP95: на стадии подготовки | AR95: на стадии подготовки | AT95: на стадии подготовки | BB95: =(AI95*'"Вес" ПИР'!$B$36+AK95*'"Вес" ПИР'!$B$37+AM95*'"Вес" ПИР'!$B$38+AO95*'"Вес" ПИР'!$B$39+AQ95*'"Вес" ПИР'!$B$40+AS95*'"Вес" ПИР'!$B$41+AU95*'"Вес" ПИР'!$B$42+AW95*'"Вес" ПИР'!$B$43+AY95*'"Вес" ПИР'!$B$44+BA95*'"Вес" ПИР'!$B$45)/100 -> 0 | BC95: на стадии подготовки | BE95: на стадии подготовки | BG95: =(BD95*'"Вес" ПИР'!$B$50+BF95*'"Вес" ПИР'!$B$51)/100 -> 0 | BI95: 0 | BK95: 31.09.2026 | BL95: =(S95*'"Вес" ПИР'!$B$3+X95*'"Вес" ПИР'!$B$4+AG95*'"Вес" ПИР'!$B$5+BB95*'"Вес" ПИР'!$B$6+BG95*'"Вес" ПИР'!$B$7+BI95*'"Вес" ПИР'!$B$8)/100 -> 0
B96: 2026 | C96: ТОО "5А Engineering" | D96: 114879100 | E96: Акмолинская область | F96: Есильский район | G96: Интернациональный с.о. | H96: с. Интернациональное | I96: Имеется | K96: на стадии подготовки | M96: на стадии подготовки | O96: на стадии подготовки | Q96: на стадии подготовки | S96: =(J96*'"Вес" ПИР'!$B$13+L96*'"Вес" ПИР'!$B$14+N96*'"Вес" ПИР'!$B$15+P96*'"Вес" ПИР'!$B$16+R96*'"Вес" ПИР'!$B$17)/100 -> 0 | T96: Готово | V96: Готово | X96: =(U96*'"Вес" ПИР'!$B$22+W96*'"Вес" ПИР'!$B$23)/100 -> 0 | AG96: =(Z96*'"Вес" ПИР'!$B$28+AB96*'"Вес" ПИР'!$B$29+AD96*'"Вес" ПИР'!$B$30+AF96*'"Вес" ПИР'!$B$31)/100 -> 0 | AJ96: на стадии подготовки | AP96: на стадии подготовки | AR96: на стадии подготовки | AT96: на стадии подготовки | BB96: =(AI96*'"Вес" ПИР'!$B$36+AK96*'"Вес" ПИР'!$B$37+AM96*'"Вес" ПИР'!$B$38+AO96*'"Вес" ПИР'!$B$39+AQ96*'"Вес" ПИР'!$B$40+AS96*'"Вес" ПИР'!$B$41+AU96*'"Вес" ПИР'!$B$42+AW96*'"Вес" ПИР'!$B$43+AY96*'"Вес" ПИР'!$B$44+BA96*'"Вес" ПИР'!$B$45)/100 -> 0 | BC96: на стадии подготовки | BE96: на стадии подготовки | BG96: =(BD96*'"Вес" ПИР'!$B$50+BF96*'"Вес" ПИР'!$B$51)/100 -> 0 | BI96: 0 | BK96: 31.09.2026 | BL96: =(S96*'"Вес" ПИР'!$B$3+X96*'"Вес" ПИР'!$B$4+AG96*'"Вес" ПИР'!$B$5+BB96*'"Вес" ПИР'!$B$6+BG96*'"Вес" ПИР'!$B$7+BI96*'"Вес" ПИР'!$B$8)/100 -> 0
B97: 2026 | C97: ТОО "5А Engineering" | D97: 115633200 | E97: Акмолинская область | F97: Зерендинский район | G97: Аккольский с.о. | H97: с.Ивановка | I97: Имеется | K97: на стадии подготовки | M97: на стадии подготовки | O97: на стадии подготовки | Q97: на стадии подготовки | S97: =(J97*'"Вес" ПИР'!$B$13+L97*'"Вес" ПИР'!$B$14+N97*'"Вес" ПИР'!$B$15+P97*'"Вес" ПИР'!$B$16+R97*'"Вес" ПИР'!$B$17)/100 -> 0 | T97: 01.12.2025-30.03.2026 | V97: 01.12.2025-30.03.2026 | X97: =(U97*'"Вес" ПИР'!$B$22+W97*'"Вес" ПИР'!$B$23)/100 -> 0 | AG97: =(Z97*'"Вес" ПИР'!$B$28+AB97*'"Вес" ПИР'!$B$29+AD97*'"Вес" ПИР'!$B$30+AF97*'"Вес" ПИР'!$B$31)/100 -> 0 | AJ97: на стадии подготовки | AP97: на стадии подготовки | AR97: на стадии подготовки | AT97: на стадии подготовки | BB97: =(AI97*'"Вес" ПИР'!$B$36+AK97*'"Вес" ПИР'!$B$37+AM97*'"Вес" ПИР'!$B$38+AO97*'"Вес" ПИР'!$B$39+AQ97*'"Вес" ПИР'!$B$40+AS97*'"Вес" ПИР'!$B$41+AU97*'"Вес" ПИР'!$B$42+AW97*'"Вес" ПИР'!$B$43+AY97*'"Вес" ПИР'!$B$44+BA97*'"Вес" ПИР'!$B$45)/100 -> 0 | BC97: на стадии подготовки | BE97: на стадии подготовки | BG97: =(BD97*'"Вес" ПИР'!$B$50+BF97*'"Вес" ПИР'!$B$51)/100 -> 0 | BI97: 0 | BK97: 46266 | BL97: =(S97*'"Вес" ПИР'!$B$3+X97*'"Вес" ПИР'!$B$4+AG97*'"Вес" ПИР'!$B$5+BB97*'"Вес" ПИР'!$B$6+BG97*'"Вес" ПИР'!$B$7+BI97*'"Вес" ПИР'!$B$8)/100 -> 0
B98: 2026 | C98: ТОО "5А Engineering" | D98: 115633300 | E98: Акмолинская область | F98: Зерендинский район | G98: Аккольский с.о. | H98: с.Казахстан | I98: Имеется | K98: на стадии подготовки | M98: на стадии подготовки | O98: на стадии подготовки | Q98: на стадии подготовки | S98: =(J98*'"Вес" ПИР'!$B$13+L98*'"Вес" ПИР'!$B$14+N98*'"Вес" ПИР'!$B$15+P98*'"Вес" ПИР'!$B$16+R98*'"Вес" ПИР'!$B$17)/100 -> 0 | T98: 01.12.2025-30.03.2026 | V98: 01.12.2025-30.03.2026 | X98: =(U98*'"Вес" ПИР'!$B$22+W98*'"Вес" ПИР'!$B$23)/100 -> 0 | AG98: =(Z98*'"Вес" ПИР'!$B$28+AB98*'"Вес" ПИР'!$B$29+AD98*'"Вес" ПИР'!$B$30+AF98*'"Вес" ПИР'!$B$31)/100 -> 0 | AJ98: на стадии подготовки | AP98: на стадии подготовки | AR98: на стадии подготовки | AT98: на стадии подготовки | BB98: =(AI98*'"Вес" ПИР'!$B$36+AK98*'"Вес" ПИР'!$B$37+AM98*'"Вес" ПИР'!$B$38+AO98*'"Вес" ПИР'!$B$39+AQ98*'"Вес" ПИР'!$B$40+AS98*'"Вес" ПИР'!$B$41+AU98*'"Вес" ПИР'!$B$42+AW98*'"Вес" ПИР'!$B$43+AY98*'"Вес" ПИР'!$B$44+BA98*'"Вес" ПИР'!$B$45)/100 -> 0 | BC98: на стадии подготовки | BE98: на стадии подготовки | BG98: =(BD98*'"Вес" ПИР'!$B$50+BF98*'"Вес" ПИР'!$B$51)/100 -> 0 | BI98: 0 | BK98: 46266 | BL98: =(S98*'"Вес" ПИР'!$B$3+X98*'"Вес" ПИР'!$B$4+AG98*'"Вес" ПИР'!$B$5+BB98*'"Вес" ПИР'!$B$6+BG98*'"Вес" ПИР'!$B$7+BI98*'"Вес" ПИР'!$B$8)/100 -> 0
B99: 2026 | C99: ТОО "5А Engineering" | D99: 115633400 | E99: Акмолинская область | F99: Зерендинский район | G99: Аккольский с.о. | H99: с.Молодежное | I99: Имеется | K99: на стадии подготовки | M99: на стадии подготовки | O99: на стадии подготовки | Q99: на стадии подготовки | S99: =(J99*'"Вес" ПИР'!$B$13+L99*'"Вес" ПИР'!$B$14+N99*'"Вес" ПИР'!$B$15+P99*'"Вес" ПИР'!$B$16+R99*'"Вес" ПИР'!$B$17)/100 -> 0 | T99: 01.12.2025-30.03.2026 | V99: 01.12.2025-30.03.2026 | X99: =(U99*'"Вес" ПИР'!$B$22+W99*'"Вес" ПИР'!$B$23)/100 -> 0 | AG99: =(Z99*'"Вес" ПИР'!$B$28+AB99*'"Вес" ПИР'!$B$29+AD99*'"Вес" ПИР'!$B$30+AF99*'"Вес" ПИР'!$B$31)/100 -> 0 | AJ99: на стадии подготовки | AP99: на стадии подготовки | AR99: на стадии подготовки | AT99: на стадии подготовки | BB99: =(AI99*'"Вес" ПИР'!$B$36+AK99*'"Вес" ПИР'!$B$37+AM99*'"Вес" ПИР'!$B$38+AO99*'"Вес" ПИР'!$B$39+AQ99*'"Вес" ПИР'!$B$40+AS99*'"Вес" ПИР'!$B$41+AU99*'"Вес" ПИР'!$B$42+AW99*'"Вес" ПИР'!$B$43+AY99*'"Вес" ПИР'!$B$44+BA99*'"Вес" ПИР'!$B$45)/100 -> 0 | BC99: на стадии подготовки | BE99: на стадии подготовки | BG99: =(BD99*'"Вес" ПИР'!$B$50+BF99*'"Вес" ПИР'!$B$51)/100 -> 0 | BI99: 0 | BK99: 46266 | BL99: =(S99*'"Вес" ПИР'!$B$3+X99*'"Вес" ПИР'!$B$4+AG99*'"Вес" ПИР'!$B$5+BB99*'"Вес" ПИР'!$B$6+BG99*'"Вес" ПИР'!$B$7+BI99*'"Вес" ПИР'!$B$8)/100 -> 0
B100: 2026 | C100: ТОО "5А Engineering" | D100: 115652100 | E100: Акмолинская область | F100: Зерендинский район | G100: Ортакский с.о. | H100: с.Ортак | I100: Имеется | K100: на стадии подготовки | M100: на стадии подготовки | O100: на стадии подготовки | Q100: на стадии подготовки | S100: =(J100*'"Вес" ПИР'!$B$13+L100*'"Вес" ПИР'!$B$14+N100*'"Вес" ПИР'!$B$15+P100*'"Вес" ПИР'!$B$16+R100*'"Вес" ПИР'!$B$17)/100 -> 0 | T100: 01.12.2025-30.03.2026 | V100: 01.12.2025-30.03.2026 | X100: =(U100*'"Вес" ПИР'!$B$22+W100*'"Вес" ПИР'!$B$23)/100 -> 0 | AG100: =(Z100*'"Вес" ПИР'!$B$28+AB100*'"Вес" ПИР'!$B$29+AD100*'"Вес" ПИР'!$B$30+AF100*'"Вес" ПИР'!$B$31)/100 -> 0 | AJ100: на стадии подготовки | AP100: на стадии подготовки | AR100: на стадии подготовки | AT100: на стадии подготовки | BB100: =(AI100*'"Вес" ПИР'!$B$36+AK100*'"Вес" ПИР'!$B$37+AM100*'"Вес" ПИР'!$B$38+AO100*'"Вес" ПИР'!$B$39+AQ100*'"Вес" ПИР'!$B$40+AS100*'"Вес" ПИР'!$B$41+AU100*'"Вес" ПИР'!$B$42+AW100*'"Вес" ПИР'!$B$43+AY100*'"Вес" ПИР'!$B$44+BA100*'"Вес" ПИР'!$B$45)/100 -> 0 | BC100: на стадии подготовки | BE100: на стадии подготовки | BG100: =(BD100*'"Вес" ПИР'!$B$50+BF100*'"Вес" ПИР'!$B$51)/100 -> 0 | BI100: 0 | BK100: 46266 | BL100: =(S100*'"Вес" ПИР'!$B$3+X100*'"Вес" ПИР'!$B$4+AG100*'"Вес" ПИР'!$B$5+BB100*'"Вес" ПИР'!$B$6+BG100*'"Вес" ПИР'!$B$7+BI100*'"Вес" ПИР'!$B$8)/100 -> 0
B101: 2026 | C101: ТОО "5А Engineering" | D101: 115657200 | E101: Акмолинская область | F101: Зерендинский район | G101: Симферопольский с.о. | H101: с.Булак | I101: Имеется | K101: на стадии подготовки | M101: на стадии подготовки | O101: на стадии подготовки | Q101: на стадии подготовки | S101: =(J101*'"Вес" ПИР'!$B$13+L101*'"Вес" ПИР'!$B$14+N101*'"Вес" ПИР'!$B$15+P101*'"Вес" ПИР'!$B$16+R101*'"Вес" ПИР'!$B$17)/100 -> 0 | T101: 01.12.2025-30.03.2026 | V101: 01.12.2025-30.03.2026 | X101: =(U101*'"Вес" ПИР'!$B$22+W101*'"Вес" ПИР'!$B$23)/100 -> 0 | AG101: =(Z101*'"Вес" ПИР'!$B$28+AB101*'"Вес" ПИР'!$B$29+AD101*'"Вес" ПИР'!$B$30+AF101*'"Вес" ПИР'!$B$31)/100 -> 0 | AJ101: на стадии подготовки | AP101: на стадии подготовки | AR101: на стадии подготовки | AT101: на стадии подготовки | BB101: =(AI101*'"Вес" ПИР'!$B$36+AK101*'"Вес" ПИР'!$B$37+AM101*'"Вес" ПИР'!$B$38+AO101*'"Вес" ПИР'!$B$39+AQ101*'"Вес" ПИР'!$B$40+AS101*'"Вес" ПИР'!$B$41+AU101*'"Вес" ПИР'!$B$42+AW101*'"Вес" ПИР'!$B$43+AY101*'"Вес" ПИР'!$B$44+BA101*'"Вес" ПИР'!$B$45)/100 -> 0 | BC101: на стадии подготовки | BE101: на стадии подготовки | BG101: =(BD101*'"Вес" ПИР'!$B$50+BF101*'"Вес" ПИР'!$B$51)/100 -> 0 | BI101: 0 | BK101: 46266 | BL101: =(S101*'"Вес" ПИР'!$B$3+X101*'"Вес" ПИР'!$B$4+AG101*'"Вес" ПИР'!$B$5+BB101*'"Вес" ПИР'!$B$6+BG101*'"Вес" ПИР'!$B$7+BI101*'"Вес" ПИР'!$B$8)/100 -> 0
B102: 2026 | C102: ТОО "5А Engineering" | D102: 115637500 | E102: Акмолинская область | F102: Зерендинский район | G102: Булакский с.о. | H102: с. Жылымды | I102: Имеется | K102: на стадии подготовки | M102: на стадии подготовки | O102: на стадии подготовки | Q102: на стадии подготовки | S102: =(J102*'"Вес" ПИР'!$B$13+L102*'"Вес" ПИР'!$B$14+N102*'"Вес" ПИР'!$B$15+P102*'"Вес" ПИР'!$B$16+R102*'"Вес" ПИР'!$B$17)/100 -> 0 | T102: 01.12.2025-30.03.2026 | V102: 01.12.2025-30.03.2026 | X102: =(U102*'"Вес" ПИР'!$B$22+W102*'"Вес" ПИР'!$B$23)/100 -> 0 | AG102: =(Z102*'"Вес" ПИР'!$B$28+AB102*'"Вес" ПИР'!$B$29+AD102*'"Вес" ПИР'!$B$30+AF102*'"Вес" ПИР'!$B$31)/100 -> 0 | AJ102: на стадии подготовки | AP102: на стадии подготовки | AR102: на стадии подготовки | AT102: на стадии подготовки | BB102: =(AI102*'"Вес" ПИР'!$B$36+AK102*'"Вес" ПИР'!$B$37+AM102*'"Вес" ПИР'!$B$38+AO102*'"Вес" ПИР'!$B$39+AQ102*'"Вес" ПИР'!$B$40+AS102*'"Вес" ПИР'!$B$41+AU102*'"Вес" ПИР'!$B$42+AW102*'"Вес" ПИР'!$B$43+AY102*'"Вес" ПИР'!$B$44+BA102*'"Вес" ПИР'!$B$45)/100 -> 0 | BC102: на стадии подготовки | BE102: на стадии подготовки | BG102: =(BD102*'"Вес" ПИР'!$B$50+BF102*'"Вес" ПИР'!$B$51)/100 -> 0 | BI102: 0 | BK102: 46266 | BL102: =(S102*'"Вес" ПИР'!$B$3+X102*'"Вес" ПИР'!$B$4+AG102*'"Вес" ПИР'!$B$5+BB102*'"Вес" ПИР'!$B$6+BG102*'"Вес" ПИР'!$B$7+BI102*'"Вес" ПИР'!$B$8)/100 -> 0
B103: 2026 | C103: ТОО "5А Engineering" | D103: 115637600 | E103: Акмолинская область | F103: Зерендинский район | G103: Булакский с.о. | H103: с. Карагай | I103: Имеется | K103: на стадии подготовки | M103: на стадии подготовки | O103: на стадии подготовки | Q103: на стадии подготовки | S103: =(J103*'"Вес" ПИР'!$B$13+L103*'"Вес" ПИР'!$B$14+N103*'"Вес" ПИР'!$B$15+P103*'"Вес" ПИР'!$B$16+R103*'"Вес" ПИР'!$B$17)/100 -> 0 | T103: 01.12.2025-30.03.2026 | V103: 01.12.2025-30.03.2026 | X103: =(U103*'"Вес" ПИР'!$B$22+W103*'"Вес" ПИР'!$B$23)/100 -> 0 | AG103: =(Z103*'"Вес" ПИР'!$B$28+AB103*'"Вес" ПИР'!$B$29+AD103*'"Вес" ПИР'!$B$30+AF103*'"Вес" ПИР'!$B$31)/100 -> 0 | AJ103: на стадии подготовки | AP103: на стадии подготовки | AR103: на стадии подготовки | AT103: на стадии подготовки | BB103: =(AI103*'"Вес" ПИР'!$B$36+AK103*'"Вес" ПИР'!$B$37+AM103*'"Вес" ПИР'!$B$38+AO103*'"Вес" ПИР'!$B$39+AQ103*'"Вес" ПИР'!$B$40+AS103*'"Вес" ПИР'!$B$41+AU103*'"Вес" ПИР'!$B$42+AW103*'"Вес" ПИР'!$B$43+AY103*'"Вес" ПИР'!$B$44+BA103*'"Вес" ПИР'!$B$45)/100 -> 0 | BC103: на стадии подготовки | BE103: на стадии подготовки | BG103: =(BD103*'"Вес" ПИР'!$B$50+BF103*'"Вес" ПИР'!$B$51)/100 -> 0 | BI103: 0 | BK103: 46266 | BL103: =(S103*'"Вес" ПИР'!$B$3+X103*'"Вес" ПИР'!$B$4+AG103*'"Вес" ПИР'!$B$5+BB103*'"Вес" ПИР'!$B$6+BG103*'"Вес" ПИР'!$B$7+BI103*'"Вес" ПИР'!$B$8)/100 -> 0
B104: 2026 | C104: ТОО "5А Engineering" | D104: 115677100 | E104: Акмолинская область | F104: Зерендинский район | G104: Сарыозекский с.о. | H104: с. Акан | I104: Имеется | K104: на стадии подготовки | M104: на стадии подготовки | O104: на стадии подготовки | Q104: на стадии подготовки | S104: =(J104*'"Вес" ПИР'!$B$13+L104*'"Вес" ПИР'!$B$14+N104*'"Вес" ПИР'!$B$15+P104*'"Вес" ПИР'!$B$16+R104*'"Вес" ПИР'!$B$17)/100 -> 0 | T104: 01.12.2025-30.03.2026 | V104: 01.12.2025-30.03.2026 | X104: =(U104*'"Вес" ПИР'!$B$22+W104*'"Вес" ПИР'!$B$23)/100 -> 0 | AG104: =(Z104*'"Вес" ПИР'!$B$28+AB104*'"Вес" ПИР'!$B$29+AD104*'"Вес" ПИР'!$B$30+AF104*'"Вес" ПИР'!$B$31)/100 -> 0 | AJ104: на стадии подготовки | AP104: на стадии подготовки | AR104: на стадии подготовки | AT104: на стадии подготовки | BB104: =(AI104*'"Вес" ПИР'!$B$36+AK104*'"Вес" ПИР'!$B$37+AM104*'"Вес" ПИР'!$B$38+AO104*'"Вес" ПИР'!$B$39+AQ104*'"Вес" ПИР'!$B$40+AS104*'"Вес" ПИР'!$B$41+AU104*'"Вес" ПИР'!$B$42+AW104*'"Вес" ПИР'!$B$43+AY104*'"Вес" ПИР'!$B$44+BA104*'"Вес" ПИР'!$B$45)/100 -> 0 | BC104: на стадии подготовки | BE104: на стадии подготовки | BG104: =(BD104*'"Вес" ПИР'!$B$50+BF104*'"Вес" ПИР'!$B$51)/100 -> 0 | BI104: 0 | BK104: 46266 | BL104: =(S104*'"Вес" ПИР'!$B$3+X104*'"Вес" ПИР'!$B$4+AG104*'"Вес" ПИР'!$B$5+BB104*'"Вес" ПИР'!$B$6+BG104*'"Вес" ПИР'!$B$7+BI104*'"Вес" ПИР'!$B$8)/100 -> 0
B105: 2026 | C105: ТОО "5А Engineering" | D105: 115677300 | E105: Акмолинская область | F105: Зерендинский район | G105: Сарыозекский с.о. | H105: с.Баратай | I105: Имеется | K105: на стадии подготовки | M105: на стадии подготовки | O105: на стадии подготовки | Q105: на стадии подготовки | S105: =(J105*'"Вес" ПИР'!$B$13+L105*'"Вес" ПИР'!$B$14+N105*'"Вес" ПИР'!$B$15+P105*'"Вес" ПИР'!$B$16+R105*'"Вес" ПИР'!$B$17)/100 -> 0 | T105: 01.12.2025-30.03.2026 | V105: 01.12.2025-30.03.2026 | X105: =(U105*'"Вес" ПИР'!$B$22+W105*'"Вес" ПИР'!$B$23)/100 -> 0 | AG105: =(Z105*'"Вес" ПИР'!$B$28+AB105*'"Вес" ПИР'!$B$29+AD105*'"Вес" ПИР'!$B$30+AF105*'"Вес" ПИР'!$B$31)/100 -> 0 | AJ105: на стадии подготовки | AP105: на стадии подготовки | AR105: на стадии подготовки | AT105: на стадии подготовки | BB105: =(AI105*'"Вес" ПИР'!$B$36+AK105*'"Вес" ПИР'!$B$37+AM105*'"Вес" ПИР'!$B$38+AO105*'"Вес" ПИР'!$B$39+AQ105*'"Вес" ПИР'!$B$40+AS105*'"Вес" ПИР'!$B$41+AU105*'"Вес" ПИР'!$B$42+AW105*'"Вес" ПИР'!$B$43+AY105*'"Вес" ПИР'!$B$44+BA105*'"Вес" ПИР'!$B$45)/100 -> 0 | BC105: на стадии подготовки | BE105: на стадии подготовки | BG105: =(BD105*'"Вес" ПИР'!$B$50+BF105*'"Вес" ПИР'!$B$51)/100 -> 0 | BI105: 0 | BK105: 46266 | BL105: =(S105*'"Вес" ПИР'!$B$3+X105*'"Вес" ПИР'!$B$4+AG105*'"Вес" ПИР'!$B$5+BB105*'"Вес" ПИР'!$B$6+BG105*'"Вес" ПИР'!$B$7+BI105*'"Вес" ПИР'!$B$8)/100 -> 0
B106: 2026 | C106: ТОО "5А Engineering" | D106: 115677800 | E106: Акмолинская область | F106: Зерендинский район | G106: Сарыозекский с.о. | H106: с.Уголки | I106: Имеется | K106: на стадии подготовки | M106: на стадии подготовки | O106: на стадии подготовки | Q106: на стадии подготовки | S106: =(J106*'"Вес" ПИР'!$B$13+L106*'"Вес" ПИР'!$B$14+N106*'"Вес" ПИР'!$B$15+P106*'"Вес" ПИР'!$B$16+R106*'"Вес" ПИР'!$B$17)/100 -> 0 | T106: 01.12.2025-30.03.2026 | V106: 01.12.2025-30.03.2026 | X106: =(U106*'"Вес" ПИР'!$B$22+W106*'"Вес" ПИР'!$B$23)/100 -> 0 | AG106: =(Z106*'"Вес" ПИР'!$B$28+AB106*'"Вес" ПИР'!$B$29+AD106*'"Вес" ПИР'!$B$30+AF106*'"Вес" ПИР'!$B$31)/100 -> 0 | AJ106: на стадии подготовки | AP106: на стадии подготовки | AR106: на стадии подготовки | AT106: на стадии подготовки | BB106: =(AI106*'"Вес" ПИР'!$B$36+AK106*'"Вес" ПИР'!$B$37+AM106*'"Вес" ПИР'!$B$38+AO106*'"Вес" ПИР'!$B$39+AQ106*'"Вес" ПИР'!$B$40+AS106*'"Вес" ПИР'!$B$41+AU106*'"Вес" ПИР'!$B$42+AW106*'"Вес" ПИР'!$B$43+AY106*'"Вес" ПИР'!$B$44+BA106*'"Вес" ПИР'!$B$45)/100 -> 0 | BC106: на стадии подготовки | BE106: на стадии подготовки | BG106: =(BD106*'"Вес" ПИР'!$B$50+BF106*'"Вес" ПИР'!$B$51)/100 -> 0 | BI106: 0 | BK106: 46266 | BL106: =(S106*'"Вес" ПИР'!$B$3+X106*'"Вес" ПИР'!$B$4+AG106*'"Вес" ПИР'!$B$5+BB106*'"Вес" ПИР'!$B$6+BG106*'"Вес" ПИР'!$B$7+BI106*'"Вес" ПИР'!$B$8)/100 -> 0
B107: 2026 | C107: ТОО "5А Engineering" | D107: 116437300 | E107: Акмолинская область | F107: Сандыктауский район | G107: Белгородский с.о. | H107: с.Преображенка | I107: Имеется | K107: на стадии подготовки | M107: на стадии подготовки | O107: на стадии подготовки | Q107: на стадии подготовки | S107: =(J107*'"Вес" ПИР'!$B$13+L107*'"Вес" ПИР'!$B$14+N107*'"Вес" ПИР'!$B$15+P107*'"Вес" ПИР'!$B$16+R107*'"Вес" ПИР'!$B$17)/100 -> 0 | T107: 01.12.2025-30.03.2026 | V107: 01.12.2025-30.03.2026 | X107: =(U107*'"Вес" ПИР'!$B$22+W107*'"Вес" ПИР'!$B$23)/100 -> 0 | AG107: =(Z107*'"Вес" ПИР'!$B$28+AB107*'"Вес" ПИР'!$B$29+AD107*'"Вес" ПИР'!$B$30+AF107*'"Вес" ПИР'!$B$31)/100 -> 0 | AJ107: на стадии подготовки | AP107: на стадии подготовки | AR107: на стадии подготовки | AT107: на стадии подготовки | BB107: =(AI107*'"Вес" ПИР'!$B$36+AK107*'"Вес" ПИР'!$B$37+AM107*'"Вес" ПИР'!$B$38+AO107*'"Вес" ПИР'!$B$39+AQ107*'"Вес" ПИР'!$B$40+AS107*'"Вес" ПИР'!$B$41+AU107*'"Вес" ПИР'!$B$42+AW107*'"Вес" ПИР'!$B$43+AY107*'"Вес" ПИР'!$B$44+BA107*'"Вес" ПИР'!$B$45)/100 -> 0 | BC107: на стадии подготовки | BE107: на стадии подготовки | BG107: =(BD107*'"Вес" ПИР'!$B$50+BF107*'"Вес" ПИР'!$B$51)/100 -> 0 | BI107: 0 | BK107: 46266 | BL107: =(S107*'"Вес" ПИР'!$B$3+X107*'"Вес" ПИР'!$B$4+AG107*'"Вес" ПИР'!$B$5+BB107*'"Вес" ПИР'!$B$6+BG107*'"Вес" ПИР'!$B$7+BI107*'"Вес" ПИР'!$B$8)/100 -> 0
B108: 2026 | C108: ТОО "5А Engineering" | D108: 116437500 | E108: Акмолинская область | F108: Сандыктауский район | G108: Белгородский с.о. | H108: с.Раздольное | I108: Имеется | K108: на стадии подготовки | M108: на стадии подготовки | O108: на стадии подготовки | Q108: на стадии подготовки | S108: =(J108*'"Вес" ПИР'!$B$13+L108*'"Вес" ПИР'!$B$14+N108*'"Вес" ПИР'!$B$15+P108*'"Вес" ПИР'!$B$16+R108*'"Вес" ПИР'!$B$17)/100 -> 0 | T108: 01.12.2025-30.03.2026 | V108: 01.12.2025-30.03.2026 | X108: =(U108*'"Вес" ПИР'!$B$22+W108*'"Вес" ПИР'!$B$23)/100 -> 0 | AG108: =(Z108*'"Вес" ПИР'!$B$28+AB108*'"Вес" ПИР'!$B$29+AD108*'"Вес" ПИР'!$B$30+AF108*'"Вес" ПИР'!$B$31)/100 -> 0 | AJ108: на стадии подготовки | AP108: на стадии подготовки | AR108: на стадии подготовки | AT108: на стадии подготовки | BB108: =(AI108*'"Вес" ПИР'!$B$36+AK108*'"Вес" ПИР'!$B$37+AM108*'"Вес" ПИР'!$B$38+AO108*'"Вес" ПИР'!$B$39+AQ108*'"Вес" ПИР'!$B$40+AS108*'"Вес" ПИР'!$B$41+AU108*'"Вес" ПИР'!$B$42+AW108*'"Вес" ПИР'!$B$43+AY108*'"Вес" ПИР'!$B$44+BA108*'"Вес" ПИР'!$B$45)/100 -> 0 | BC108: на стадии подготовки | BE108: на стадии подготовки | BG108: =(BD108*'"Вес" ПИР'!$B$50+BF108*'"Вес" ПИР'!$B$51)/100 -> 0 | BI108: 0 | BK108: 46266 | BL108: =(S108*'"Вес" ПИР'!$B$3+X108*'"Вес" ПИР'!$B$4+AG108*'"Вес" ПИР'!$B$5+BB108*'"Вес" ПИР'!$B$6+BG108*'"Вес" ПИР'!$B$7+BI108*'"Вес" ПИР'!$B$8)/100 -> 0
... B136: 2026 | C136: ТОО "5А Engineering" | D136: 117061500 | E136: Акмолинская область | F136: Бурабайский район | G136: Урумкайский с.о. | H136: с. Кульстан | I136: Имеется | K136: на стадии подготовки | M136: на стадии подготовки | O136: на стадии подготовки | Q136: на стадии подготовки | S136: =(J136*'"Вес" ПИР'!$B$13+L136*'"Вес" ПИР'!$B$14+N136*'"Вес" ПИР'!$B$15+P136*'"Вес" ПИР'!$B$16+R136*'"Вес" ПИР'!$B$17)/100 -> 0 | T136: 01.12.2025-30.03.2026 | V136: 01.12.2025-30.03.2026 | X136: =(U136*'"Вес" ПИР'!$B$22+W136*'"Вес" ПИР'!$B$23)/100 -> 0 | AG136: =(Z136*'"Вес" ПИР'!$B$28+AB136*'"Вес" ПИР'!$B$29+AD136*'"Вес" ПИР'!$B$30+AF136*'"Вес" ПИР'!$B$31)/100 -> 0 | AJ136: на стадии подготовки | AP136: на стадии подготовки | AR136: на стадии подготовки | AT136: на стадии подготовки | BB136: =(AI136*'"Вес" ПИР'!$B$36+AK136*'"Вес" ПИР'!$B$37+AM136*'"Вес" ПИР'!$B$38+AO136*'"Вес" ПИР'!$B$39+AQ136*'"Вес" ПИР'!$B$40+AS136*'"Вес" ПИР'!$B$41+AU136*'"Вес" ПИР'!$B$42+AW136*'"Вес" ПИР'!$B$43+AY136*'"Вес" ПИР'!$B$44+BA136*'"Вес" ПИР'!$B$45)/100 -> 0 | BC136: на стадии подготовки | BE136: на стадии подготовки | BG136: =(BD136*'"Вес" ПИР'!$B$50+BF136*'"Вес" ПИР'!$B$51)/100 -> 0 | BI136: 0 | BK136: 46266 | BL136: =(S136*'"Вес" ПИР'!$B$3+X136*'"Вес" ПИР'!$B$4+AG136*'"Вес" ПИР'!$B$5+BB136*'"Вес" ПИР'!$B$6+BG136*'"Вес" ПИР'!$B$7+BI136*'"Вес" ПИР'!$B$8)/100 -> 0
B137: 2026 | C137: ТОО "5А Engineering" | D137: 111847300 | E137: Акмолинская область | F137: г.Степногорск | G137: Богембайский с.о. | H137: с. Богембай | I137: Имеется | K137: на стадии подготовки | M137: на стадии подготовки | O137: на стадии подготовки | Q137: на стадии подготовки | S137: =(J137*'"Вес" ПИР'!$B$13+L137*'"Вес" ПИР'!$B$14+N137*'"Вес" ПИР'!$B$15+P137*'"Вес" ПИР'!$B$16+R137*'"Вес" ПИР'!$B$17)/100 -> 0 | T137: Выдача 30.03.2026 | V137: Выдача 30.03.2026 | X137: =(U137*'"Вес" ПИР'!$B$22+W137*'"Вес" ПИР'!$B$23)/100 -> 0 | AG137: =(Z137*'"Вес" ПИР'!$B$28+AB137*'"Вес" ПИР'!$B$29+AD137*'"Вес" ПИР'!$B$30+AF137*'"Вес" ПИР'!$B$31)/100 -> 0 | AJ137: на стадии подготовки | AP137: на стадии подготовки | AR137: на стадии подготовки | AT137: на стадии подготовки | BB137: =(AI137*'"Вес" ПИР'!$B$36+AK137*'"Вес" ПИР'!$B$37+AM137*'"Вес" ПИР'!$B$38+AO137*'"Вес" ПИР'!$B$39+AQ137*'"Вес" ПИР'!$B$40+AS137*'"Вес" ПИР'!$B$41+AU137*'"Вес" ПИР'!$B$42+AW137*'"Вес" ПИР'!$B$43+AY137*'"Вес" ПИР'!$B$44+BA137*'"Вес" ПИР'!$B$45)/100 -> 0 | BC137: на стадии подготовки | BE137: на стадии подготовки | BG137: =(BD137*'"Вес" ПИР'!$B$50+BF137*'"Вес" ПИР'!$B$51)/100 -> 0 | BI137: 0 | BK137: 31.09.2026 | BL137: =(S137*'"Вес" ПИР'!$B$3+X137*'"Вес" ПИР'!$B$4+AG137*'"Вес" ПИР'!$B$5+BB137*'"Вес" ПИР'!$B$6+BG137*'"Вес" ПИР'!$B$7+BI137*'"Вес" ПИР'!$B$8)/100 -> 0
B138: 2026 | C138: ТОО "5А Engineering" | D138: 114653100 | E138: Акмолинская область | F138: Ерейментауский район | G138: Улентинский с.о. | H138: ст. Уленты | I138: Имеется | K138: на стадии подготовки | M138: на стадии подготовки | O138: на стадии подготовки | Q138: на стадии подготовки | S138: =(J138*'"Вес" ПИР'!$B$13+L138*'"Вес" ПИР'!$B$14+N138*'"Вес" ПИР'!$B$15+P138*'"Вес" ПИР'!$B$16+R138*'"Вес" ПИР'!$B$17)/100 -> 0 | T138: Готово | V138: Готово | X138: =(U138*'"Вес" ПИР'!$B$22+W138*'"Вес" ПИР'!$B$23)/100 -> 0 | AG138: =(Z138*'"Вес" ПИР'!$B$28+AB138*'"Вес" ПИР'!$B$29+AD138*'"Вес" ПИР'!$B$30+AF138*'"Вес" ПИР'!$B$31)/100 -> 0 | AJ138: на стадии подготовки | AP138: на стадии подготовки | AR138: на стадии подготовки | AT138: на стадии подготовки | BB138: =(AI138*'"Вес" ПИР'!$B$36+AK138*'"Вес" ПИР'!$B$37+AM138*'"Вес" ПИР'!$B$38+AO138*'"Вес" ПИР'!$B$39+AQ138*'"Вес" ПИР'!$B$40+AS138*'"Вес" ПИР'!$B$41+AU138*'"Вес" ПИР'!$B$42+AW138*'"Вес" ПИР'!$B$43+AY138*'"Вес" ПИР'!$B$44+BA138*'"Вес" ПИР'!$B$45)/100 -> 0 | BC138: на стадии подготовки | BE138: на стадии подготовки | BG138: =(BD138*'"Вес" ПИР'!$B$50+BF138*'"Вес" ПИР'!$B$51)/100 -> 0 | BI138: 0 | BK138: 46218 | BL138: =(S138*'"Вес" ПИР'!$B$3+X138*'"Вес" ПИР'!$B$4+AG138*'"Вес" ПИР'!$B$5+BB138*'"Вес" ПИР'!$B$6+BG138*'"Вес" ПИР'!$B$7+BI138*'"Вес" ПИР'!$B$8)/100 -> 0
B139: 2026 | C139: ТОО "5А Engineering" | D139: 114847200 | E139: Акмолинская область | F139: Есильский район | G139: Зареченский с.о. | H139: с. Дальное | I139: Имеется | K139: на стадии подготовки | M139: на стадии подготовки | O139: на стадии подготовки | Q139: на стадии подготовки | S139: =(J139*'"Вес" ПИР'!$B$13+L139*'"Вес" ПИР'!$B$14+N139*'"Вес" ПИР'!$B$15+P139*'"Вес" ПИР'!$B$16+R139*'"Вес" ПИР'!$B$17)/100 -> 0 | T139: Готово | V139: Готово | X139: =(U139*'"Вес" ПИР'!$B$22+W139*'"Вес" ПИР'!$B$23)/100 -> 0 | AG139: =(Z139*'"Вес" ПИР'!$B$28+AB139*'"Вес" ПИР'!$B$29+AD139*'"Вес" ПИР'!$B$30+AF139*'"Вес" ПИР'!$B$31)/100 -> 0 | AJ139: на стадии подготовки | AP139: на стадии подготовки | AR139: на стадии подготовки | AT139: на стадии подготовки | BB139: =(AI139*'"Вес" ПИР'!$B$36+AK139*'"Вес" ПИР'!$B$37+AM139*'"Вес" ПИР'!$B$38+AO139*'"Вес" ПИР'!$B$39+AQ139*'"Вес" ПИР'!$B$40+AS139*'"Вес" ПИР'!$B$41+AU139*'"Вес" ПИР'!$B$42+AW139*'"Вес" ПИР'!$B$43+AY139*'"Вес" ПИР'!$B$44+BA139*'"Вес" ПИР'!$B$45)/100 -> 0 | BC139: на стадии подготовки | BE139: на стадии подготовки | BG139: =(BD139*'"Вес" ПИР'!$B$50+BF139*'"Вес" ПИР'!$B$51)/100 -> 0 | BI139: 0 | BK139: 31.09.2026 | BL139: =(S139*'"Вес" ПИР'!$B$3+X139*'"Вес" ПИР'!$B$4+AG139*'"Вес" ПИР'!$B$5+BB139*'"Вес" ПИР'!$B$6+BG139*'"Вес" ПИР'!$B$7+BI139*'"Вес" ПИР'!$B$8)/100 -> 0
B140: 2026 | C140: ТОО "5А Engineering" | D140: 114857100 | E140: Акмолинская область | F140: Есильский район | G140: Красивинский с.о. | H140: ст. Красивая | I140: Имеется | K140: на стадии подготовки | M140: на стадии подготовки | O140: на стадии подготовки | Q140: на стадии подготовки | S140: =(J140*'"Вес" ПИР'!$B$13+L140*'"Вес" ПИР'!$B$14+N140*'"Вес" ПИР'!$B$15+P140*'"Вес" ПИР'!$B$16+R140*'"Вес" ПИР'!$B$17)/100 -> 0 | T140: Готово | V140: Готово | X140: =(U140*'"Вес" ПИР'!$B$22+W140*'"Вес" ПИР'!$B$23)/100 -> 0 | AG140: =(Z140*'"Вес" ПИР'!$B$28+AB140*'"Вес" ПИР'!$B$29+AD140*'"Вес" ПИР'!$B$30+AF140*'"Вес" ПИР'!$B$31)/100 -> 0 | AJ140: на стадии подготовки | AP140: на стадии подготовки | AR140: на стадии подготовки | AT140: на стадии подготовки | BB140: =(AI140*'"Вес" ПИР'!$B$36+AK140*'"Вес" ПИР'!$B$37+AM140*'"Вес" ПИР'!$B$38+AO140*'"Вес" ПИР'!$B$39+AQ140*'"Вес" ПИР'!$B$40+AS140*'"Вес" ПИР'!$B$41+AU140*'"Вес" ПИР'!$B$42+AW140*'"Вес" ПИР'!$B$43+AY140*'"Вес" ПИР'!$B$44+BA140*'"Вес" ПИР'!$B$45)/100 -> 0 | BC140: на стадии подготовки | BE140: на стадии подготовки | BG140: =(BD140*'"Вес" ПИР'!$B$50+BF140*'"Вес" ПИР'!$B$51)/100 -> 0 | BI140: 0 | BK140: 31.09.2026 | BL140: =(S140*'"Вес" ПИР'!$B$3+X140*'"Вес" ПИР'!$B$4+AG140*'"Вес" ПИР'!$B$5+BB140*'"Вес" ПИР'!$B$6+BG140*'"Вес" ПИР'!$B$7+BI140*'"Вес" ПИР'!$B$8)/100 -> 0
B141: 2026 | C141: ТОО "5А Engineering" | D141: 115635200 | E141: Акмолинская область | F141: Зерендинский район | G141: Алексеевский с.о. | H141: ст. Жаманаши | I141: Имеется | K141: на стадии подготовки | M141: на стадии подготовки | O141: на стадии подготовки | Q141: на стадии подготовки | S141: =(J141*'"Вес" ПИР'!$B$13+L141*'"Вес" ПИР'!$B$14+N141*'"Вес" ПИР'!$B$15+P141*'"Вес" ПИР'!$B$16+R141*'"Вес" ПИР'!$B$17)/100 -> 0 | T141: 01.12.2025-30.03.2026 | V141: 01.12.2025-30.03.2026 | X141: =(U141*'"Вес" ПИР'!$B$22+W141*'"Вес" ПИР'!$B$23)/100 -> 0 | AG141: =(Z141*'"Вес" ПИР'!$B$28+AB141*'"Вес" ПИР'!$B$29+AD141*'"Вес" ПИР'!$B$30+AF141*'"Вес" ПИР'!$B$31)/100 -> 0 | AJ141: на стадии подготовки | AP141: на стадии подготовки | AR141: на стадии подготовки | AT141: на стадии подготовки | BB141: =(AI141*'"Вес" ПИР'!$B$36+AK141*'"Вес" ПИР'!$B$37+AM141*'"Вес" ПИР'!$B$38+AO141*'"Вес" ПИР'!$B$39+AQ141*'"Вес" ПИР'!$B$40+AS141*'"Вес" ПИР'!$B$41+AU141*'"Вес" ПИР'!$B$42+AW141*'"Вес" ПИР'!$B$43+AY141*'"Вес" ПИР'!$B$44+BA141*'"Вес" ПИР'!$B$45)/100 -> 0 | BC141: на стадии подготовки | BE141: на стадии подготовки | BG141: =(BD141*'"Вес" ПИР'!$B$50+BF141*'"Вес" ПИР'!$B$51)/100 -> 0 | BI141: 0 | BK141: 46266 | BL141: =(S141*'"Вес" ПИР'!$B$3+X141*'"Вес" ПИР'!$B$4+AG141*'"Вес" ПИР'!$B$5+BB141*'"Вес" ПИР'!$B$6+BG141*'"Вес" ПИР'!$B$7+BI141*'"Вес" ПИР'!$B$8)/100 -> 0
B142: 2026 | C142: ТОО "5А Engineering" | D142: 115669800 | E142: Акмолинская область | F142: Зерендинский район | G142: Байтерекский с.о. | H142: с. Ульгили | I142: Имеется | K142: на стадии подготовки | M142: на стадии подготовки | O142: на стадии подготовки | Q142: на стадии подготовки | S142: =(J142*'"Вес" ПИР'!$B$13+L142*'"Вес" ПИР'!$B$14+N142*'"Вес" ПИР'!$B$15+P142*'"Вес" ПИР'!$B$16+R142*'"Вес" ПИР'!$B$17)/100 -> 0 | T142: 01.12.2025-30.03.2026 | V142: 01.12.2025-30.03.2026 | X142: =(U142*'"Вес" ПИР'!$B$22+W142*'"Вес" ПИР'!$B$23)/100 -> 0 | AG142: =(Z142*'"Вес" ПИР'!$B$28+AB142*'"Вес" ПИР'!$B$29+AD142*'"Вес" ПИР'!$B$30+AF142*'"Вес" ПИР'!$B$31)/100 -> 0 | AJ142: на стадии подготовки | AP142: на стадии подготовки | AR142: на стадии подготовки | AT142: на стадии подготовки | BB142: =(AI142*'"Вес" ПИР'!$B$36+AK142*'"Вес" ПИР'!$B$37+AM142*'"Вес" ПИР'!$B$38+AO142*'"Вес" ПИР'!$B$39+AQ142*'"Вес" ПИР'!$B$40+AS142*'"Вес" ПИР'!$B$41+AU142*'"Вес" ПИР'!$B$42+AW142*'"Вес" ПИР'!$B$43+AY142*'"Вес" ПИР'!$B$44+BA142*'"Вес" ПИР'!$B$45)/100 -> 0 | BC142: на стадии подготовки | BE142: на стадии подготовки | BG142: =(BD142*'"Вес" ПИР'!$B$50+BF142*'"Вес" ПИР'!$B$51)/100 -> 0 | BI142: 0 | BK142: 46266 | BL142: =(S142*'"Вес" ПИР'!$B$3+X142*'"Вес" ПИР'!$B$4+AG142*'"Вес" ПИР'!$B$5+BB142*'"Вес" ПИР'!$B$6+BG142*'"Вес" ПИР'!$B$7+BI142*'"Вес" ПИР'!$B$8)/100 -> 0
B143: 2026 | C143: ТОО "5А Engineering" | D143: 116030200 | E143: Акмолинская область | F143: Коргалжынский район | G143: Коржинкольский с.о. | H143: с. Абай | I143: Имеется | K143: на стадии подготовки | M143: на стадии подготовки | O143: на стадии подготовки | Q143: на стадии подготовки | S143: =(J143*'"Вес" ПИР'!$B$13+L143*'"Вес" ПИР'!$B$14+N143*'"Вес" ПИР'!$B$15+P143*'"Вес" ПИР'!$B$16+R143*'"Вес" ПИР'!$B$17)/100 -> 0 | T143: Готово | V143: Готово | X143: =(U143*'"Вес" ПИР'!$B$22+W143*'"Вес" ПИР'!$B$23)/100 -> 0 | AG143: =(Z143*'"Вес" ПИР'!$B$28+AB143*'"Вес" ПИР'!$B$29+AD143*'"Вес" ПИР'!$B$30+AF143*'"Вес" ПИР'!$B$31)/100 -> 0 | AJ143: на стадии подготовки | AP143: на стадии подготовки | AR143: на стадии подготовки | AT143: на стадии подготовки | BB143: =(AI143*'"Вес" ПИР'!$B$36+AK143*'"Вес" ПИР'!$B$37+AM143*'"Вес" ПИР'!$B$38+AO143*'"Вес" ПИР'!$B$39+AQ143*'"Вес" ПИР'!$B$40+AS143*'"Вес" ПИР'!$B$41+AU143*'"Вес" ПИР'!$B$42+AW143*'"Вес" ПИР'!$B$43+AY143*'"Вес" ПИР'!$B$44+BA143*'"Вес" ПИР'!$B$45)/100 -> 0 | BC143: на стадии подготовки | BE143: на стадии подготовки | BG143: =(BD143*'"Вес" ПИР'!$B$50+BF143*'"Вес" ПИР'!$B$51)/100 -> 0 | BI143: 0 | BK143: 31.09.2026 | BL143: =(S143*'"Вес" ПИР'!$B$3+X143*'"Вес" ПИР'!$B$4+AG143*'"Вес" ПИР'!$B$5+BB143*'"Вес" ПИР'!$B$6+BG143*'"Вес" ПИР'!$B$7+BI143*'"Вес" ПИР'!$B$8)/100 -> 0
B144: 2026 | C144: ТОО "5А Engineering" | D144: 116438200 | E144: Акмолинская область | F144: Сандыктауский район | G144: Берликский с.о. | H144: с.Арбузинка | I144: Имеется | K144: на стадии подготовки | M144: на стадии подготовки | O144: на стадии подготовки | Q144: на стадии подготовки | S144: =(J144*'"Вес" ПИР'!$B$13+L144*'"Вес" ПИР'!$B$14+N144*'"Вес" ПИР'!$B$15+P144*'"Вес" ПИР'!$B$16+R144*'"Вес" ПИР'!$B$17)/100 -> 0 | T144: 01.12.2025-30.03.2026 | V144: 01.12.2025-30.03.2026 | X144: =(U144*'"Вес" ПИР'!$B$22+W144*'"Вес" ПИР'!$B$23)/100 -> 0 | AG144: =(Z144*'"Вес" ПИР'!$B$28+AB144*'"Вес" ПИР'!$B$29+AD144*'"Вес" ПИР'!$B$30+AF144*'"Вес" ПИР'!$B$31)/100 -> 0 | AJ144: на стадии подготовки | AP144: на стадии подготовки | AR144: на стадии подготовки | AT144: на стадии подготовки | BB144: =(AI144*'"Вес" ПИР'!$B$36+AK144*'"Вес" ПИР'!$B$37+AM144*'"Вес" ПИР'!$B$38+AO144*'"Вес" ПИР'!$B$39+AQ144*'"Вес" ПИР'!$B$40+AS144*'"Вес" ПИР'!$B$41+AU144*'"Вес" ПИР'!$B$42+AW144*'"Вес" ПИР'!$B$43+AY144*'"Вес" ПИР'!$B$44+BA144*'"Вес" ПИР'!$B$45)/100 -> 0 | BC144: на стадии подготовки | BE144: на стадии подготовки | BG144: =(BD144*'"Вес" ПИР'!$B$50+BF144*'"Вес" ПИР'!$B$51)/100 -> 0 | BI144: 0 | BK144: 46266 | BL144: =(S144*'"Вес" ПИР'!$B$3+X144*'"Вес" ПИР'!$B$4+AG144*'"Вес" ПИР'!$B$5+BB144*'"Вес" ПИР'!$B$6+BG144*'"Вес" ПИР'!$B$7+BI144*'"Вес" ПИР'!$B$8)/100 -> 0
B145: 2026 | C145: ТОО "5А Engineering" | D145: 116453400 | E145: Акмолинская область | F145: Сандыктауский район | G145: Новоникольский с.о. | H145: с.Мысок | I145: Имеется | K145: на стадии подготовки | M145: на стадии подготовки | O145: на стадии подготовки | Q145: на стадии подготовки | S145: =(J145*'"Вес" ПИР'!$B$13+L145*'"Вес" ПИР'!$B$14+N145*'"Вес" ПИР'!$B$15+P145*'"Вес" ПИР'!$B$16+R145*'"Вес" ПИР'!$B$17)/100 -> 0 | T145: 01.12.2025-30.03.2026 | V145: 01.12.2025-30.03.2026 | X145: =(U145*'"Вес" ПИР'!$B$22+W145*'"Вес" ПИР'!$B$23)/100 -> 0 | AG145: =(Z145*'"Вес" ПИР'!$B$28+AB145*'"Вес" ПИР'!$B$29+AD145*'"Вес" ПИР'!$B$30+AF145*'"Вес" ПИР'!$B$31)/100 -> 0 | AJ145: на стадии подготовки | AP145: на стадии подготовки | AR145: на стадии подготовки | AT145: на стадии подготовки | BB145: =(AI145*'"Вес" ПИР'!$B$36+AK145*'"Вес" ПИР'!$B$37+AM145*'"Вес" ПИР'!$B$38+AO145*'"Вес" ПИР'!$B$39+AQ145*'"Вес" ПИР'!$B$40+AS145*'"Вес" ПИР'!$B$41+AU145*'"Вес" ПИР'!$B$42+AW145*'"Вес" ПИР'!$B$43+AY145*'"Вес" ПИР'!$B$44+BA145*'"Вес" ПИР'!$B$45)/100 -> 0 | BC145: на стадии подготовки | BE145: на стадии подготовки | BG145: =(BD145*'"Вес" ПИР'!$B$50+BF145*'"Вес" ПИР'!$B$51)/100 -> 0 | BI145: 0 | BK145: 46266 | BL145: =(S145*'"Вес" ПИР'!$B$3+X145*'"Вес" ПИР'!$B$4+AG145*'"Вес" ПИР'!$B$5+BB145*'"Вес" ПИР'!$B$6+BG145*'"Вес" ПИР'!$B$7+BI145*'"Вес" ПИР'!$B$8)/100 -> 0
B146: 2026 | C146: ТОО "5А Engineering" | D146: 116845600 | E146: Акмолинская область | F146: Шортандинский район | G146: Новоселовский с.о. | H146: с.Ошак | I146: Имеется | K146: на стадии подготовки | M146: на стадии подготовки | O146: на стадии подготовки | Q146: на стадии подготовки | S146: =(J146*'"Вес" ПИР'!$B$13+L146*'"Вес" ПИР'!$B$14+N146*'"Вес" ПИР'!$B$15+P146*'"Вес" ПИР'!$B$16+R146*'"Вес" ПИР'!$B$17)/100 -> 0 | T146: 01.12.2025-30.03.2026 | V146: 01.12.2025-30.03.2026 | X146: =(U146*'"Вес" ПИР'!$B$22+W146*'"Вес" ПИР'!$B$23)/100 -> 0 | AG146: =(Z146*'"Вес" ПИР'!$B$28+AB146*'"Вес" ПИР'!$B$29+AD146*'"Вес" ПИР'!$B$30+AF146*'"Вес" ПИР'!$B$31)/100 -> 0 | AJ146: на стадии подготовки | AP146: на стадии подготовки | AR146: на стадии подготовки | AT146: на стадии подготовки | BB146: =(AI146*'"Вес" ПИР'!$B$36+AK146*'"Вес" ПИР'!$B$37+AM146*'"Вес" ПИР'!$B$38+AO146*'"Вес" ПИР'!$B$39+AQ146*'"Вес" ПИР'!$B$40+AS146*'"Вес" ПИР'!$B$41+AU146*'"Вес" ПИР'!$B$42+AW146*'"Вес" ПИР'!$B$43+AY146*'"Вес" ПИР'!$B$44+BA146*'"Вес" ПИР'!$B$45)/100 -> 0 | BC146: на стадии подготовки | BE146: на стадии подготовки | BG146: =(BD146*'"Вес" ПИР'!$B$50+BF146*'"Вес" ПИР'!$B$51)/100 -> 0 | BI146: 0 | BK146: 46266 | BL146: =(S146*'"Вес" ПИР'!$B$3+X146*'"Вес" ПИР'!$B$4+AG146*'"Вес" ПИР'!$B$5+BB146*'"Вес" ПИР'!$B$6+BG146*'"Вес" ПИР'!$B$7+BI146*'"Вес" ПИР'!$B$8)/100 -> 0
B147: 2026 | C147: ТОО "5А Engineering" | D147: 115243200 | E147: Акмолинская область | F147: Жаксынский район | G147: Жанакииминский с.о. | H147: с.Алгабас | I147: Имеется | K147: на стадии подготовки | M147: на стадии подготовки | O147: на стадии подготовки | Q147: на стадии подготовки | S147: =(J147*'"Вес" ПИР'!$B$13+L147*'"Вес" ПИР'!$B$14+N147*'"Вес" ПИР'!$B$15+P147*'"Вес" ПИР'!$B$16+R147*'"Вес" ПИР'!$B$17)/100 -> 0 | T147: Готово | V147: Готово | X147: =(U147*'"Вес" ПИР'!$B$22+W147*'"Вес" ПИР'!$B$23)/100 -> 0 | AG147: =(Z147*'"Вес" ПИР'!$B$28+AB147*'"Вес" ПИР'!$B$29+AD147*'"Вес" ПИР'!$B$30+AF147*'"Вес" ПИР'!$B$31)/100 -> 0 | AJ147: на стадии подготовки | AP147: на стадии подготовки | AR147: на стадии подготовки | AT147: на стадии подготовки | BB147: =(AI147*'"Вес" ПИР'!$B$36+AK147*'"Вес" ПИР'!$B$37+AM147*'"Вес" ПИР'!$B$38+AO147*'"Вес" ПИР'!$B$39+AQ147*'"Вес" ПИР'!$B$40+AS147*'"Вес" ПИР'!$B$41+AU147*'"Вес" ПИР'!$B$42+AW147*'"Вес" ПИР'!$B$43+AY147*'"Вес" ПИР'!$B$44+BA147*'"Вес" ПИР'!$B$45)/100 -> 0 | BC147: на стадии подготовки | BE147: на стадии подготовки | BG147: =(BD147*'"Вес" ПИР'!$B$50+BF147*'"Вес" ПИР'!$B$51)/100 -> 0 | BI147: 0 | BK147: 31.09.2026 | BL147: =(S147*'"Вес" ПИР'!$B$3+X147*'"Вес" ПИР'!$B$4+AG147*'"Вес" ПИР'!$B$5+BB147*'"Вес" ПИР'!$B$6+BG147*'"Вес" ПИР'!$B$7+BI147*'"Вес" ПИР'!$B$8)/100 -> 0
B148: 2026 | C148: ТОО "5А Engineering" | D148: 115247400 | E148: Акмолинская область | F148: Жаксынский район | G148: Ишимский с.о. | H148: с.Монастырка | I148: Имеется | K148: на стадии подготовки | M148: на стадии подготовки | O148: на стадии подготовки | Q148: на стадии подготовки | S148: =(J148*'"Вес" ПИР'!$B$13+L148*'"Вес" ПИР'!$B$14+N148*'"Вес" ПИР'!$B$15+P148*'"Вес" ПИР'!$B$16+R148*'"Вес" ПИР'!$B$17)/100 -> 0 | T148: Готово | V148: Готово | X148: =(U148*'"Вес" ПИР'!$B$22+W148*'"Вес" ПИР'!$B$23)/100 -> 0 | AG148: =(Z148*'"Вес" ПИР'!$B$28+AB148*'"Вес" ПИР'!$B$29+AD148*'"Вес" ПИР'!$B$30+AF148*'"Вес" ПИР'!$B$31)/100 -> 0 | AJ148: на стадии подготовки | AP148: на стадии подготовки | AR148: на стадии подготовки | AT148: на стадии подготовки | BB148: =(AI148*'"Вес" ПИР'!$B$36+AK148*'"Вес" ПИР'!$B$37+AM148*'"Вес" ПИР'!$B$38+AO148*'"Вес" ПИР'!$B$39+AQ148*'"Вес" ПИР'!$B$40+AS148*'"Вес" ПИР'!$B$41+AU148*'"Вес" ПИР'!$B$42+AW148*'"Вес" ПИР'!$B$43+AY148*'"Вес" ПИР'!$B$44+BA148*'"Вес" ПИР'!$B$45)/100 -> 0 | BC148: на стадии подготовки | BE148: на стадии подготовки | BG148: =(BD148*'"Вес" ПИР'!$B$50+BF148*'"Вес" ПИР'!$B$51)/100 -> 0 | BI148: 0 | BK148: 31.09.2026 | BL148: =(S148*'"Вес" ПИР'!$B$3+X148*'"Вес" ПИР'!$B$4+AG148*'"Вес" ПИР'!$B$5+BB148*'"Вес" ПИР'!$B$6+BG148*'"Вес" ПИР'!$B$7+BI148*'"Вес" ПИР'!$B$8)/100 -> 0
B149: 2026 | C149: ТОО "5А Engineering" | D149: 116637500 | E149: Акмолинская область | F149: Целиноградский район | G149: Нуресильский с.о. | H149: с.Раздольное | I149: Имеется | K149: на стадии подготовки | M149: на стадии подготовки | O149: на стадии подготовки | Q149: на стадии подготовки | S149: =(J149*'"Вес" ПИР'!$B$13+L149*'"Вес" ПИР'!$B$14+N149*'"Вес" ПИР'!$B$15+P149*'"Вес" ПИР'!$B$16+R149*'"Вес" ПИР'!$B$17)/100 -> 0 | T149: Готово | V149: Готово | X149: =(U149*'"Вес" ПИР'!$B$22+W149*'"Вес" ПИР'!$B$23)/100 -> 0 | AG149: =(Z149*'"Вес" ПИР'!$B$28+AB149*'"Вес" ПИР'!$B$29+AD149*'"Вес" ПИР'!$B$30+AF149*'"Вес" ПИР'!$B$31)/100 -> 0 | AJ149: на стадии подготовки | AP149: на стадии подготовки | AR149: на стадии подготовки | AT149: на стадии подготовки | BB149: =(AI149*'"Вес" ПИР'!$B$36+AK149*'"Вес" ПИР'!$B$37+AM149*'"Вес" ПИР'!$B$38+AO149*'"Вес" ПИР'!$B$39+AQ149*'"Вес" ПИР'!$B$40+AS149*'"Вес" ПИР'!$B$41+AU149*'"Вес" ПИР'!$B$42+AW149*'"Вес" ПИР'!$B$43+AY149*'"Вес" ПИР'!$B$44+BA149*'"Вес" ПИР'!$B$45)/100 -> 0 | BC149: на стадии подготовки | BE149: на стадии подготовки | BG149: =(BD149*'"Вес" ПИР'!$B$50+BF149*'"Вес" ПИР'!$B$51)/100 -> 0 | BI149: 0 | BK149: 46218 | BL149: =(S149*'"Вес" ПИР'!$B$3+X149*'"Вес" ПИР'!$B$4+AG149*'"Вес" ПИР'!$B$5+BB149*'"Вес" ПИР'!$B$6+BG149*'"Вес" ПИР'!$B$7+BI149*'"Вес" ПИР'!$B$8)/100 -> 0
B150: 2026 | C150: ТОО "5А Engineering" | D150: 116661300 | E150: Акмолинская область | F150: Целиноградский район | G150: с.о. Родина | H150: с.Садовое | I150: Имеется | K150: на стадии подготовки | M150: на стадии подготовки | O150: на стадии подготовки | Q150: на стадии подготовки | S150: =(J150*'"Вес" ПИР'!$B$13+L150*'"Вес" ПИР'!$B$14+N150*'"Вес" ПИР'!$B$15+P150*'"Вес" ПИР'!$B$16+R150*'"Вес" ПИР'!$B$17)/100 -> 0 | T150: Готово | V150: Готово | X150: =(U150*'"Вес" ПИР'!$B$22+W150*'"Вес" ПИР'!$B$23)/100 -> 0 | AG150: =(Z150*'"Вес" ПИР'!$B$28+AB150*'"Вес" ПИР'!$B$29+AD150*'"Вес" ПИР'!$B$30+AF150*'"Вес" ПИР'!$B$31)/100 -> 0 | AJ150: на стадии подготовки | AP150: на стадии подготовки | AR150: на стадии подготовки | AT150: на стадии подготовки | BB150: =(AI150*'"Вес" ПИР'!$B$36+AK150*'"Вес" ПИР'!$B$37+AM150*'"Вес" ПИР'!$B$38+AO150*'"Вес" ПИР'!$B$39+AQ150*'"Вес" ПИР'!$B$40+AS150*'"Вес" ПИР'!$B$41+AU150*'"Вес" ПИР'!$B$42+AW150*'"Вес" ПИР'!$B$43+AY150*'"Вес" ПИР'!$B$44+BA150*'"Вес" ПИР'!$B$45)/100 -> 0 | BC150: на стадии подготовки | BE150: на стадии подготовки | BG150: =(BD150*'"Вес" ПИР'!$B$50+BF150*'"Вес" ПИР'!$B$51)/100 -> 0 | BI150: 0 | BK150: 46218 | BL150: =(S150*'"Вес" ПИР'!$B$3+X150*'"Вес" ПИР'!$B$4+AG150*'"Вес" ПИР'!$B$5+BB150*'"Вес" ПИР'!$B$6+BG150*'"Вес" ПИР'!$B$7+BI150*'"Вес" ПИР'!$B$8)/100 -> 0
B151: 2026 | C151: ТОО "5А Engineering" | D151: 113253300 | E151: Акмолинская область | F151: Аккольский район | G151: Енбекский с.о. | H151: с.Рамадан | I151: Имеется | K151: на стадии подготовки | M151: на стадии подготовки | O151: на стадии подготовки | Q151: на стадии подготовки | S151: =(J151*'"Вес" ПИР'!$B$13+L151*'"Вес" ПИР'!$B$14+N151*'"Вес" ПИР'!$B$15+P151*'"Вес" ПИР'!$B$16+R151*'"Вес" ПИР'!$B$17)/100 -> 0 | T151: Готово | V151: Готово | X151: =(U151*'"Вес" ПИР'!$B$22+W151*'"Вес" ПИР'!$B$23)/100 -> 0 | AG151: =(Z151*'"Вес" ПИР'!$B$28+AB151*'"Вес" ПИР'!$B$29+AD151*'"Вес" ПИР'!$B$30+AF151*'"Вес" ПИР'!$B$31)/100 -> 0 | AJ151: на стадии подготовки | AP151: на стадии подготовки | AR151: на стадии подготовки | AT151: на стадии подготовки | BB151: =(AI151*'"Вес" ПИР'!$B$36+AK151*'"Вес" ПИР'!$B$37+AM151*'"Вес" ПИР'!$B$38+AO151*'"Вес" ПИР'!$B$39+AQ151*'"Вес" ПИР'!$B$40+AS151*'"Вес" ПИР'!$B$41+AU151*'"Вес" ПИР'!$B$42+AW151*'"Вес" ПИР'!$B$43+AY151*'"Вес" ПИР'!$B$44+BA151*'"Вес" ПИР'!$B$45)/100 -> 0 | BC151: на стадии подготовки | BE151: на стадии подготовки | BG151: =(BD151*'"Вес" ПИР'!$B$50+BF151*'"Вес" ПИР'!$B$51)/100 -> 0 | BI151: 0 | BK151: 46218 | BL151: =(S151*'"Вес" ПИР'!$B$3+X151*'"Вес" ПИР'!$B$4+AG151*'"Вес" ПИР'!$B$5+BB151*'"Вес" ПИР'!$B$6+BG151*'"Вес" ПИР'!$B$7+BI151*'"Вес" ПИР'!$B$8)/100 -> 0
B152: 2026 | C152: ТОО "5А Engineering" | D152: 113247200 | E152: Акмолинская область | F152: Аккольский район | G152: Наумовский с.о. | H152: с.Кемеркол | I152: Имеется | K152: на стадии подготовки | M152: на стадии подготовки | O152: на стадии подготовки | Q152: на стадии подготовки | S152: =(J152*'"Вес" ПИР'!$B$13+L152*'"Вес" ПИР'!$B$14+N152*'"Вес" ПИР'!$B$15+P152*'"Вес" ПИР'!$B$16+R152*'"Вес" ПИР'!$B$17)/100 -> 0 | T152: Готово | V152: Готово | X152: =(U152*'"Вес" ПИР'!$B$22+W152*'"Вес" ПИР'!$B$23)/100 -> 0 | AG152: =(Z152*'"Вес" ПИР'!$B$28+AB152*'"Вес" ПИР'!$B$29+AD152*'"Вес" ПИР'!$B$30+AF152*'"Вес" ПИР'!$B$31)/100 -> 0 | AJ152: на стадии подготовки | AP152: на стадии подготовки | AR152: на стадии подготовки | AT152: на стадии подготовки | BB152: =(AI152*'"Вес" ПИР'!$B$36+AK152*'"Вес" ПИР'!$B$37+AM152*'"Вес" ПИР'!$B$38+AO152*'"Вес" ПИР'!$B$39+AQ152*'"Вес" ПИР'!$B$40+AS152*'"Вес" ПИР'!$B$41+AU152*'"Вес" ПИР'!$B$42+AW152*'"Вес" ПИР'!$B$43+AY152*'"Вес" ПИР'!$B$44+BA152*'"Вес" ПИР'!$B$45)/100 -> 0 | BC152: на стадии подготовки | BE152: на стадии подготовки | BG152: =(BD152*'"Вес" ПИР'!$B$50+BF152*'"Вес" ПИР'!$B$51)/100 -> 0 | BI152: 0 | BK152: 46218 | BL152: =(S152*'"Вес" ПИР'!$B$3+X152*'"Вес" ПИР'!$B$4+AG152*'"Вес" ПИР'!$B$5+BB152*'"Вес" ПИР'!$B$6+BG152*'"Вес" ПИР'!$B$7+BI152*'"Вес" ПИР'!$B$8)/100 -> 0
B153: 2026 | C153: ТОО "5А Engineering" | D153: 113640500 | E153: Акмолинская область | F153: Астраханский район | G153: Жалтырский с.о. | H153: с.Жарсуат | I153: Имеется | K153: на стадии подготовки | M153: на стадии подготовки | O153: на стадии подготовки | Q153: на стадии подготовки | S153: =(J153*'"Вес" ПИР'!$B$13+L153*'"Вес" ПИР'!$B$14+N153*'"Вес" ПИР'!$B$15+P153*'"Вес" ПИР'!$B$16+R153*'"Вес" ПИР'!$B$17)/100 -> 0 | T153: 01.12.2025-30.03.2026 | V153: 01.12.2025-30.03.2026 | X153: =(U153*'"Вес" ПИР'!$B$22+W153*'"Вес" ПИР'!$B$23)/100 -> 0 | AG153: =(Z153*'"Вес" ПИР'!$B$28+AB153*'"Вес" ПИР'!$B$29+AD153*'"Вес" ПИР'!$B$30+AF153*'"Вес" ПИР'!$B$31)/100 -> 0 | AJ153: на стадии подготовки | AP153: на стадии подготовки | AR153: на стадии подготовки | AT153: на стадии подготовки | BB153: =(AI153*'"Вес" ПИР'!$B$36+AK153*'"Вес" ПИР'!$B$37+AM153*'"Вес" ПИР'!$B$38+AO153*'"Вес" ПИР'!$B$39+AQ153*'"Вес" ПИР'!$B$40+AS153*'"Вес" ПИР'!$B$41+AU153*'"Вес" ПИР'!$B$42+AW153*'"Вес" ПИР'!$B$43+AY153*'"Вес" ПИР'!$B$44+BA153*'"Вес" ПИР'!$B$45)/100 -> 0 | BC153: на стадии подготовки | BE153: на стадии подготовки | BG153: =(BD153*'"Вес" ПИР'!$B$50+BF153*'"Вес" ПИР'!$B$51)/100 -> 0 | BI153: 0 | BK153: 46266 | BL153: =(S153*'"Вес" ПИР'!$B$3+X153*'"Вес" ПИР'!$B$4+AG153*'"Вес" ПИР'!$B$5+BB153*'"Вес" ПИР'!$B$6+BG153*'"Вес" ПИР'!$B$7+BI153*'"Вес" ПИР'!$B$8)/100 -> 0
B154: 2026 | C154: ТОО "5А Engineering" | D154: 114047200 | E154: Акмолинская область | F154: Буландынский район | G154: Новобратский с.о. | H154: с.Буденовка | I154: Имеется | K154: на стадии подготовки | M154: на стадии подготовки | O154: на стадии подготовки | Q154: на стадии подготовки | S154: =(J154*'"Вес" ПИР'!$B$13+L154*'"Вес" ПИР'!$B$14+N154*'"Вес" ПИР'!$B$15+P154*'"Вес" ПИР'!$B$16+R154*'"Вес" ПИР'!$B$17)/100 -> 0 | T154: Готово | V154: Готово | X154: =(U154*'"Вес" ПИР'!$B$22+W154*'"Вес" ПИР'!$B$23)/100 -> 0 | AG154: =(Z154*'"Вес" ПИР'!$B$28+AB154*'"Вес" ПИР'!$B$29+AD154*'"Вес" ПИР'!$B$30+AF154*'"Вес" ПИР'!$B$31)/100 -> 0 | AJ154: на стадии подготовки | AP154: на стадии подготовки | AR154: на стадии подготовки | AT154: на стадии подготовки | BB154: =(AI154*'"Вес" ПИР'!$B$36+AK154*'"Вес" ПИР'!$B$37+AM154*'"Вес" ПИР'!$B$38+AO154*'"Вес" ПИР'!$B$39+AQ154*'"Вес" ПИР'!$B$40+AS154*'"Вес" ПИР'!$B$41+AU154*'"Вес" ПИР'!$B$42+AW154*'"Вес" ПИР'!$B$43+AY154*'"Вес" ПИР'!$B$44+BA154*'"Вес" ПИР'!$B$45)/100 -> 0 | BC154: на стадии подготовки | BE154: на стадии подготовки | BG154: =(BD154*'"Вес" ПИР'!$B$50+BF154*'"Вес" ПИР'!$B$51)/100 -> 0 | BI154: 0 | BK154: 46218 | BL154: =(S154*'"Вес" ПИР'!$B$3+X154*'"Вес" ПИР'!$B$4+AG154*'"Вес" ПИР'!$B$5+BB154*'"Вес" ПИР'!$B$6+BG154*'"Вес" ПИР'!$B$7+BI154*'"Вес" ПИР'!$B$8)/100 -> 0
B155: 2026 | C155: ТОО "5А Engineering" | D155: 114645300 | E155: Акмолинская область | F155: Ерейментауский район | G155: Куншалганский с.о. | H155: с.Шакей | I155: Имеется | K155: на стадии подготовки | M155: на стадии подготовки | O155: на стадии подготовки | Q155: на стадии подготовки | S155: =(J155*'"Вес" ПИР'!$B$13+L155*'"Вес" ПИР'!$B$14+N155*'"Вес" ПИР'!$B$15+P155*'"Вес" ПИР'!$B$16+R155*'"Вес" ПИР'!$B$17)/100 -> 0 | T155: Готово | V155: Готово | X155: =(U155*'"Вес" ПИР'!$B$22+W155*'"Вес" ПИР'!$B$23)/100 -> 0 | AG155: =(Z155*'"Вес" ПИР'!$B$28+AB155*'"Вес" ПИР'!$B$29+AD155*'"Вес" ПИР'!$B$30+AF155*'"Вес" ПИР'!$B$31)/100 -> 0 | AJ155: на стадии подготовки | AP155: на стадии подготовки | AR155: на стадии подготовки | AT155: на стадии подготовки | BB155: =(AI155*'"Вес" ПИР'!$B$36+AK155*'"Вес" ПИР'!$B$37+AM155*'"Вес" ПИР'!$B$38+AO155*'"Вес" ПИР'!$B$39+AQ155*'"Вес" ПИР'!$B$40+AS155*'"Вес" ПИР'!$B$41+AU155*'"Вес" ПИР'!$B$42+AW155*'"Вес" ПИР'!$B$43+AY155*'"Вес" ПИР'!$B$44+BA155*'"Вес" ПИР'!$B$45)/100 -> 0 | BC155: на стадии подготовки | BE155: на стадии подготовки | BG155: =(BD155*'"Вес" ПИР'!$B$50+BF155*'"Вес" ПИР'!$B$51)/100 -> 0 | BI155: 0 | BK155: 46218 | BL155: =(S155*'"Вес" ПИР'!$B$3+X155*'"Вес" ПИР'!$B$4+AG155*'"Вес" ПИР'!$B$5+BB155*'"Вес" ПИР'!$B$6+BG155*'"Вес" ПИР'!$B$7+BI155*'"Вес" ПИР'!$B$8)/100 -> 0
B156: 2026 | C156: ТОО "5А Engineering" | D156: 115655200 | E156: Акмолинская область | F156: Зерендинский район | G156: с.о. Малика Габдуллина | H156: с.Дороговка | I156: Имеется | K156: на стадии подготовки | M156: на стадии подготовки | O156: на стадии подготовки | Q156: на стадии подготовки | S156: =(J156*'"Вес" ПИР'!$B$13+L156*'"Вес" ПИР'!$B$14+N156*'"Вес" ПИР'!$B$15+P156*'"Вес" ПИР'!$B$16+R156*'"Вес" ПИР'!$B$17)/100 -> 0 | T156: 01.12.2025-30.03.2026 | V156: 01.12.2025-30.03.2026 | X156: =(U156*'"Вес" ПИР'!$B$22+W156*'"Вес" ПИР'!$B$23)/100 -> 0 | AG156: =(Z156*'"Вес" ПИР'!$B$28+AB156*'"Вес" ПИР'!$B$29+AD156*'"Вес" ПИР'!$B$30+AF156*'"Вес" ПИР'!$B$31)/100 -> 0 | AJ156: на стадии подготовки | AP156: на стадии подготовки | AR156: на стадии подготовки | AT156: на стадии подготовки | BB156: =(AI156*'"Вес" ПИР'!$B$36+AK156*'"Вес" ПИР'!$B$37+AM156*'"Вес" ПИР'!$B$38+AO156*'"Вес" ПИР'!$B$39+AQ156*'"Вес" ПИР'!$B$40+AS156*'"Вес" ПИР'!$B$41+AU156*'"Вес" ПИР'!$B$42+AW156*'"Вес" ПИР'!$B$43+AY156*'"Вес" ПИР'!$B$44+BA156*'"Вес" ПИР'!$B$45)/100 -> 0 | BC156: на стадии подготовки | BE156: на стадии подготовки | BG156: =(BD156*'"Вес" ПИР'!$B$50+BF156*'"Вес" ПИР'!$B$51)/100 -> 0 | BI156: 0 | BK156: 46266 | BL156: =(S156*'"Вес" ПИР'!$B$3+X156*'"Вес" ПИР'!$B$4+AG156*'"Вес" ПИР'!$B$5+BB156*'"Вес" ПИР'!$B$6+BG156*'"Вес" ПИР'!$B$7+BI156*'"Вес" ПИР'!$B$8)/100 -> 0
B157: 2026 | C157: ТОО "5А Engineering" | D157: 115655700 | E157: Акмолинская область | F157: Зерендинский район | G157: с.о. Малика Габдуллина | H157: с.Малые Тюкты | I157: Имеется | K157: на стадии подготовки | M157: на стадии подготовки | O157: на стадии подготовки | Q157: на стадии подготовки | S157: =(J157*'"Вес" ПИР'!$B$13+L157*'"Вес" ПИР'!$B$14+N157*'"Вес" ПИР'!$B$15+P157*'"Вес" ПИР'!$B$16+R157*'"Вес" ПИР'!$B$17)/100 -> 0 | T157: 01.12.2025-30.03.2026 | V157: 01.12.2025-30.03.2026 | X157: =(U157*'"Вес" ПИР'!$B$22+W157*'"Вес" ПИР'!$B$23)/100 -> 0 | AG157: =(Z157*'"Вес" ПИР'!$B$28+AB157*'"Вес" ПИР'!$B$29+AD157*'"Вес" ПИР'!$B$30+AF157*'"Вес" ПИР'!$B$31)/100 -> 0 | AJ157: на стадии подготовки | AP157: на стадии подготовки | AR157: на стадии подготовки | AT157: на стадии подготовки | BB157: =(AI157*'"Вес" ПИР'!$B$36+AK157*'"Вес" ПИР'!$B$37+AM157*'"Вес" ПИР'!$B$38+AO157*'"Вес" ПИР'!$B$39+AQ157*'"Вес" ПИР'!$B$40+AS157*'"Вес" ПИР'!$B$41+AU157*'"Вес" ПИР'!$B$42+AW157*'"Вес" ПИР'!$B$43+AY157*'"Вес" ПИР'!$B$44+BA157*'"Вес" ПИР'!$B$45)/100 -> 0 | BC157: на стадии подготовки | BE157: на стадии подготовки | BG157: =(BD157*'"Вес" ПИР'!$B$50+BF157*'"Вес" ПИР'!$B$51)/100 -> 0 | BI157: 0 | BK157: 46266 | BL157: =(S157*'"Вес" ПИР'!$B$3+X157*'"Вес" ПИР'!$B$4+AG157*'"Вес" ПИР'!$B$5+BB157*'"Вес" ПИР'!$B$6+BG157*'"Вес" ПИР'!$B$7+BI157*'"Вес" ПИР'!$B$8)/100 -> 0
B158: 2026 | C158: ТОО "5А Engineering" | D158: 115655800 | E158: Акмолинская область | F158: Зерендинский район | G158: с.о. Малика Габдуллина | H158: с.Серафимовка | I158: Имеется | K158: на стадии подготовки | M158: на стадии подготовки | O158: на стадии подготовки | Q158: на стадии подготовки | S158: =(J158*'"Вес" ПИР'!$B$13+L158*'"Вес" ПИР'!$B$14+N158*'"Вес" ПИР'!$B$15+P158*'"Вес" ПИР'!$B$16+R158*'"Вес" ПИР'!$B$17)/100 -> 0 | T158: 01.12.2025-30.03.2026 | V158: 01.12.2025-30.03.2026 | X158: =(U158*'"Вес" ПИР'!$B$22+W158*'"Вес" ПИР'!$B$23)/100 -> 0 | AG158: =(Z158*'"Вес" ПИР'!$B$28+AB158*'"Вес" ПИР'!$B$29+AD158*'"Вес" ПИР'!$B$30+AF158*'"Вес" ПИР'!$B$31)/100 -> 0 | AJ158: на стадии подготовки | AP158: на стадии подготовки | AR158: на стадии подготовки | AT158: на стадии подготовки | BB158: =(AI158*'"Вес" ПИР'!$B$36+AK158*'"Вес" ПИР'!$B$37+AM158*'"Вес" ПИР'!$B$38+AO158*'"Вес" ПИР'!$B$39+AQ158*'"Вес" ПИР'!$B$40+AS158*'"Вес" ПИР'!$B$41+AU158*'"Вес" ПИР'!$B$42+AW158*'"Вес" ПИР'!$B$43+AY158*'"Вес" ПИР'!$B$44+BA158*'"Вес" ПИР'!$B$45)/100 -> 0 | BC158: на стадии подготовки | BE158: на стадии подготовки | BG158: =(BD158*'"Вес" ПИР'!$B$50+BF158*'"Вес" ПИР'!$B$51)/100 -> 0 | BI158: 0 | BK158: 46266 | BL158: =(S158*'"Вес" ПИР'!$B$3+X158*'"Вес" ПИР'!$B$4+AG158*'"Вес" ПИР'!$B$5+BB158*'"Вес" ПИР'!$B$6+BG158*'"Вес" ПИР'!$B$7+BI158*'"Вес" ПИР'!$B$8)/100 -> 0
B159: 2026 | C159: ТОО "5А Engineering" | D159: 115657300 | E159: Акмолинская область | F159: Зерендинский район | G159: Симферопольский с.о. | H159: с.Жолдыбай | I159: Имеется | K159: на стадии подготовки | M159: на стадии подготовки | O159: на стадии подготовки | Q159: на стадии подготовки | S159: =(J159*'"Вес" ПИР'!$B$13+L159*'"Вес" ПИР'!$B$14+N159*'"Вес" ПИР'!$B$15+P159*'"Вес" ПИР'!$B$16+R159*'"Вес" ПИР'!$B$17)/100 -> 0 | T159: 01.12.2025-30.03.2026 | V159: 01.12.2025-30.03.2026 | X159: =(U159*'"Вес" ПИР'!$B$22+W159*'"Вес" ПИР'!$B$23)/100 -> 0 | AG159: =(Z159*'"Вес" ПИР'!$B$28+AB159*'"Вес" ПИР'!$B$29+AD159*'"Вес" ПИР'!$B$30+AF159*'"Вес" ПИР'!$B$31)/100 -> 0 | AJ159: на стадии подготовки | AP159: на стадии подготовки | AR159: на стадии подготовки | AT159: на стадии подготовки | BB159: =(AI159*'"Вес" ПИР'!$B$36+AK159*'"Вес" ПИР'!$B$37+AM159*'"Вес" ПИР'!$B$38+AO159*'"Вес" ПИР'!$B$39+AQ159*'"Вес" ПИР'!$B$40+AS159*'"Вес" ПИР'!$B$41+AU159*'"Вес" ПИР'!$B$42+AW159*'"Вес" ПИР'!$B$43+AY159*'"Вес" ПИР'!$B$44+BA159*'"Вес" ПИР'!$B$45)/100 -> 0 | BC159: на стадии подготовки | BE159: на стадии подготовки | BG159: =(BD159*'"Вес" ПИР'!$B$50+BF159*'"Вес" ПИР'!$B$51)/100 -> 0 | BI159: 0 | BK159: 46266 | BL159: =(S159*'"Вес" ПИР'!$B$3+X159*'"Вес" ПИР'!$B$4+AG159*'"Вес" ПИР'!$B$5+BB159*'"Вес" ПИР'!$B$6+BG159*'"Вес" ПИР'!$B$7+BI159*'"Вес" ПИР'!$B$8)/100 -> 0
B160: 2026 | C160: ТОО "5А Engineering" | D160: 113651200 | E160: Акмолинская область | F160: Астраханский район | G160: Острогорский с.о. | H160: с.Караколь | I160: Имеется | K160: на стадии подготовки | M160: на стадии подготовки | O160: на стадии подготовки | Q160: на стадии подготовки | S160: =(J160*'"Вес" ПИР'!$B$13+L160*'"Вес" ПИР'!$B$14+N160*'"Вес" ПИР'!$B$15+P160*'"Вес" ПИР'!$B$16+R160*'"Вес" ПИР'!$B$17)/100 -> 0 | T160: 01.12.2025-30.03.2026 | V160: 01.12.2025-30.03.2026 | X160: =(U160*'"Вес" ПИР'!$B$22+W160*'"Вес" ПИР'!$B$23)/100 -> 0 | AG160: =(Z160*'"Вес" ПИР'!$B$28+AB160*'"Вес" ПИР'!$B$29+AD160*'"Вес" ПИР'!$B$30+AF160*'"Вес" ПИР'!$B$31)/100 -> 0 | AJ160: на стадии подготовки | AP160: на стадии подготовки | AR160: на стадии подготовки | AT160: на стадии подготовки | BB160: =(AI160*'"Вес" ПИР'!$B$36+AK160*'"Вес" ПИР'!$B$37+AM160*'"Вес" ПИР'!$B$38+AO160*'"Вес" ПИР'!$B$39+AQ160*'"Вес" ПИР'!$B$40+AS160*'"Вес" ПИР'!$B$41+AU160*'"Вес" ПИР'!$B$42+AW160*'"Вес" ПИР'!$B$43+AY160*'"Вес" ПИР'!$B$44+BA160*'"Вес" ПИР'!$B$45)/100 -> 0 | BC160: на стадии подготовки | BE160: на стадии подготовки | BG160: =(BD160*'"Вес" ПИР'!$B$50+BF160*'"Вес" ПИР'!$B$51)/100 -> 0 | BI160: 0 | BK160: 46266 | BL160: =(S160*'"Вес" ПИР'!$B$3+X160*'"Вес" ПИР'!$B$4+AG160*'"Вес" ПИР'!$B$5+BB160*'"Вес" ПИР'!$B$6+BG160*'"Вес" ПИР'!$B$7+BI160*'"Вес" ПИР'!$B$8)/100 -> 0
B161: 2026 | C161: ТОО "5А Engineering" | D161: 116039100 | E161: Акмолинская область | F161: Коргалжынский район | G161: Майшукурский с.о. | H161: с.Майшукур | I161: Имеется | K161: на стадии подготовки | M161: на стадии подготовки | O161: на стадии подготовки | Q161: на стадии подготовки | S161: =(J161*'"Вес" ПИР'!$B$13+L161*'"Вес" ПИР'!$B$14+N161*'"Вес" ПИР'!$B$15+P161*'"Вес" ПИР'!$B$16+R161*'"Вес" ПИР'!$B$17)/100 -> 0 | T161: Готово | V161: Готово | X161: =(U161*'"Вес" ПИР'!$B$22+W161*'"Вес" ПИР'!$B$23)/100 -> 0 | AG161: =(Z161*'"Вес" ПИР'!$B$28+AB161*'"Вес" ПИР'!$B$29+AD161*'"Вес" ПИР'!$B$30+AF161*'"Вес" ПИР'!$B$31)/100 -> 0 | AJ161: на стадии подготовки | AP161: на стадии подготовки | AR161: на стадии подготовки | AT161: на стадии подготовки | BB161: =(AI161*'"Вес" ПИР'!$B$36+AK161*'"Вес" ПИР'!$B$37+AM161*'"Вес" ПИР'!$B$38+AO161*'"Вес" ПИР'!$B$39+AQ161*'"Вес" ПИР'!$B$40+AS161*'"Вес" ПИР'!$B$41+AU161*'"Вес" ПИР'!$B$42+AW161*'"Вес" ПИР'!$B$43+AY161*'"Вес" ПИР'!$B$44+BA161*'"Вес" ПИР'!$B$45)/100 -> 0 | BC161: на стадии подготовки | BE161: на стадии подготовки | BG161: =(BD161*'"Вес" ПИР'!$B$50+BF161*'"Вес" ПИР'!$B$51)/100 -> 0 | BI161: 0 | BK161: 31.09.2026 | BL161: =(S161*'"Вес" ПИР'!$B$3+X161*'"Вес" ПИР'!$B$4+AG161*'"Вес" ПИР'!$B$5+BB161*'"Вес" ПИР'!$B$6+BG161*'"Вес" ПИР'!$B$7+BI161*'"Вес" ПИР'!$B$8)/100 -> 0
B162: 2026 | C162: ТОО "5А Engineering" | D162: 116453300 | E162: Акмолинская область | F162: Сандыктауский район | G162: Новоникольский с.о. | H162: с.Меньшиковка | I162: Имеется | K162: на стадии подготовки | M162: на стадии подготовки | O162: на стадии подготовки | Q162: на стадии подготовки | S162: =(J162*'"Вес" ПИР'!$B$13+L162*'"Вес" ПИР'!$B$14+N162*'"Вес" ПИР'!$B$15+P162*'"Вес" ПИР'!$B$16+R162*'"Вес" ПИР'!$B$17)/100 -> 0 | T162: 01.12.2025-30.03.2026 | V162: 01.12.2025-30.03.2026 | X162: =(U162*'"Вес" ПИР'!$B$22+W162*'"Вес" ПИР'!$B$23)/100 -> 0 | AG162: =(Z162*'"Вес" ПИР'!$B$28+AB162*'"Вес" ПИР'!$B$29+AD162*'"Вес" ПИР'!$B$30+AF162*'"Вес" ПИР'!$B$31)/100 -> 0 | AJ162: на стадии подготовки | AP162: на стадии подготовки | AR162: на стадии подготовки | AT162: на стадии подготовки | BB162: =(AI162*'"Вес" ПИР'!$B$36+AK162*'"Вес" ПИР'!$B$37+AM162*'"Вес" ПИР'!$B$38+AO162*'"Вес" ПИР'!$B$39+AQ162*'"Вес" ПИР'!$B$40+AS162*'"Вес" ПИР'!$B$41+AU162*'"Вес" ПИР'!$B$42+AW162*'"Вес" ПИР'!$B$43+AY162*'"Вес" ПИР'!$B$44+BA162*'"Вес" ПИР'!$B$45)/100 -> 0 | BC162: на стадии подготовки | BE162: на стадии подготовки | BG162: =(BD162*'"Вес" ПИР'!$B$50+BF162*'"Вес" ПИР'!$B$51)/100 -> 0 | BI162: 0 | BK162: 46266 | BL162: =(S162*'"Вес" ПИР'!$B$3+X162*'"Вес" ПИР'!$B$4+AG162*'"Вес" ПИР'!$B$5+BB162*'"Вес" ПИР'!$B$6+BG162*'"Вес" ПИР'!$B$7+BI162*'"Вес" ПИР'!$B$8)/100 -> 0
B163: 2026 | C163: ТОО "5А Engineering" | D163: 116843200 | E163: Акмолинская область | F163: Шортандинский район | G163: Новокубанский с.о. | H163: с.Алтайское | I163: Имеется | K163: на стадии подготовки | M163: на стадии подготовки | O163: на стадии подготовки | Q163: на стадии подготовки | S163: =(J163*'"Вес" ПИР'!$B$13+L163*'"Вес" ПИР'!$B$14+N163*'"Вес" ПИР'!$B$15+P163*'"Вес" ПИР'!$B$16+R163*'"Вес" ПИР'!$B$17)/100 -> 0 | T163: 01.12.2025-30.03.2026 | V163: 01.12.2025-30.03.2026 | X163: =(U163*'"Вес" ПИР'!$B$22+W163*'"Вес" ПИР'!$B$23)/100 -> 0 | AG163: =(Z163*'"Вес" ПИР'!$B$28+AB163*'"Вес" ПИР'!$B$29+AD163*'"Вес" ПИР'!$B$30+AF163*'"Вес" ПИР'!$B$31)/100 -> 0 | AJ163: на стадии подготовки | AP163: на стадии подготовки | AR163: на стадии подготовки | AT163: на стадии подготовки | BB163: =(AI163*'"Вес" ПИР'!$B$36+AK163*'"Вес" ПИР'!$B$37+AM163*'"Вес" ПИР'!$B$38+AO163*'"Вес" ПИР'!$B$39+AQ163*'"Вес" ПИР'!$B$40+AS163*'"Вес" ПИР'!$B$41+AU163*'"Вес" ПИР'!$B$42+AW163*'"Вес" ПИР'!$B$43+AY163*'"Вес" ПИР'!$B$44+BA163*'"Вес" ПИР'!$B$45)/100 -> 0 | BC163: на стадии подготовки | BE163: на стадии подготовки | BG163: =(BD163*'"Вес" ПИР'!$B$50+BF163*'"Вес" ПИР'!$B$51)/100 -> 0 | BI163: 0 | BK163: 46266 | BL163: =(S163*'"Вес" ПИР'!$B$3+X163*'"Вес" ПИР'!$B$4+AG163*'"Вес" ПИР'!$B$5+BB163*'"Вес" ПИР'!$B$6+BG163*'"Вес" ПИР'!$B$7+BI163*'"Вес" ПИР'!$B$8)/100 -> 0
B164: 2026 | C164: ТОО "5А Engineering" | D164: 114043200 | E164: Акмолинская область | F164: Буландынский район | G164: Карамышевский с.о. | H164: с. Мат | I164: Имеется | K164: на стадии подготовки | M164: на стадии подготовки | O164: на стадии подготовки | Q164: на стадии подготовки | S164: =(J164*'"Вес" ПИР'!$B$13+L164*'"Вес" ПИР'!$B$14+N164*'"Вес" ПИР'!$B$15+P164*'"Вес" ПИР'!$B$16+R164*'"Вес" ПИР'!$B$17)/100 -> 0 | T164: Готово | V164: Готово | X164: =(U164*'"Вес" ПИР'!$B$22+W164*'"Вес" ПИР'!$B$23)/100 -> 0 | AG164: =(Z164*'"Вес" ПИР'!$B$28+AB164*'"Вес" ПИР'!$B$29+AD164*'"Вес" ПИР'!$B$30+AF164*'"Вес" ПИР'!$B$31)/100 -> 0 | AJ164: на стадии подготовки | AP164: на стадии подготовки | AR164: на стадии подготовки | AT164: на стадии подготовки | BB164: =(AI164*'"Вес" ПИР'!$B$36+AK164*'"Вес" ПИР'!$B$37+AM164*'"Вес" ПИР'!$B$38+AO164*'"Вес" ПИР'!$B$39+AQ164*'"Вес" ПИР'!$B$40+AS164*'"Вес" ПИР'!$B$41+AU164*'"Вес" ПИР'!$B$42+AW164*'"Вес" ПИР'!$B$43+AY164*'"Вес" ПИР'!$B$44+BA164*'"Вес" ПИР'!$B$45)/100 -> 0 | BC164: на стадии подготовки | BE164: на стадии подготовки | BG164: =(BD164*'"Вес" ПИР'!$B$50+BF164*'"Вес" ПИР'!$B$51)/100 -> 0 | BI164: 0 | BK164: 46218 | BL164: =(S164*'"Вес" ПИР'!$B$3+X164*'"Вес" ПИР'!$B$4+AG164*'"Вес" ПИР'!$B$5+BB164*'"Вес" ПИР'!$B$6+BG164*'"Вес" ПИР'!$B$7+BI164*'"Вес" ПИР'!$B$8)/100 -> 0
B165: 2026 | C165: ТОО "5А Engineering" | D165: 117055400 | E165: Акмолинская область | F165: Бурабайский район | G165: Атамекен с.о. | H165: с. Жасыл | I165: Имеется | K165: на стадии подготовки | M165: на стадии подготовки | O165: на стадии подготовки | Q165: на стадии подготовки | S165: =(J165*'"Вес" ПИР'!$B$13+L165*'"Вес" ПИР'!$B$14+N165*'"Вес" ПИР'!$B$15+P165*'"Вес" ПИР'!$B$16+R165*'"Вес" ПИР'!$B$17)/100 -> 0 | T165: 01.12.2025-30.03.2026 | V165: 01.12.2025-30.03.2026 | X165: =(U165*'"Вес" ПИР'!$B$22+W165*'"Вес" ПИР'!$B$23)/100 -> 0 | AG165: =(Z165*'"Вес" ПИР'!$B$28+AB165*'"Вес" ПИР'!$B$29+AD165*'"Вес" ПИР'!$B$30+AF165*'"Вес" ПИР'!$B$31)/100 -> 0 | AJ165: на стадии подготовки | AP165: на стадии подготовки | AR165: на стадии подготовки | AT165: на стадии подготовки | BB165: =(AI165*'"Вес" ПИР'!$B$36+AK165*'"Вес" ПИР'!$B$37+AM165*'"Вес" ПИР'!$B$38+AO165*'"Вес" ПИР'!$B$39+AQ165*'"Вес" ПИР'!$B$40+AS165*'"Вес" ПИР'!$B$41+AU165*'"Вес" ПИР'!$B$42+AW165*'"Вес" ПИР'!$B$43+AY165*'"Вес" ПИР'!$B$44+BA165*'"Вес" ПИР'!$B$45)/100 -> 0 | BC165: на стадии подготовки | BE165: на стадии подготовки | BG165: =(BD165*'"Вес" ПИР'!$B$50+BF165*'"Вес" ПИР'!$B$51)/100 -> 0 | BI165: 0 | BK165: 46266 | BL165: =(S165*'"Вес" ПИР'!$B$3+X165*'"Вес" ПИР'!$B$4+AG165*'"Вес" ПИР'!$B$5+BB165*'"Вес" ПИР'!$B$6+BG165*'"Вес" ПИР'!$B$7+BI165*'"Вес" ПИР'!$B$8)/100 -> 0
B166: 2026 | C166: ТОО "5А Engineering" | D166: 113433300 | E166: Акмолинская область | F166: Аршалынский район | G166: с.о. Жибек жолы | H166: рзд. 41 | I166: Имеется | K166: на стадии подготовки | M166: на стадии подготовки | O166: на стадии подготовки | Q166: на стадии подготовки | S166: =(J166*'"Вес" ПИР'!$B$13+L166*'"Вес" ПИР'!$B$14+N166*'"Вес" ПИР'!$B$15+P166*'"Вес" ПИР'!$B$16+R166*'"Вес" ПИР'!$B$17)/100 -> 0 | T166: 01.12.2025-30.03.2026 | V166: 01.12.2025-30.03.2026 | X166: =(U166*'"Вес" ПИР'!$B$22+W166*'"Вес" ПИР'!$B$23)/100 -> 0 | AG166: =(Z166*'"Вес" ПИР'!$B$28+AB166*'"Вес" ПИР'!$B$29+AD166*'"Вес" ПИР'!$B$30+AF166*'"Вес" ПИР'!$B$31)/100 -> 0 | AJ166: на стадии подготовки | AP166: на стадии подготовки | AR166: на стадии подготовки | AT166: на стадии подготовки | BB166: =(AI166*'"Вес" ПИР'!$B$36+AK166*'"Вес" ПИР'!$B$37+AM166*'"Вес" ПИР'!$B$38+AO166*'"Вес" ПИР'!$B$39+AQ166*'"Вес" ПИР'!$B$40+AS166*'"Вес" ПИР'!$B$41+AU166*'"Вес" ПИР'!$B$42+AW166*'"Вес" ПИР'!$B$43+AY166*'"Вес" ПИР'!$B$44+BA166*'"Вес" ПИР'!$B$45)/100 -> 0 | BC166: на стадии подготовки | BE166: на стадии подготовки | BG166: =(BD166*'"Вес" ПИР'!$B$50+BF166*'"Вес" ПИР'!$B$51)/100 -> 0 | BI166: 0 | BK166: 46266 | BL166: =(S166*'"Вес" ПИР'!$B$3+X166*'"Вес" ПИР'!$B$4+AG166*'"Вес" ПИР'!$B$5+BB166*'"Вес" ПИР'!$B$6+BG166*'"Вес" ПИР'!$B$7+BI166*'"Вес" ПИР'!$B$8)/100 -> 0
B167: 2026 | C167: ТОО "5А Engineering" | D167: 114659200 | E167: Акмолинская область | F167: Ерейментауский район | G167: Тургайский с.о. | H167: с. Нижний Торгай | I167: Имеется | K167: на стадии подготовки | M167: на стадии подготовки | O167: на стадии подготовки | Q167: на стадии подготовки | S167: =(J167*'"Вес" ПИР'!$B$13+L167*'"Вес" ПИР'!$B$14+N167*'"Вес" ПИР'!$B$15+P167*'"Вес" ПИР'!$B$16+R167*'"Вес" ПИР'!$B$17)/100 -> 0 | T167: Готово | V167: Готово | X167: =(U167*'"Вес" ПИР'!$B$22+W167*'"Вес" ПИР'!$B$23)/100 -> 0 | AG167: =(Z167*'"Вес" ПИР'!$B$28+AB167*'"Вес" ПИР'!$B$29+AD167*'"Вес" ПИР'!$B$30+AF167*'"Вес" ПИР'!$B$31)/100 -> 0 | AJ167: на стадии подготовки | AP167: на стадии подготовки | AR167: на стадии подготовки | AT167: на стадии подготовки | BB167: =(AI167*'"Вес" ПИР'!$B$36+AK167*'"Вес" ПИР'!$B$37+AM167*'"Вес" ПИР'!$B$38+AO167*'"Вес" ПИР'!$B$39+AQ167*'"Вес" ПИР'!$B$40+AS167*'"Вес" ПИР'!$B$41+AU167*'"Вес" ПИР'!$B$42+AW167*'"Вес" ПИР'!$B$43+AY167*'"Вес" ПИР'!$B$44+BA167*'"Вес" ПИР'!$B$45)/100 -> 0 | BC167: на стадии подготовки | BE167: на стадии подготовки | BG167: =(BD167*'"Вес" ПИР'!$B$50+BF167*'"Вес" ПИР'!$B$51)/100 -> 0 | BI167: 0 | BK167: 46218 | BL167: =(S167*'"Вес" ПИР'!$B$3+X167*'"Вес" ПИР'!$B$4+AG167*'"Вес" ПИР'!$B$5+BB167*'"Вес" ПИР'!$B$6+BG167*'"Вес" ПИР'!$B$7+BI167*'"Вес" ПИР'!$B$8)/100 -> 0
B168: 2026 | C168: ТОО "5А Engineering" | D168: 114879300 | E168: Акмолинская область | F168: Есильский район | G168: Интернациональный с.о. | H168: с. Биртал | I168: Имеется | K168: на стадии подготовки | M168: на стадии подготовки | O168: на стадии подготовки | Q168: на стадии подготовки | S168: =(J168*'"Вес" ПИР'!$B$13+L168*'"Вес" ПИР'!$B$14+N168*'"Вес" ПИР'!$B$15+P168*'"Вес" ПИР'!$B$16+R168*'"Вес" ПИР'!$B$17)/100 -> 0 | T168: Готово | V168: Готово | X168: =(U168*'"Вес" ПИР'!$B$22+W168*'"Вес" ПИР'!$B$23)/100 -> 0 | AG168: =(Z168*'"Вес" ПИР'!$B$28+AB168*'"Вес" ПИР'!$B$29+AD168*'"Вес" ПИР'!$B$30+AF168*'"Вес" ПИР'!$B$31)/100 -> 0 | AJ168: на стадии подготовки | AP168: на стадии подготовки | AR168: на стадии подготовки | AT168: на стадии подготовки | BB168: =(AI168*'"Вес" ПИР'!$B$36+AK168*'"Вес" ПИР'!$B$37+AM168*'"Вес" ПИР'!$B$38+AO168*'"Вес" ПИР'!$B$39+AQ168*'"Вес" ПИР'!$B$40+AS168*'"Вес" ПИР'!$B$41+AU168*'"Вес" ПИР'!$B$42+AW168*'"Вес" ПИР'!$B$43+AY168*'"Вес" ПИР'!$B$44+BA168*'"Вес" ПИР'!$B$45)/100 -> 0 | BC168: на стадии подготовки | BE168: на стадии подготовки | BG168: =(BD168*'"Вес" ПИР'!$B$50+BF168*'"Вес" ПИР'!$B$51)/100 -> 0 | BI168: 0 | BK168: 31.09.2026 | BL168: =(S168*'"Вес" ПИР'!$B$3+X168*'"Вес" ПИР'!$B$4+AG168*'"Вес" ПИР'!$B$5+BB168*'"Вес" ПИР'!$B$6+BG168*'"Вес" ПИР'!$B$7+BI168*'"Вес" ПИР'!$B$8)/100 -> 0
B169: 2026 | C169: ТОО "5А Engineering" | D169: 113220400 | E169: Акмолинская область | F169: Аккольский район | H169: с. Радовка | I169: Имеется | K169: на стадии подготовки | M169: на стадии подготовки | O169: на стадии подготовки | Q169: на стадии подготовки | S169: =(J169*'"Вес" ПИР'!$B$13+L169*'"Вес" ПИР'!$B$14+N169*'"Вес" ПИР'!$B$15+P169*'"Вес" ПИР'!$B$16+R169*'"Вес" ПИР'!$B$17)/100 -> 0 | T169: Готово | V169: Готово | X169: =(U169*'"Вес" ПИР'!$B$22+W169*'"Вес" ПИР'!$B$23)/100 -> 0 | AG169: =(Z169*'"Вес" ПИР'!$B$28+AB169*'"Вес" ПИР'!$B$29+AD169*'"Вес" ПИР'!$B$30+AF169*'"Вес" ПИР'!$B$31)/100 -> 0 | AJ169: на стадии подготовки | AP169: на стадии подготовки | AR169: на стадии подготовки | AT169: на стадии подготовки | BB169: =(AI169*'"Вес" ПИР'!$B$36+AK169*'"Вес" ПИР'!$B$37+AM169*'"Вес" ПИР'!$B$38+AO169*'"Вес" ПИР'!$B$39+AQ169*'"Вес" ПИР'!$B$40+AS169*'"Вес" ПИР'!$B$41+AU169*'"Вес" ПИР'!$B$42+AW169*'"Вес" ПИР'!$B$43+AY169*'"Вес" ПИР'!$B$44+BA169*'"Вес" ПИР'!$B$45)/100 -> 0 | BC169: на стадии подготовки | BE169: на стадии подготовки | BG169: =(BD169*'"Вес" ПИР'!$B$50+BF169*'"Вес" ПИР'!$B$51)/100 -> 0 | BI169: 0 | BK169: 46218 | BL169: =(S169*'"Вес" ПИР'!$B$3+X169*'"Вес" ПИР'!$B$4+AG169*'"Вес" ПИР'!$B$5+BB169*'"Вес" ПИР'!$B$6+BG169*'"Вес" ПИР'!$B$7+BI169*'"Вес" ПИР'!$B$8)/100 -> 0
B170: 2026 | C170: ТОО "5А Engineering" | D170: 113447200 | E170: Акмолинская область | F170: Аршалынский район | G170: с.о. Турген | H170: с. Красное Озеро | I170: Имеется | K170: на стадии подготовки | M170: на стадии подготовки | O170: на стадии подготовки | Q170: на стадии подготовки | S170: =(J170*'"Вес" ПИР'!$B$13+L170*'"Вес" ПИР'!$B$14+N170*'"Вес" ПИР'!$B$15+P170*'"Вес" ПИР'!$B$16+R170*'"Вес" ПИР'!$B$17)/100 -> 0 | T170: 01.12.2025-30.03.2026 | V170: 01.12.2025-30.03.2026 | X170: =(U170*'"Вес" ПИР'!$B$22+W170*'"Вес" ПИР'!$B$23)/100 -> 0 | AG170: =(Z170*'"Вес" ПИР'!$B$28+AB170*'"Вес" ПИР'!$B$29+AD170*'"Вес" ПИР'!$B$30+AF170*'"Вес" ПИР'!$B$31)/100 -> 0 | AJ170: на стадии подготовки | AP170: на стадии подготовки | AR170: на стадии подготовки | AT170: на стадии подготовки | BB170: =(AI170*'"Вес" ПИР'!$B$36+AK170*'"Вес" ПИР'!$B$37+AM170*'"Вес" ПИР'!$B$38+AO170*'"Вес" ПИР'!$B$39+AQ170*'"Вес" ПИР'!$B$40+AS170*'"Вес" ПИР'!$B$41+AU170*'"Вес" ПИР'!$B$42+AW170*'"Вес" ПИР'!$B$43+AY170*'"Вес" ПИР'!$B$44+BA170*'"Вес" ПИР'!$B$45)/100 -> 0 | BC170: на стадии подготовки | BE170: на стадии подготовки | BG170: =(BD170*'"Вес" ПИР'!$B$50+BF170*'"Вес" ПИР'!$B$51)/100 -> 0 | BI170: 0 | BK170: 46266 | BL170: =(S170*'"Вес" ПИР'!$B$3+X170*'"Вес" ПИР'!$B$4+AG170*'"Вес" ПИР'!$B$5+BB170*'"Вес" ПИР'!$B$6+BG170*'"Вес" ПИР'!$B$7+BI170*'"Вес" ПИР'!$B$8)/100 -> 0
B171: 2026 | C171: ТОО "5А Engineering" | D171: 114035300 | E171: Акмолинская область | F171: Буландынский район | G171: Алтындынский с.о. | H171: с. Боярка | I171: Имеется | K171: на стадии подготовки | M171: на стадии подготовки | O171: на стадии подготовки | Q171: на стадии подготовки | S171: =(J171*'"Вес" ПИР'!$B$13+L171*'"Вес" ПИР'!$B$14+N171*'"Вес" ПИР'!$B$15+P171*'"Вес" ПИР'!$B$16+R171*'"Вес" ПИР'!$B$17)/100 -> 0 | T171: Готово | V171: Готово | X171: =(U171*'"Вес" ПИР'!$B$22+W171*'"Вес" ПИР'!$B$23)/100 -> 0 | AG171: =(Z171*'"Вес" ПИР'!$B$28+AB171*'"Вес" ПИР'!$B$29+AD171*'"Вес" ПИР'!$B$30+AF171*'"Вес" ПИР'!$B$31)/100 -> 0 | AJ171: на стадии подготовки | AP171: на стадии подготовки | AR171: на стадии подготовки | AT171: на стадии подготовки | BB171: =(AI171*'"Вес" ПИР'!$B$36+AK171*'"Вес" ПИР'!$B$37+AM171*'"Вес" ПИР'!$B$38+AO171*'"Вес" ПИР'!$B$39+AQ171*'"Вес" ПИР'!$B$40+AS171*'"Вес" ПИР'!$B$41+AU171*'"Вес" ПИР'!$B$42+AW171*'"Вес" ПИР'!$B$43+AY171*'"Вес" ПИР'!$B$44+BA171*'"Вес" ПИР'!$B$45)/100 -> 0 | BC171: на стадии подготовки | BE171: на стадии подготовки | BG171: =(BD171*'"Вес" ПИР'!$B$50+BF171*'"Вес" ПИР'!$B$51)/100 -> 0 | BI171: 0 | BK171: 46218 | BL171: =(S171*'"Вес" ПИР'!$B$3+X171*'"Вес" ПИР'!$B$4+AG171*'"Вес" ПИР'!$B$5+BB171*'"Вес" ПИР'!$B$6+BG171*'"Вес" ПИР'!$B$7+BI171*'"Вес" ПИР'!$B$8)/100 -> 0
B172: 2026 | C172: ТОО "5А Engineering" | D172: 114037400 | E172: Акмолинская область | F172: Буландынский район | G172: Ергольский с.о. | H172: с. Новокиевка | I172: Имеется | K172: на стадии подготовки | M172: на стадии подготовки | O172: на стадии подготовки | Q172: на стадии подготовки | S172: =(J172*'"Вес" ПИР'!$B$13+L172*'"Вес" ПИР'!$B$14+N172*'"Вес" ПИР'!$B$15+P172*'"Вес" ПИР'!$B$16+R172*'"Вес" ПИР'!$B$17)/100 -> 0 | T172: Готово | V172: Готово | X172: =(U172*'"Вес" ПИР'!$B$22+W172*'"Вес" ПИР'!$B$23)/100 -> 0 | AG172: =(Z172*'"Вес" ПИР'!$B$28+AB172*'"Вес" ПИР'!$B$29+AD172*'"Вес" ПИР'!$B$30+AF172*'"Вес" ПИР'!$B$31)/100 -> 0 | AJ172: на стадии подготовки | AP172: на стадии подготовки | AR172: на стадии подготовки | AT172: на стадии подготовки | BB172: =(AI172*'"Вес" ПИР'!$B$36+AK172*'"Вес" ПИР'!$B$37+AM172*'"Вес" ПИР'!$B$38+AO172*'"Вес" ПИР'!$B$39+AQ172*'"Вес" ПИР'!$B$40+AS172*'"Вес" ПИР'!$B$41+AU172*'"Вес" ПИР'!$B$42+AW172*'"Вес" ПИР'!$B$43+AY172*'"Вес" ПИР'!$B$44+BA172*'"Вес" ПИР'!$B$45)/100 -> 0 | BC172: на стадии подготовки | BE172: на стадии подготовки | BG172: =(BD172*'"Вес" ПИР'!$B$50+BF172*'"Вес" ПИР'!$B$51)/100 -> 0 | BI172: 0 | BK172: 46218 | BL172: =(S172*'"Вес" ПИР'!$B$3+X172*'"Вес" ПИР'!$B$4+AG172*'"Вес" ПИР'!$B$5+BB172*'"Вес" ПИР'!$B$6+BG172*'"Вес" ПИР'!$B$7+BI172*'"Вес" ПИР'!$B$8)/100 -> 0
B173: 2026 | C173: ТОО "5А Engineering" | D173: 114637400 | E173: Акмолинская область | F173: Ерейментауский район | G173: с.о. Олжабай батыра | H173: с.Ынтымак | I173: Имеется | K173: на стадии подготовки | M173: на стадии подготовки | O173: на стадии подготовки | Q173: на стадии подготовки | S173: =(J173*'"Вес" ПИР'!$B$13+L173*'"Вес" ПИР'!$B$14+N173*'"Вес" ПИР'!$B$15+P173*'"Вес" ПИР'!$B$16+R173*'"Вес" ПИР'!$B$17)/100 -> 0 | T173: Готово | V173: Готово | X173: =(U173*'"Вес" ПИР'!$B$22+W173*'"Вес" ПИР'!$B$23)/100 -> 0 | AG173: =(Z173*'"Вес" ПИР'!$B$28+AB173*'"Вес" ПИР'!$B$29+AD173*'"Вес" ПИР'!$B$30+AF173*'"Вес" ПИР'!$B$31)/100 -> 0 | AJ173: на стадии подготовки | AP173: на стадии подготовки | AR173: на стадии подготовки | AT173: на стадии подготовки | BB173: =(AI173*'"Вес" ПИР'!$B$36+AK173*'"Вес" ПИР'!$B$37+AM173*'"Вес" ПИР'!$B$38+AO173*'"Вес" ПИР'!$B$39+AQ173*'"Вес" ПИР'!$B$40+AS173*'"Вес" ПИР'!$B$41+AU173*'"Вес" ПИР'!$B$42+AW173*'"Вес" ПИР'!$B$43+AY173*'"Вес" ПИР'!$B$44+BA173*'"Вес" ПИР'!$B$45)/100 -> 0 | BC173: на стадии подготовки | BE173: на стадии подготовки | BG173: =(BD173*'"Вес" ПИР'!$B$50+BF173*'"Вес" ПИР'!$B$51)/100 -> 0 | BI173: 0 | BK173: 46218 | BL173: =(S173*'"Вес" ПИР'!$B$3+X173*'"Вес" ПИР'!$B$4+AG173*'"Вес" ПИР'!$B$5+BB173*'"Вес" ПИР'!$B$6+BG173*'"Вес" ПИР'!$B$7+BI173*'"Вес" ПИР'!$B$8)/100 -> 0
B174: 2026 | C174: ТОО "5А Engineering" | D174: 115673400 | E174: Акмолинская область | F174: Зерендинский район | G174: с.о. им. Сакена Сейфулина | H174: с. Караозек | I174: Имеется | K174: на стадии подготовки | M174: на стадии подготовки | O174: на стадии подготовки | Q174: на стадии подготовки | S174: =(J174*'"Вес" ПИР'!$B$13+L174*'"Вес" ПИР'!$B$14+N174*'"Вес" ПИР'!$B$15+P174*'"Вес" ПИР'!$B$16+R174*'"Вес" ПИР'!$B$17)/100 -> 0 | T174: 01.12.2025-30.03.2026 | V174: 01.12.2025-30.03.2026 | X174: =(U174*'"Вес" ПИР'!$B$22+W174*'"Вес" ПИР'!$B$23)/100 -> 0 | AG174: =(Z174*'"Вес" ПИР'!$B$28+AB174*'"Вес" ПИР'!$B$29+AD174*'"Вес" ПИР'!$B$30+AF174*'"Вес" ПИР'!$B$31)/100 -> 0 | AJ174: на стадии подготовки | AP174: на стадии подготовки | AR174: на стадии подготовки | AT174: на стадии подготовки | BB174: =(AI174*'"Вес" ПИР'!$B$36+AK174*'"Вес" ПИР'!$B$37+AM174*'"Вес" ПИР'!$B$38+AO174*'"Вес" ПИР'!$B$39+AQ174*'"Вес" ПИР'!$B$40+AS174*'"Вес" ПИР'!$B$41+AU174*'"Вес" ПИР'!$B$42+AW174*'"Вес" ПИР'!$B$43+AY174*'"Вес" ПИР'!$B$44+BA174*'"Вес" ПИР'!$B$45)/100 -> 0 | BC174: на стадии подготовки | BE174: на стадии подготовки | BG174: =(BD174*'"Вес" ПИР'!$B$50+BF174*'"Вес" ПИР'!$B$51)/100 -> 0 | BI174: 0 | BK174: 46266 | BL174: =(S174*'"Вес" ПИР'!$B$3+X174*'"Вес" ПИР'!$B$4+AG174*'"Вес" ПИР'!$B$5+BB174*'"Вес" ПИР'!$B$6+BG174*'"Вес" ПИР'!$B$7+BI174*'"Вес" ПИР'!$B$8)/100 -> 0
B175: 2026 | D175: 111847100 | E175: Акмолинская область | F175: Степногорск г.а. | G175: Богенбайский с.о. | H175: с. Байконыс | I175: Имеется | K175: на стадии подготовки | M175: на стадии подготовки | O175: на стадии подготовки | Q175: на стадии подготовки | S175: =(J175*'"Вес" ПИР'!$B$13+L175*'"Вес" ПИР'!$B$14+N175*'"Вес" ПИР'!$B$15+P175*'"Вес" ПИР'!$B$16+R175*'"Вес" ПИР'!$B$17)/100 -> 0 | T175: Готово | V175: Готово | X175: =(U175*'"Вес" ПИР'!$B$22+W175*'"Вес" ПИР'!$B$23)/100 -> 0 | AG175: =(Z175*'"Вес" ПИР'!$B$28+AB175*'"Вес" ПИР'!$B$29+AD175*'"Вес" ПИР'!$B$30+AF175*'"Вес" ПИР'!$B$31)/100 -> 0 | AJ175: на стадии подготовки | AP175: на стадии подготовки | AR175: на стадии подготовки | AT175: на стадии подготовки | BB175: =(AI175*'"Вес" ПИР'!$B$36+AK175*'"Вес" ПИР'!$B$37+AM175*'"Вес" ПИР'!$B$38+AO175*'"Вес" ПИР'!$B$39+AQ175*'"Вес" ПИР'!$B$40+AS175*'"Вес" ПИР'!$B$41+AU175*'"Вес" ПИР'!$B$42+AW175*'"Вес" ПИР'!$B$43+AY175*'"Вес" ПИР'!$B$44+BA175*'"Вес" ПИР'!$B$45)/100 -> 0 | BC175: на стадии подготовки | BE175: на стадии подготовки | BG175: =(BD175*'"Вес" ПИР'!$B$50+BF175*'"Вес" ПИР'!$B$51)/100 -> 0 | BI175: 0 | BK175: 46218 | BL175: =(S175*'"Вес" ПИР'!$B$3+X175*'"Вес" ПИР'!$B$4+AG175*'"Вес" ПИР'!$B$5+BB175*'"Вес" ПИР'!$B$6+BG175*'"Вес" ПИР'!$B$7+BI175*'"Вес" ПИР'!$B$8)/100 -> 0
...

Sheet СМР
A1: Номер заказа | B1: КАТО | C1: Область | D1: Район | E1: Сельский округ | F1: СНП | G1: Предоставление ГПР (наличие) | H1: Уведомление о начале строительно-монтажных работ | I1: Мобилизация подрядчика (дата) | J1: Дата начала СМР | K1: Дата завершения СМР | L1: % выполнения СМР | M1: Устранение замечаний технадзора (наличие) | N1: Авторский надзор (план график и журнал авторского надзора) | O1: Исполнительная документация (% предоставления) | P1: Плановая дата завершения | Q1: Фактическая готовность (%) | R1: Письменное подтверждение ГАСКа и НПЦзем | S1: Декларация о соответствии | T1: Акт ввода в эксплуатацию | U1: Счет-фактура на выполненные работы; | V1: Справки стоимости выполненных работ и затрат формы КС-3; | W1: Актов выполненных работ формы 2В; | X1: Объемная справка о выполненных работах и расходе материалов; | Y1: Счет-фактура на материалы Подрядчика (не включенные в справочные нормативы, для подтверждения фактических затрат Подрядчика); | Z1: Сертификаты CT-KZ на материалы (при наличии); | AA1: Протокол об изменениях в проекте (при необходимости); | AB1: Корретировка ЗУП (при необходимости) | AC1: Корретировка ПСД (при необходимости) | AD1: Технический Акт приемки выполненных работ. | AE1: Заключения Комиссии о готовности к приемке построенного объекта;
M2: 5 замечаний: 3 устранено

Sheet ИТД
A1: - Справки от землепользователей и органов управления земельными ресурсами об отсутствии претензий после окончания строительства; | B1: - Справка о принятии на учет трассы ВОЛС от АИС ГЗК Республики Казахстан или отделами; | C1: - Перечень внесённых в проект изменений, отступлений от проектных решений и согласований к ним; | D1: - Откорректированные после прокладки и монтажа кабеля рабочие чертежи проектной документации; | E1: - Паспорт трассы; | F1: - Укладочная схема-ведомость; | G1: - Картограмма глубины залегания кабеля и сигнально-предупредительной ленты; | H1: - Профиль перехода через водные и другие преграды, выполненные методом ГНБ; | I1: - Акт освидетельствования скрытых работ; | J1: - Протокол входного контроля строительной длины ВОК; | K1: - Протокол монтажа муфт; | L1: - Протокол измерения затухания на сварочных соединениях ОВ; | M1: - Протокол монтажа оптического КРОССа; | N1: - Схема распределения волокон на участке; | O1: - Схема заземления бронепокровов ВОК в шахте ОП; | P1: - Протокол измерения длины ОВ в нарастающем порядке; | Q1: - Рефлектограммы измерения волокон на участке; | R1: - Заводские паспорта строительных длин ВОК; | S1: Заводские паспорта и сертификаты на материалы и оборудование

Sheet "Вес" ПИР
A1: Вес внутри ПИР
A2: Вид работ | B2: Вес, % | C2: Примечание
A3: Получение исходно-разрешительных документов | B3: 7.5 | C3: Акт выбора трассы, АПЗ, ТУ на подключение к сетям телекоммуникаций, постановление на проведение ПИР, ТУ на пересечение, и т.п.
A4: Инженерные изыскания | B4: 15 | C4: Инженерно-геодезические и инженерно-геологические изыскания
A5: Проектирование | B5: 37.5 | C5: Разработка рабочих чертежей, сметной документации, экологической части проекта, проекта организации строительства
A6: Согласование проекта | B6: 10 | C6: Согласование проекта с заинтересованными госорганами и организациями, экологической части проекта, историко-культурная экспертиза (археологическая экспертиза), согласование с заказчиком
A7: Землеустроительный проект | B7: 15 | C7: Получение отвода земельных участков под ВОЛС, выполнение землеустроительного проекта, узаконение отведенных земельных участков и внесение их в базы госкадастра
A8: Экспертиза проекта | B8: 15 | C8: Комплексная вневедомственная экспертиза проекта
A9: Итого | B9: =SUM(B3:B8) -> 100
A11: Исходно-разрешительные документы
A12: Вид работ | B12: Вес, % | C12: Примечание
A13: ='ПИР-ПСД'!I2 -> Акт выбора трасс | B13: 5 | C13: Низкий вес, т.к. эти документы должен предоставить Заказчик
A14: ='ПИР-ПСД'!K2 -> АПЗ | B14: 30
A15: ='ПИР-ПСД'!M2 -> Технические условия на подключение | B15: 5 | C15: Низкий вес, т.к. эти документы должен предоставить Заказчик
A16: ='ПИР-ПСД'!O2 -> Постановление о разрешении на ПИР | B16: 30
A17: ='ПИР-ПСД'!Q2 -> Технические условия на пересечение | B17: 30
A18: Итого | B18: =SUM(B13:B17) -> 100
A20: Инженерные изыскания
A21: Вид работ | B21: Вес, % | C21: Примечание
A22: ='ПИР-ПСД'!T2 -> Инженерно геологические изыскания | B22: 25
A23: ='ПИР-ПСД'!V2 -> Инженерно-геодезические изыскания | B23: 75
A24: Итого | B24: =SUM(B22:B23) -> 100
A26: Проектирование
A27: Вид работ | B27: Вес, % | C27: Примечание
A28: ='ПИР-ПСД'!Y2 -> Рабочие чертежи | B28: 75
A29: ='ПИР-ПСД'!AA2 -> Сметная документация | B29: 15
A30: ='ПИР-ПСД'!AC2 -> Проект организации строительства | B30: 2.5
A31: ='ПИР-ПСД'!AE2 -> Экологическая часть проекта | B31: 7.5
A32: Итого | B32: =SUM(B28:B31) -> 100
A34: Согласования
A35: Вид работ | B35: Вес, % | C35: Примечание
A36: ='ПИР-ПСД'!AH2 -> Заключение историко-культурной экспертизы | B36: 15
A37: ='ПИР-ПСД'!AJ2 -> Письмо об отсутствии сибиреязвенных захоронений и скотомогильников | B37: 2.5
A38: ='ПИР-ПСД'!AL2 -> Протокол дозиметрического контроля | B38: 2.5
A39: ='ПИР-ПСД'!AN2 -> Протокол измерений содержания радона и продуктов его распада в воздухе | B39: 2.5
A40: ='ПИР-ПСД'!AP2 -> Согласование трассы ВОЛС с соответствующей Бассейновой водохозяйственной инспекцией | B40: 5
A41: ='ПИР-ПСД'!AR2 -> Согласование с АО "Авиационная администрация Казахстана" | B41: 2.5
A42: ='ПИР-ПСД'!AT2 -> Согласование трассы ВОЛС с местным Лесхозом | B42: 2.5
A43: ='ПИР-ПСД'!AV2 -> Согласование с владельцами пересекаемых коммуникаций | B43: 15
A44: ='ПИР-ПСД'!AX2 -> Согласование экологической части проекта | B44: 25
A45: ='ПИР-ПСД'!AZ2 -> Согласование проекта с Заказчиком | B45: 27.5
A46: Итого | B46: =SUM(B36:B45) -> 100
A48: Землеустроительные работы
A49: Вид работ | B49: Вес, % | C49: Примечание
A50: ='ПИР-ПСД'!BC2 -> Землеотвод под ВОЛС (постановление, гос акт. серветут, распоряжение) | B50: 25
A51: ='ПИР-ПСД'!BE2 -> Изготовление землеустроительного проекта | B51: 75
A52: Итого | B52: =SUM(B50:B51) -> 100

Sheet ВОЛС
B2: ОБЩАЯ протяженность ВОЛС | C2: =C3+C4 -> 35437.781
B3: ВОЛС 2026 | C3: =C9+C88+C113+C182+C254+C274+C295+C326+C347+C384+C422+C473+C555+C573+C586+C592+C633+C667+C701+C722+C744+C841+C854+C899+C930+C961+C1009+C1115+C1141+C1195+C1220+C1260+C1271+C1371+C1412+C1486+C1517+C1545+C1566+C1581+C1627+C1644+C1661+C1711+C1726+C1743+C1757+C1805+C1860+C1877+C1900+C1926+C1946+C1981+C2003+C2023+C2116+C2151+C2169+C2179+C2202+C2235+C2250+C2305+C2343+C2388+C2426+C2457+C2496+C2539+C2557+C2576+C2649+C2668+C2706+C2714+C2732+C2748+C2773+C2792 -> 20519.873
B4: ВОЛС 2027 | C4: =C42+C158+C224+C308+C419+C460+C492+C500+C522+C540+C602+C614+C686+C771+C791+C799+C809+C830+C878+C933+C944+C988+C1036+C1046+C1059+C1099+C1129+C1170+C1219+C1310+C1328+C1356+C1388+C1437+C1453+C1467+C1506+C1600+C1678+C1694+C1771+C1784+C1794+C1851+C1915+C1960+C2044+C2068+C2086+C2101+C2136+C2218+C2283+C2322+C2328+C2335+C2365+C2450+C2477+C2521+C2617+C2632+C2654+C2686+C2695+C2761+C2809 -> 14917.908
A5: №п/п | B5: Наименование проекта/Населенный пункт | C5: Ориентировочная протяженность ВОЛС (км) | D5: Год
B6: % выполнения
B7: «Обеспечение высокоскоростным доступом к сети Интернет Республики Казахстан»
A8: 1 | B8: Туркестанская область | C8: =C9+C88+C113+C182+C254+C274+C295+C326+C347 -> 2141.975
A9: 1.1 | B9: Байдибекский район | C9: =SUM(C10:C41) -> 352.17 | D9: 2026
A10: 1.1.1 | B10: с.Алгабас | C10: 12.94 | D10: 2026
A11: 1.1.2 | B11: с.Жана Талап | C11: 17.447 | D11: 2026
A12: 1.1.3 | B12: с.Жулдыз | C12: 4.2 | D12: 2026
A13: 1.1.4 | B13: с.Жолгабас | C13: 10.1 | D13: 2026
A14: 1.1.5 | B14: с.Кенес | C14: 22.509 | D14: 2026
A15: 1.1.6 | B15: с.Туракты | C15: 5.56 | D15: 2026
A16: 1.1.7 | B16: с.Танатар | C16: 9.5 | D16: 2026
A17: 1.1.8 | B17: с.Алмалы | C17: 4.66 | D17: 2026
A18: 1.1.9 | B18: с.Жарыкбас | C18: 12.679 | D18: 2026
A19: 1.1.10 | B19: с.Амансай | C19: 8.7 | D19: 2026
A20: 1.1.11 | B20: Ж.Боролдай | C20: 3.92 | D20: 2026
A21: 1.1.12 | B21: с.Жыланды | C21: 9.1 | D21: 2026
... A41: 1.1.32 | B41: с.Акбулак | C41: 13.56 | D41: 2026
A42: 1.2 | B42: Жетысайский район | C42: =SUM(C43:C87) -> 228.3 | D42: 2027
A43: 1.2.1 | B43: Байтерек (Алимбетов (Жданов) | C43: 6.45 | D43: 2027
A44: 1.2.2 | B44: Жетіқазына (с.Кызыласкер) | C44: 4.2 | D44: 2027
A45: 1.2.3 | B45: с.Жана даур (Целина) | C45: 6.7 | D45: 2027
A46: 1.2.4 | B46: с.Бирлик | C46: 3 | D46: 2027
A47: 1.2.5 | B47: с.Достык | C47: 2.4 | D47: 2027
A48: 1.2.6 | B48: Алпамыс (с.Женис) | C48: 7 | D48: 2027
A49: 1.2.7 | B49: Кемер (с.Кирпичное) | C49: 12.7 | D49: 2027
A50: 1.2.8 | B50: Күрішті (с.Карисауыл) | C50: 5 | D50: 2027
A51: 1.2.9 | B51: Сырабат (с.Ленинабад) | C51: 2.9 | D51: 2027
A52: 1.2.10 | B52: с.Сайлау | C52: 6.2 | D52: 2027
A53: 1.2.11 | B53: Сұлу бұлақ (с.Чкалов) | C53: 4.95 | D53: 2027
A54: 1.2.12 | B54: с.Тын дала | C54: 10.1 | D54: 2027
... A87: 1.2.45 | B87: Ғарышкер (с.Гагарин) | C87: 8.5 | D87: 2027
A88: 1.2 | B88: Казыгуртский район | C88: =SUM(C89:C112) -> 284.67 | D88: 2026
A89: 1.3.1 | B89: с.Аккум | C89: 10.65 | D89: 2026
A90: 1.3.2 | B90: с.Жылыбулак | C90: 14.01 | D90: 2026
A91: 1.3.3 | B91: с.Женис | C91: 6.7 | D91: 2026
A92: 1.3.4 | B92: с.Карабастау | C92: 8.2 | D92: 2026
A93: 1.3.5 | B93: с.Тилектес | C93: 6.36 | D93: 2026
A94: 1.3.6 | B94: с.Кызылбулак | C94: 17.3 | D94: 2026
A95: 1.3.7 | B95: с.Угам | C95: 33 | D95: 2026
A96: 1.3.8 | B96: Заңғар | C96: 7.8 | D96: 2026
A97: 1.3.9 | B97: с. Сырлысай | C97: 6.9 | D97: 2026
A98: 1.3.10 | B98: с.Карабау | C98: 8.7 | D98: 2026
A99: 1.3.11 | B99: с.Тугыртас | C99: 11.9 | D99: 2026
A100: 1.3.12 | B100: с. Атажұрт | C100: 9.7 | D100: 2026
... A112: 1.3.24 | B112: с.Карабау | C112: 5.7 | D112: 2026
A113: 1.3 | B113: Келесский район | C113: =SUM(C114:C157) -> 293.2 | D113: 2026
A114: 1.4.1 | B114: с.Жуантобе | C114: 7.75 | D114: 2026
A115: 1.4.2 | B115: с.Акжар | C115: 7.1 | D115: 2026
A116: 1.4.3 | B116: с.М.Горький (кендала) | C116: 2.5 | D116: 2026
A117: 1.4.4 | B117: с.Когерту | C117: 4.6 | D117: 2026
A118: 1.4.5 | B118: с.Кия жол | C118: 2.9 | D118: 2026
A119: 1.4.6 | B119: с.Куйган | C119: 5.9 | D119: 2026
A120: 1.4.7 | B120: с.Тартогай | C120: 12.6 | D120: 2026
A121: 1.4.8 | B121: с.Тентексай | C121: 6.4 | D121: 2026
A122: 1.4.9 | B122: Дихан (Садовая) | C122: 4.8 | D122: 2026
A123: 1.4.10 | B123: Косоткел Социализм | C123: 2.5 | D123: 2026
A124: 1.4.11 | B124: с.Уш агаш | C124: 5.7 | D124: 2026
A125: 1.4.12 | B125: с.Шырылдак | C125: 4.1 | D125: 2026
... A157: 1.4.44 | B157: с Коммунмзм (с Ащысай) | C157: 8.2 | D157: 2026
A158: 1.5 | B158: Мактааральский район | C158: =SUM(C159:C181) -> 187.87 | D158: 2027
A159: 1.5.1 | B159: с.Водное (Көксу) | C159: 70 | D159: 2027
A160: 1.5.2 | B160: с.Еркинабад | C160: 2.7 | D160: 2027
A161: 1.5.3 | B161: с.Жантаксай | C161: 6.61 | D161: 2027
A162: 1.5.4 | B162: с.Арайлы | C162: 9.1 | D162: 2027
A163: 1.5.5 | B163: с.Нурлы жол | C163: 11.8 | D163: 2027
A164: 1.5.6 | B164: с.Шапагат | C164: 0.55 | D164: 2027
A165: 1.5.7 | B165: с.Азамат | C165: 5.83 | D165: 2027
A166: 1.5.8 | B166: с.Каракыр | C166: 4.35 | D166: 2027
A167: 1.5.9 | B167: Мырзатөбе (с.Макталы) | C167: 12.2 | D167: 2027
A168: 1.5.10 | B168: Өркен (с.Кызыл ту) | C168: 3.75 | D168: 2027
A169: 1.5.11 | B169: с.Ак алтын | C169: 3.2 | D169: 2027
A170: 1.5.12 | B170: с.Амангелды (Альфараби) | C170: 3.6 | D170: 2027
... A181: 1.5.23 | B181: с.Жана турмыс | C181: 3.9 | D181: 2027
A182: 1.4 | B182: Ордабасынский район, Сайрамский район | C182: =SUM(C183:C223) -> 200.165 | D182: 2026
A183: 1.6.1 | B183: с.Боралдай | C183: 8 | D183: 2026
A184: 1.6.2 | B184: с.Кызыл сенгир | C184: 8.2 | D184: 2026
A185: 1.6.3 | B185: с.Карабастау | C185: 6.25 | D185: 2026
A186: 1.6.4 | B186: с.Кемер | C186: 2.73 | D186: 2026
A187: 1.6.5 | B187: с.Бирлик | C187: 4.63 | D187: 2026
A188: 1.6.6 | B188: с.Теспе | C188: 2.28 | D188: 2026
A189: 1.6.7 | B189: с.Ынтымак | C189: 2.21 | D189: 2026
A190: 1.6.8 | B190: с.Дихан | C190: 11.5 | D190: 2026
A191: 1.6.9 | B191: с.Бейсен | C191: 3.22 | D191: 2026
A192: 1.6.10 | B192: с.Акжол | C192: 2.875 | D192: 2026
A193: 1.6.11 | B193: с.Жулдыз | C193: 3 | D193: 2026
A194: 1.6.12 | B194: с.Ынтымак | C194: 3 | D194: 2026
... A223: 1.6.41 | B223: с.Жанатурмыс | C223: 1 | D223: 2026
A224: 1.7 | B224: Отырарский район, Шардаринский район | C224: =SUM(C225:C253) -> 289.47 | D224: 2027
A225: 1.7.1 | B225: с.Самырат (Үштам) | C225: 6 | D225: 2027
A226: 1.7.2 | B226: с.Аккол | C226: 4 | D226: 2027
A227: 1.7.3 | B227: с.Колкудук | C227: 4.37 | D227: 2027
A228: 1.7.4 | B228: с.Каргалы | C228: 11.7 | D228: 2027
A229: 1.7.5 | B229: с.Жанкел | C229: 18.5 | D229: 2027
A230: 1.7.6 | B230: с.Шенгельды | C230: 5.2 | D230: 2027
A231: 1.7.7 | B231: с.Ызакол | C231: 7.6 | D231: 2027
A232: 1.7.8 | B232: Бесторанғыл | C232: 4.7 | D232: 2027
...
